Workbook

Sheet Tech Graph
A1: Date | B1: Intellectualists | C1: Clerks | D1: Literacy | E1: Status | F1: Base Research Points | G1: Plurality | H1: Tech Modifier | I1: Total Research Points | J1: Yearly Research Points | K1: New Costs | L1: Date | M1: Leftover Tech Cost
A2: 1830 | B2: 0.0098 | C2: 0.0041 | D2: 0.1 | E2: Great Power | F2: =(MIN(B2,0.02)*150)+(MIN(C2,0.04)*50)+(MIN(D2,1)*4)+(IF(E2="Great Power",1.5,IF(E2="Secondary Power",1.25,IF(E2="Westernized Nation",1,0)))) -> 3.575 | G2: 0.3 | H2: 0 | I2: =F2*(1+H2+G2) -> 4.6475 | J2: =I2*365 -> 1696.3375 | K2: 244800 | L2: 1830 | M2: =MAX(K2-J2,0) -> 243103.66
A3: 1831 | B3: 0.01 | C3: 0.0043 | D3: 0.10171429 | E3: Great Power | F3: =(MIN(B3,0.02)*150)+(MIN(C3,0.04)*50)+(MIN(D3,1)*4)+(IF(E3="Great Power",1.5,IF(E3="Secondary Power",1.25,IF(E3="Westernized Nation",1,0)))) -> 3.6218571 | G3: =MIN(G2+(4*2/90/100*12),1) -> 0.31066667 | H3: 0 | I3: =F3*(1+H3+G3) -> 4.7470474 | J3: =I3*365 -> 1732.6723 | L3: 1831 | M3: =MAX((M2+K3-J3)*0.994,0) -> 239922.76
A4: 1832 | B4: 0.0108 | C4: 0.0045 | D4: 0.1036 | E4: Great Power | F4: =(MIN(B4,0.02)*150)+(MIN(C4,0.04)*50)+(MIN(D4,1)*4)+(IF(E4="Great Power",1.5,IF(E4="Secondary Power",1.25,IF(E4="Westernized Nation",1,0)))) -> 3.7594 | G4: =MIN(G3+(4*2/90/100*12),1) -> 0.32133333 | H4: 0 | I4: =F4*(1+H4+G4) -> 4.9674205 | J4: =I4*365 -> 1813.1085 | L4: 1832 | M4: =MAX((M3+K4-J4)*0.994,0) -> 236681
A5: 1833 | B5: 0.0116 | C5: 0.0047 | D5: 0.10565714 | E5: Great Power | F5: =(MIN(B5,0.02)*150)+(MIN(C5,0.04)*50)+(MIN(D5,1)*4)+(IF(E5="Great Power",1.5,IF(E5="Secondary Power",1.25,IF(E5="Westernized Nation",1,0)))) -> 3.8976286 | G5: =MIN(G4+(4*2/90/100*12),1) -> 0.332 | H5: 0 | I5: =F5*(1+H5+G5) -> 5.1916413 | J5: =I5*365 -> 1894.9491 | L5: 1833 | M5: =MAX((M4+K5-J5)*0.994,0) -> 233377.33
A6: 1834 | B6: 0.0124 | C6: 0.0049 | D6: 0.10788571 | E6: Great Power | F6: =(MIN(B6,0.02)*150)+(MIN(C6,0.04)*50)+(MIN(D6,1)*4)+(IF(E6="Great Power",1.5,IF(E6="Secondary Power",1.25,IF(E6="Westernized Nation",1,0)))) -> 4.0365429 | G6: =MIN(G5+(4*2/90/100*12),1) -> 0.34266667 | H6: 0 | I6: =F6*(1+H6+G6) -> 5.4197315 | J6: =I6*365 -> 1978.202 | L6: 1834 | M6: =MAX((M5+K6-J6)*0.994,0) -> 230010.74
A7: 1835 | B7: 0.0132 | C7: 0.0051 | D7: 0.11028571 | E7: Great Power | F7: =(MIN(B7,0.02)*150)+(MIN(C7,0.04)*50)+(MIN(D7,1)*4)+(IF(E7="Great Power",1.5,IF(E7="Secondary Power",1.25,IF(E7="Westernized Nation",1,0)))) -> 4.1761429 | G7: =MIN(G6+(4*2/90/100*12),1) -> 0.35333333 | H7: 0 | I7: =F7*(1+H7+G7) -> 5.6517133 | J7: =I7*365 -> 2062.8754 | L7: 1835 | M7: =MAX((M6+K7-J7)*0.994,0) -> 226580.17
A8: 1836 | B8: 0.014 | C8: 0.0053 | D8: 0.11285714 | E8: Great Power | F8: =(MIN(B8,0.02)*150)+(MIN(C8,0.04)*50)+(MIN(D8,1)*4)+(IF(E8="Great Power",1.5,IF(E8="Secondary Power",1.25,IF(E8="Westernized Nation",1,0)))) -> 4.3164286 | G8: =MIN(G7+(4*2/90/100*12),1) -> 0.364 | H8: 0 | I8: =F8*(1+H8+G8) -> 5.8876086 | J8: =I8*365 -> 2148.9771 | L8: 1836 | M8: =MAX((M7+K8-J8)*0.994,0) -> 223084.61
A9: 1837 | B9: 0.0148 | C9: 0.0055 | D9: 0.1156 | E9: Great Power | F9: =(MIN(B9,0.02)*150)+(MIN(C9,0.04)*50)+(MIN(D9,1)*4)+(IF(E9="Great Power",1.5,IF(E9="Secondary Power",1.25,IF(E9="Westernized Nation",1,0)))) -> 4.4574 | G9: =MIN(G8+(4*2/90/100*12),1) -> 0.37466667 | H9: 0 | I9: =F9*(1+H9+G9) -> 6.1274392 | J9: =I9*365 -> 2236.5153 | L9: 1837 | M9: =MAX((M8+K9-J9)*0.994,0) -> 219523
A10: 1838 | B10: 0.0156 | C10: 0.0057 | D10: 0.11851429 | E10: Great Power | F10: =(MIN(B10,0.02)*150)+(MIN(C10,0.04)*50)+(MIN(D10,1)*4)+(IF(E10="Great Power",1.5,IF(E10="Secondary Power",1.25,IF(E10="Westernized Nation",1,0)))) -> 4.5990571 | G10: =MIN(G9+(4*2/90/100*12),1) -> 0.38533333 | H10: 0 | I10: =F10*(1+H10+G10) -> 6.3712272 | J10: =I10*365 -> 2325.4979 | L10: 1838 | M10: =MAX((M9+K10-J10)*0.994,0) -> 215894.32
A11: 1839 | B11: 0.0164 | C11: 0.0059 | D11: 0.1216 | E11: Great Power | F11: =(MIN(B11,0.02)*150)+(MIN(C11,0.04)*50)+(MIN(D11,1)*4)+(IF(E11="Great Power",1.5,IF(E11="Secondary Power",1.25,IF(E11="Westernized Nation",1,0)))) -> 4.7414 | G11: =MIN(G10+(4*2/90/100*12),1) -> 0.396 | H11: 0 | I11: =F11*(1+H11+G11) -> 6.6189944 | J11: =I11*365 -> 2415.933 | L11: 1839 | M11: =MAX((M10+K11-J11)*0.994,0) -> 212197.52
A12: 1840 | B12: 0.0172 | C12: 0.0061 | D12: 0.12485714 | E12: Great Power | F12: =(MIN(B12,0.02)*150)+(MIN(C12,0.04)*50)+(MIN(D12,1)*4)+(IF(E12="Great Power",1.5,IF(E12="Secondary Power",1.25,IF(E12="Westernized Nation",1,0)))) -> 4.8844286 | G12: =MIN(G11+(4*2/90/100*12),1) -> 0.40666667 | H12: 0.5 | I12: =F12*(1+H12+G12) -> 9.3129771 | J12: =I12*365 -> 3399.2367 | K12: 32400 | L12: 1840 | M12: =MAX((M11+K12-J12)*0.994,0) -> 239751.09
A13: 1841 | B13: 0.018 | C13: 0.0063 | D13: 0.12828571 | E13: Great Power | F13: =(MIN(B13,0.02)*150)+(MIN(C13,0.04)*50)+(MIN(D13,1)*4)+(IF(E13="Great Power",1.5,IF(E13="Secondary Power",1.25,IF(E13="Westernized Nation",1,0)))) -> 5.0281429 | G13: =MIN(G12+(4*2/90/100*12),1) -> 0.41733333 | H13: 0.5 | I13: =F13*(1+H13+G13) -> 9.6406259 | J13: =I13*365 -> 3518.8285 | L13: 1841 | M13: =MAX((M12+K13-J13)*0.994,0) -> 234814.87
A14: 1842 | B14: 0.0188 | C14: 0.0065 | D14: 0.13188571 | E14: Great Power | F14: =(MIN(B14,0.02)*150)+(MIN(C14,0.04)*50)+(MIN(D14,1)*4)+(IF(E14="Great Power",1.5,IF(E14="Secondary Power",1.25,IF(E14="Westernized Nation",1,0)))) -> 5.1725429 | G14: =MIN(G13+(4*2/90/100*12),1) -> 0.428 | H14: 0.5 | I14: =F14*(1+H14+G14) -> 9.9726626 | J14: =I14*365 -> 3640.0219 | L14: 1842 | M14: =MAX((M13+K14-J14)*0.994,0) -> 229787.8
A15: 1843 | B15: 0.0196 | C15: 0.0067 | D15: 0.13565714 | E15: Great Power | F15: =(MIN(B15,0.02)*150)+(MIN(C15,0.04)*50)+(MIN(D15,1)*4)+(IF(E15="Great Power",1.5,IF(E15="Secondary Power",1.25,IF(E15="Westernized Nation",1,0)))) -> 5.3176286 | G15: =MIN(G14+(4*2/90/100*12),1) -> 0.43866667 | H15: 1 | I15: =F15*(1+H15+G15) -> 12.967924 | J15: =I15*365 -> 4733.2921 | L15: 1843 | M15: =MAX((M14+K15-J15)*0.994,0) -> 223704.18
A16: 1844 | B16: 0.0204 | C16: 0.0069 | D16: 0.139876 | E16: Great Power | F16: =(MIN(B16,0.02)*150)+(MIN(C16,0.04)*50)+(MIN(D16,1)*4)+(IF(E16="Great Power",1.5,IF(E16="Secondary Power",1.25,IF(E16="Westernized Nation",1,0)))) -> 5.404504 | G16: =MIN(G15+(4*2/90/100*12),1) -> 0.44933333 | H16: 1 | I16: =F16*(1+H16+G16) -> 13.237432 | J16: =I16*365 -> 4831.6626 | L16: 1844 | M16: =MAX((M15+K16-J16)*0.994,0) -> 217559.28
A17: 1845 | B17: 0.0212 | C17: 0.0071 | D17: 0.14468971 | E17: Great Power | F17: =(MIN(B17,0.02)*150)+(MIN(C17,0.04)*50)+(MIN(D17,1)*4)+(IF(E17="Great Power",1.5,IF(E17="Secondary Power",1.25,IF(E17="Westernized Nation",1,0)))) -> 5.4337589 | G17: =MIN(G16+(4*2/90/100*12),1) -> 0.46 | H17: 1 | I17: =F17*(1+H17+G17) -> 13.367047 | J17: =I17*365 -> 4878.9721 | L17: 1845 | M17: =MAX((M16+K17-J17)*0.994,0) -> 211404.23
A18: 1846 | B18: 0.022 | C18: 0.0073 | D18: 0.149704 | E18: Great Power | F18: =(MIN(B18,0.02)*150)+(MIN(C18,0.04)*50)+(MIN(D18,1)*4)+(IF(E18="Great Power",1.5,IF(E18="Secondary Power",1.25,IF(E18="Westernized Nation",1,0)))) -> 5.463816 | G18: =MIN(G17+(4*2/90/100*12),1) -> 0.47066667 | H18: 1 | I18: =F18*(1+H18+G18) -> 13.499268 | J18: =I18*365 -> 4927.2328 | L18: 1846 | M18: =MAX((M17+K18-J18)*0.994,0) -> 205238.13
A19: 1847 | B19: 0.0228 | C19: 0.0075 | D19: 0.15491886 | E19: Great Power | F19: =(MIN(B19,0.02)*150)+(MIN(C19,0.04)*50)+(MIN(D19,1)*4)+(IF(E19="Great Power",1.5,IF(E19="Secondary Power",1.25,IF(E19="Westernized Nation",1,0)))) -> 5.4946754 | G19: =MIN(G18+(4*2/90/100*12),1) -> 0.48133333 | H19: 1 | I19: =F19*(1+H19+G19) -> 13.634121 | J19: =I19*365 -> 4976.4543 | L19: 1847 | M19: =MAX((M18+K19-J19)*0.994,0) -> 199060.11
A20: 1848 | B20: 0.0236 | C20: 0.0077 | D20: 0.16033429 | E20: Great Power | F20: =(MIN(B20,0.02)*150)+(MIN(C20,0.04)*50)+(MIN(D20,1)*4)+(IF(E20="Great Power",1.5,IF(E20="Secondary Power",1.25,IF(E20="Westernized Nation",1,0)))) -> 5.5263371 | G20: =MIN(G19+(4*2/90/100*12),1) -> 0.492 | H20: 1 | I20: =F20*(1+H20+G20) -> 13.771632 | J20: =I20*365 -> 5026.6457 | K20: 10800 | L20: 1848 | M20: =MAX((M19+K20-J20)*0.994,0) -> 203604.46
A21: 1849 | B21: 0.0244 | C21: 0.0079 | D21: 0.16595029 | E21: Great Power | F21: =(MIN(B21,0.02)*150)+(MIN(C21,0.04)*50)+(MIN(D21,1)*4)+(IF(E21="Great Power",1.5,IF(E21="Secondary Power",1.25,IF(E21="Westernized Nation",1,0)))) -> 5.5588011 | G21: =MIN(G20+(4*2/90/100*12),1) -> 0.50266667 | H21: 1 | I21: =F21*(1+H21+G21) -> 13.911826 | J21: =I21*365 -> 5077.8166 | L21: 1849 | M21: =MAX((M20+K21-J21)*0.994,0) -> 197335.49
A22: 1850 | B22: 0.0252 | C22: 0.0081 | D22: 0.17176686 | E22: Great Power | F22: =(MIN(B22,0.02)*150)+(MIN(C22,0.04)*50)+(MIN(D22,1)*4)+(IF(E22="Great Power",1.5,IF(E22="Secondary Power",1.25,IF(E22="Westernized Nation",1,0)))) -> 5.5920674 | G22: =MIN(G21+(4*2/90/100*12),1) -> 0.51333333 | H22: 1 | I22: =F22*(1+H22+G22) -> 14.054729 | J22: =I22*365 -> 5129.9763 | K22: 259200 | L22: 1850 | M22: =MAX((M21+K22-J22)*0.994,0) -> 448697.08
A23: 1851 | B23: 0.026 | C23: 0.0083 | D23: 0.177784 | E23: Great Power | F23: =(MIN(B23,0.02)*150)+(MIN(C23,0.04)*50)+(MIN(D23,1)*4)+(IF(E23="Great Power",1.5,IF(E23="Secondary Power",1.25,IF(E23="Westernized Nation",1,0)))) -> 5.626136 | G23: =MIN(G22+(4*2/90/100*12),1) -> 0.524 | H23: 1 | I23: =F23*(1+H23+G23) -> 14.200367 | J23: =I23*365 -> 5183.1341 | L23: 1851 | M23: =MAX((M22+K23-J23)*0.994,0) -> 440852.86
A24: 1852 | B24: 0.0268 | C24: 0.0085 | D24: 0.18453314 | E24: Great Power | F24: =(MIN(B24,0.02)*150)+(MIN(C24,0.04)*50)+(MIN(D24,1)*4)+(IF(E24="Great Power",1.5,IF(E24="Secondary Power",1.25,IF(E24="Westernized Nation",1,0)))) -> 5.6631326 | G24: =MIN(G23+(4*2/90/100*12),1) -> 0.53466667 | H24: 1 | I24: =F24*(1+H24+G24) -> 14.354153 | J24: =I24*365 -> 5239.266 | L24: 1852 | M24: =MAX((M23+K24-J24)*0.994,0) -> 432999.91
A25: 1853 | B25: 0.0276 | C25: 0.0087 | D25: 0.1915 | E25: Great Power | F25: =(MIN(B25,0.02)*150)+(MIN(C25,0.04)*50)+(MIN(D25,1)*4)+(IF(E25="Great Power",1.5,IF(E25="Secondary Power",1.25,IF(E25="Westernized Nation",1,0)))) -> 5.701 | G25: =MIN(G24+(4*2/90/100*12),1) -> 0.54533333 | H25: 1 | I25: =F25*(1+H25+G25) -> 14.510945 | J25: =I25*365 -> 5296.495 | L25: 1853 | M25: =MAX((M24+K25-J25)*0.994,0) -> 425137.2
A26: 1854 | B26: 0.0284 | C26: 0.0089 | D26: 0.19925029 | E26: Great Power | F26: =(MIN(B26,0.02)*150)+(MIN(C26,0.04)*50)+(MIN(D26,1)*4)+(IF(E26="Great Power",1.5,IF(E26="Secondary Power",1.25,IF(E26="Westernized Nation",1,0)))) -> 5.7420011 | G26: =MIN(G25+(4*2/90/100*12),1) -> 0.556 | H26: 1 | I26: =F26*(1+H26+G26) -> 14.676555 | J26: =I26*365 -> 5356.9425 | L26: 1854 | M26: =MAX((M25+K26-J26)*0.994,0) -> 417261.57
A27: 1855 | B27: 0.0292 | C27: 0.0091 | D27: 0.20723543 | E27: Great Power | F27: =(MIN(B27,0.02)*150)+(MIN(C27,0.04)*50)+(MIN(D27,1)*4)+(IF(E27="Great Power",1.5,IF(E27="Secondary Power",1.25,IF(E27="Westernized Nation",1,0)))) -> 5.7839417 | G27: =MIN(G26+(4*2/90/100*12),1) -> 0.56666667 | H27: 1 | I27: =F27*(1+H27+G27) -> 14.84545 | J27: =I27*365 -> 5418.5894 | K27: 21600 | L27: 1855 | M27: =MAX((M26+K27-J27)*0.994,0) -> 430842.32
A28: 1856 | B28: 0.03 | C28: 0.0093 | D28: 0.21575543 | E28: Great Power | F28: =(MIN(B28,0.02)*150)+(MIN(C28,0.04)*50)+(MIN(D28,1)*4)+(IF(E28="Great Power",1.5,IF(E28="Secondary Power",1.25,IF(E28="Westernized Nation",1,0)))) -> 5.8280217 | G28: =MIN(G27+(4*2/90/100*12),1) -> 0.57733333 | H28: 1 | I28: =F28*(1+H28+G28) -> 15.020755 | J28: =I28*365 -> 5482.5754 | L28: 1856 | M28: =MAX((M27+K28-J28)*0.994,0) -> 422807.59
A29: 1857 | B29: 0.0308 | C29: 0.0095 | D29: 0.22637029 | E29: Great Power | F29: =(MIN(B29,0.02)*150)+(MIN(C29,0.04)*50)+(MIN(D29,1)*4)+(IF(E29="Great Power",1.5,IF(E29="Secondary Power",1.25,IF(E29="Westernized Nation",1,0)))) -> 5.8804811 | G29: =MIN(G28+(4*2/90/100*12),1) -> 0.588 | H29: 1 | I29: =F29*(1+H29+G29) -> 15.218685 | J29: =I29*365 -> 5554.8201 | L29: 1857 | M29: =MAX((M28+K29-J29)*0.994,0) -> 414749.25
A30: 1858 | B30: 0.0316 | C30: 0.0097 | D30: 0.23728 | E30: Great Power | F30: =(MIN(B30,0.02)*150)+(MIN(C30,0.04)*50)+(MIN(D30,1)*4)+(IF(E30="Great Power",1.5,IF(E30="Secondary Power",1.25,IF(E30="Westernized Nation",1,0)))) -> 5.93412 | G30: =MIN(G29+(4*2/90/100*12),1) -> 0.59866667 | H30: 1 | I30: =F30*(1+H30+G30) -> 15.4208 | J30: =I30*365 -> 5628.5919 | L30: 1858 | M30: =MAX((M29+K30-J30)*0.994,0) -> 406665.94
A31: 1859 | B31: 0.0324 | C31: 0.0099 | D31: 0.24848457 | E31: Great Power | F31: =(MIN(B31,0.02)*150)+(MIN(C31,0.04)*50)+(MIN(D31,1)*4)+(IF(E31="Great Power",1.5,IF(E31="Secondary Power",1.25,IF(E31="Westernized Nation",1,0)))) -> 5.9889383 | G31: =MIN(G30+(4*2/90/100*12),1) -> 0.60933333 | H31: 1 | I31: =F31*(1+H31+G31) -> 15.627136 | J31: =I31*365 -> 5703.9047 | L31: 1859 | M31: =MAX((M30+K31-J31)*0.994,0) -> 398556.26
A32: 1860 | B32: 0.0332 | C32: 0.0101 | D32: 0.259984 | E32: Great Power | F32: =(MIN(B32,0.02)*150)+(MIN(C32,0.04)*50)+(MIN(D32,1)*4)+(IF(E32="Great Power",1.5,IF(E32="Secondary Power",1.25,IF(E32="Westernized Nation",1,0)))) -> 6.044936 | G32: =MIN(G31+(4*2/90/100*12),1) -> 0.62 | H32: 1 | I32: =F32*(1+H32+G32) -> 15.837732 | J32: =I32*365 -> 5780.7723 | K32: 10800 | L32: 1860 | M32: =MAX((M31+K32-J32)*0.994,0) -> 401154.04
A33: 1861 | B33: 0.034 | C33: 0.0103 | D33: 0.27177829 | E33: Great Power | F33: =(MIN(B33,0.02)*150)+(MIN(C33,0.04)*50)+(MIN(D33,1)*4)+(IF(E33="Great Power",1.5,IF(E33="Secondary Power",1.25,IF(E33="Westernized Nation",1,0)))) -> 6.1021131 | G33: =MIN(G32+(4*2/90/100*12),1) -> 0.63066667 | H33: 1.5 | I33: =F33*(1+H33+G33) -> 19.103682 | J33: =I33*365 -> 6972.844 | L33: 1861 | M33: =MAX((M32+K33-J33)*0.994,0) -> 391816.11
A34: 1862 | B34: 0.0348 | C34: 0.0105 | D34: 0.28386743 | E34: Great Power | F34: =(MIN(B34,0.02)*150)+(MIN(C34,0.04)*50)+(MIN(D34,1)*4)+(IF(E34="Great Power",1.5,IF(E34="Secondary Power",1.25,IF(E34="Westernized Nation",1,0)))) -> 6.1604697 | G34: =MIN(G33+(4*2/90/100*12),1) -> 0.64133333 | H34: 1.5 | I34: =F34*(1+H34+G34) -> 19.352089 | J34: =I34*365 -> 7063.5124 | L34: 1862 | M34: =MAX((M33+K34-J34)*0.994,0) -> 382444.08
A35: 1863 | B35: 0.0356 | C35: 0.0107 | D35: 0.29625143 | E35: Great Power | F35: =(MIN(B35,0.02)*150)+(MIN(C35,0.04)*50)+(MIN(D35,1)*4)+(IF(E35="Great Power",1.5,IF(E35="Secondary Power",1.25,IF(E35="Westernized Nation",1,0)))) -> 6.2200057 | G35: =MIN(G34+(4*2/90/100*12),1) -> 0.652 | H35: 1.5 | I35: =F35*(1+H35+G35) -> 19.605458 | J35: =I35*365 -> 7155.9922 | L35: 1863 | M35: =MAX((M34+K35-J35)*0.994,0) -> 373036.36
A36: 1864 | B36: 0.0364 | C36: 0.0109 | D36: 0.30966743 | E36: Great Power | F36: =(MIN(B36,0.02)*150)+(MIN(C36,0.04)*50)+(MIN(D36,1)*4)+(IF(E36="Great Power",1.5,IF(E36="Secondary Power",1.25,IF(E36="Westernized Nation",1,0)))) -> 6.2836697 | G36: =MIN(G35+(4*2/90/100*12),1) -> 0.66266667 | H36: 1.5 | I36: =F36*(1+H36+G36) -> 19.873153 | J36: =I36*365 -> 7253.7008 | L36: 1864 | M36: =MAX((M35+K36-J36)*0.994,0) -> 363587.96
A37: 1865 | B37: 0.0372 | C37: 0.0111 | D37: 0.32339543 | E37: Great Power | F37: =(MIN(B37,0.02)*150)+(MIN(C37,0.04)*50)+(MIN(D37,1)*4)+(IF(E37="Great Power",1.5,IF(E37="Secondary Power",1.25,IF(E37="Westernized Nation",1,0)))) -> 6.3485817 | G37: =MIN(G36+(4*2/90/100*12),1) -> 0.67333333 | H37: 1.5 | I37: =F37*(1+H37+G37) -> 20.146166 | J37: =I37*365 -> 7353.3506 | L37: 1865 | M37: =MAX((M36+K37-J37)*0.994,0) -> 354097.2
A38: 1866 | B38: 0.038 | C38: 0.0113 | D38: 0.33743543 | E38: Great Power | F38: =(MIN(B38,0.02)*150)+(MIN(C38,0.04)*50)+(MIN(D38,1)*4)+(IF(E38="Great Power",1.5,IF(E38="Secondary Power",1.25,IF(E38="Westernized Nation",1,0)))) -> 6.4147417 | G38: =MIN(G37+(4*2/90/100*12),1) -> 0.684 | H38: 1.5 | I38: =F38*(1+H38+G38) -> 20.424538 | J38: =I38*365 -> 7454.9562 | L38: 1866 | M38: =MAX((M37+K38-J38)*0.994,0) -> 344562.39
A39: 1867 | B39: 0.0388 | C39: 0.0115 | D39: 0.35178743 | E39: Great Power | F39: =(MIN(B39,0.02)*150)+(MIN(C39,0.04)*50)+(MIN(D39,1)*4)+(IF(E39="Great Power",1.5,IF(E39="Secondary Power",1.25,IF(E39="Westernized Nation",1,0)))) -> 6.4821497 | G39: =MIN(G38+(4*2/90/100*12),1) -> 0.69466667 | H39: 1.5 | I39: =F39*(1+H39+G39) -> 20.708308 | J39: =I39*365 -> 7558.5323 | L39: 1867 | M39: =MAX((M38+K39-J39)*0.994,0) -> 334981.84
A40: 1868 | B40: 0.0396 | C40: 0.0117 | D40: 0.36645143 | E40: Great Power | F40: =(MIN(B40,0.02)*150)+(MIN(C40,0.04)*50)+(MIN(D40,1)*4)+(IF(E40="Great Power",1.5,IF(E40="Secondary Power",1.25,IF(E40="Westernized Nation",1,0)))) -> 6.5508057 | G40: =MIN(G39+(4*2/90/100*12),1) -> 0.70533333 | H40: 1.5 | I40: =F40*(1+H40+G40) -> 20.997516 | J40: =I40*365 -> 7664.0933 | L40: 1868 | M40: =MAX((M39+K40-J40)*0.994,0) -> 325353.84
A41: 1869 | B41: 0.0404 | C41: 0.0119 | D41: 0.38142743 | E41: Great Power | F41: =(MIN(B41,0.02)*150)+(MIN(C41,0.04)*50)+(MIN(D41,1)*4)+(IF(E41="Great Power",1.5,IF(E41="Secondary Power",1.25,IF(E41="Westernized Nation",1,0)))) -> 6.6207097 | G41: =MIN(G40+(4*2/90/100*12),1) -> 0.716 | H41: 1.5 | I41: =F41*(1+H41+G41) -> 21.292202 | J41: =I41*365 -> 7771.6539 | L41: 1869 | M41: =MAX((M40+K41-J41)*0.994,0) -> 315676.69
A42: 1870 | B42: 0.041 | C42: 0.0121 | D42: 0.39671543 | E42: Great Power | F42: =(MIN(B42,0.02)*150)+(MIN(C42,0.04)*50)+(MIN(D42,1)*4)+(IF(E42="Great Power",1.5,IF(E42="Secondary Power",1.25,IF(E42="Westernized Nation",1,0)))) -> 6.6918617 | G42: =MIN(G41+(4*2/90/100*12),1) -> 0.72666667 | H42: 1.5 | I42: =F42*(1+H42+G42) -> 21.592407 | J42: =I42*365 -> 7881.2286 | K42: 331200 | L42: 1870 | M42: =MAX((M41+K42-J42)*0.994,0) -> 635161.49
A43: 1871 | B43: 0.041 | C43: 0.0123 | D43: 0.412744 | E43: Great Power | F43: =(MIN(B43,0.02)*150)+(MIN(C43,0.04)*50)+(MIN(D43,1)*4)+(IF(E43="Great Power",1.5,IF(E43="Secondary Power",1.25,IF(E43="Westernized Nation",1,0)))) -> 6.765976 | G43: =MIN(G42+(4*2/90/100*12),1) -> 0.73733333 | H43: 2.5 | I43: =F43*(1+H43+G43) -> 28.669696 | J43: =I43*365 -> 10464.439 | L43: 1871 | M43: =MAX((M42+K43-J43)*0.994,0) -> 620948.87
A44: 1872 | B44: 0.041 | C44: 0.0125 | D44: 0.42909314 | E44: Great Power | F44: =(MIN(B44,0.02)*150)+(MIN(C44,0.04)*50)+(MIN(D44,1)*4)+(IF(E44="Great Power",1.5,IF(E44="Secondary Power",1.25,IF(E44="Westernized Nation",1,0)))) -> 6.8413726 | G44: =MIN(G43+(4*2/90/100*12),1) -> 0.748 | H44: 2.5 | I44: =F44*(1+H44+G44) -> 29.062151 | J44: =I44*365 -> 10607.685 | K44: 14400 | L44: 1872 | M44: =MAX((M43+K44-J44)*0.994,0) -> 620992.73
A45: 1873 | B45: 0.041 | C45: 0.0127 | D45: 0.44576286 | E45: Great Power | F45: =(MIN(B45,0.02)*150)+(MIN(C45,0.04)*50)+(MIN(D45,1)*4)+(IF(E45="Great Power",1.5,IF(E45="Secondary Power",1.25,IF(E45="Westernized Nation",1,0)))) -> 6.9180514 | G45: =MIN(G44+(4*2/90/100*12),1) -> 0.75866667 | H45: 2.5 | I45: =F45*(1+H45+G45) -> 29.461675 | J45: =I45*365 -> 10753.511 | L45: 1873 | M45: =MAX((M44+K45-J45)*0.994,0) -> 606577.79
A46: 1874 | B46: 0.041 | C46: 0.0129 | D46: 0.46275314 | E46: Great Power | F46: =(MIN(B46,0.02)*150)+(MIN(C46,0.04)*50)+(MIN(D46,1)*4)+(IF(E46="Great Power",1.5,IF(E46="Secondary Power",1.25,IF(E46="Westernized Nation",1,0)))) -> 6.9960126 | G46: =MIN(G45+(4*2/90/100*12),1) -> 0.76933333 | H46: 2.5 | I46: =F46*(1+H46+G46) -> 29.86831 | J46: =I46*365 -> 10901.933 | L46: 1874 | M46: =MAX((M45+K46-J46)*0.994,0) -> 592101.8
A47: 1875 | B47: 0.041 | C47: 0.0131 | D47: 0.480064 | E47: Great Power | F47: =(MIN(B47,0.02)*150)+(MIN(C47,0.04)*50)+(MIN(D47,1)*4)+(IF(E47="Great Power",1.5,IF(E47="Secondary Power",1.25,IF(E47="Westernized Nation",1,0)))) -> 7.075256 | G47: =MIN(G46+(4*2/90/100*12),1) -> 0.78 | H47: 2.5 | I47: =F47*(1+H47+G47) -> 30.282096 | J47: =I47*365 -> 11052.965 | K47: 14400 | L47: 1875 | M47: =MAX((M46+K47-J47)*0.994,0) -> 591876.14
A48: 1876 | B48: 0.041 | C48: 0.0133 | D48: 0.49769543 | E48: Great Power | F48: =(MIN(B48,0.02)*150)+(MIN(C48,0.04)*50)+(MIN(D48,1)*4)+(IF(E48="Great Power",1.5,IF(E48="Secondary Power",1.25,IF(E48="Westernized Nation",1,0)))) -> 7.1557817 | G48: =MIN(G47+(4*2/90/100*12),1) -> 0.79066667 | H48: 2.5 | I48: =F48*(1+H48+G48) -> 30.703074 | J48: =I48*365 -> 11206.622 | L48: 1876 | M48: =MAX((M47+K48-J48)*0.994,0) -> 577185.5
A49: 1877 | B49: 0.041 | C49: 0.0135 | D49: 0.51564743 | E49: Great Power | F49: =(MIN(B49,0.02)*150)+(MIN(C49,0.04)*50)+(MIN(D49,1)*4)+(IF(E49="Great Power",1.5,IF(E49="Secondary Power",1.25,IF(E49="Westernized Nation",1,0)))) -> 7.2375897 | G49: =MIN(G48+(4*2/90/100*12),1) -> 0.80133333 | H49: 2.5 | I49: =F49*(1+H49+G49) -> 31.131286 | J49: =I49*365 -> 11362.919 | L49: 1877 | M49: =MAX((M48+K49-J49)*0.994,0) -> 562427.65
A50: 1878 | B50: 0.041 | C50: 0.0137 | D50: 0.53392 | E50: Great Power | F50: =(MIN(B50,0.02)*150)+(MIN(C50,0.04)*50)+(MIN(D50,1)*4)+(IF(E50="Great Power",1.5,IF(E50="Secondary Power",1.25,IF(E50="Westernized Nation",1,0)))) -> 7.32068 | G50: =MIN(G49+(4*2/90/100*12),1) -> 0.812 | H50: 2.5 | I50: =F50*(1+H50+G50) -> 31.566772 | J50: =I50*365 -> 11521.872 | L50: 1878 | M50: =MAX((M49+K50-J50)*0.994,0) -> 547600.34
A51: 1879 | B51: 0.041 | C51: 0.0139 | D51: 0.55251314 | E51: Great Power | F51: =(MIN(B51,0.02)*150)+(MIN(C51,0.04)*50)+(MIN(D51,1)*4)+(IF(E51="Great Power",1.5,IF(E51="Secondary Power",1.25,IF(E51="Westernized Nation",1,0)))) -> 7.4050526 | G51: =MIN(G50+(4*2/90/100*12),1) -> 0.82266667 | H51: 2.5 | I51: =F51*(1+H51+G51) -> 32.009574 | J51: =I51*365 -> 11683.494 | L51: 1879 | M51: =MAX((M50+K51-J51)*0.994,0) -> 532701.35
A52: 1880 | B52: 0.041 | C52: 0.0141 | D52: 0.57142686 | E52: Great Power | F52: =(MIN(B52,0.02)*150)+(MIN(C52,0.04)*50)+(MIN(D52,1)*4)+(IF(E52="Great Power",1.5,IF(E52="Secondary Power",1.25,IF(E52="Westernized Nation",1,0)))) -> 7.4907074 | G52: =MIN(G51+(4*2/90/100*12),1) -> 0.83333333 | H52: 2.5 | I52: =F52*(1+H52+G52) -> 32.459732 | J52: =I52*365 -> 11847.802 | K52: 50400 | L52: 1880 | M52: =MAX((M51+K52-J52)*0.994,0) -> 567826.02
A53: 1881 | B53: 0.041 | C53: 0.0143 | D53: 0.59066114 | E53: Great Power | F53: =(MIN(B53,0.02)*150)+(MIN(C53,0.04)*50)+(MIN(D53,1)*4)+(IF(E53="Great Power",1.5,IF(E53="Secondary Power",1.25,IF(E53="Westernized Nation",1,0)))) -> 7.5776446 | G53: =MIN(G52+(4*2/90/100*12),1) -> 0.844 | H53: 3.5 | I53: =F53*(1+H53+G53) -> 40.494933 | J53: =I53*365 -> 14780.65 | L53: 1881 | M53: =MAX((M52+K53-J53)*0.994,0) -> 549727.1
A54: 1882 | B54: 0.041 | C54: 0.0145 | D54: 0.610216 | E54: Great Power | F54: =(MIN(B54,0.02)*150)+(MIN(C54,0.04)*50)+(MIN(D54,1)*4)+(IF(E54="Great Power",1.5,IF(E54="Secondary Power",1.25,IF(E54="Westernized Nation",1,0)))) -> 7.665864 | G54: =MIN(G53+(4*2/90/100*12),1) -> 0.85466667 | H54: 3.5 | I54: =F54*(1+H54+G54) -> 41.048146 | J54: =I54*365 -> 14982.573 | L54: 1882 | M54: =MAX((M53+K54-J54)*0.994,0) -> 531536.06
A55: 1883 | B55: 0.041 | C55: 0.0147 | D55: 0.63009143 | E55: Great Power | F55: =(MIN(B55,0.02)*150)+(MIN(C55,0.04)*50)+(MIN(D55,1)*4)+(IF(E55="Great Power",1.5,IF(E55="Secondary Power",1.25,IF(E55="Westernized Nation",1,0)))) -> 7.7553657 | G55: =MIN(G54+(4*2/90/100*12),1) -> 0.86533333 | H55: 3.5 | I55: =F55*(1+H55+G55) -> 41.610122 | J55: =I55*365 -> 15187.695 | L55: 1883 | M55: =MAX((M54+K55-J55)*0.994,0) -> 513250.27
A56: 1884 | B56: 0.041 | C56: 0.0149 | D56: 0.65190743 | E56: Great Power | F56: =(MIN(B56,0.02)*150)+(MIN(C56,0.04)*50)+(MIN(D56,1)*4)+(IF(E56="Great Power",1.5,IF(E56="Secondary Power",1.25,IF(E56="Westernized Nation",1,0)))) -> 7.8526297 | G56: =MIN(G55+(4*2/90/100*12),1) -> 0.876 | H56: 3.5 | I56: =F56*(1+H56+G56) -> 42.215737 | J56: =I56*365 -> 15408.744 | L56: 1884 | M56: =MAX((M55+K56-J56)*0.994,0) -> 494854.48
A57: 1885 | B57: 0.041 | C57: 0.0151 | D57: 0.67406971 | E57: Great Power | F57: =(MIN(B57,0.02)*150)+(MIN(C57,0.04)*50)+(MIN(D57,1)*4)+(IF(E57="Great Power",1.5,IF(E57="Secondary Power",1.25,IF(E57="Westernized Nation",1,0)))) -> 7.9512789 | G57: =MIN(G56+(4*2/90/100*12),1) -> 0.88666667 | H57: 3.5 | I57: =F57*(1+H57+G57) -> 42.830889 | J57: =I57*365 -> 15633.274 | L57: 1885 | M57: =MAX((M56+K57-J57)*0.994,0) -> 476345.88
A58: 1886 | B58: 0.041 | C58: 0.0153 | D58: 0.69657829 | E58: Great Power | F58: =(MIN(B58,0.02)*150)+(MIN(C58,0.04)*50)+(MIN(D58,1)*4)+(IF(E58="Great Power",1.5,IF(E58="Secondary Power",1.25,IF(E58="Westernized Nation",1,0)))) -> 8.0513131 | G58: =MIN(G57+(4*2/90/100*12),1) -> 0.89733333 | H58: 3.5 | I58: =F58*(1+H58+G58) -> 43.455621 | J58: =I58*365 -> 15861.302 | L58: 1886 | M58: =MAX((M57+K58-J58)*0.994,0) -> 457721.67
A59: 1887 | B59: 0.041 | C59: 0.0155 | D59: 0.71943314 | E59: Great Power | F59: =(MIN(B59,0.02)*150)+(MIN(C59,0.04)*50)+(MIN(D59,1)*4)+(IF(E59="Great Power",1.5,IF(E59="Secondary Power",1.25,IF(E59="Westernized Nation",1,0)))) -> 8.1527326 | G59: =MIN(G58+(4*2/90/100*12),1) -> 0.908 | H59: 3.5 | I59: =F59*(1+H59+G59) -> 44.089978 | J59: =I59*365 -> 16092.842 | L59: 1887 | M59: =MAX((M58+K59-J59)*0.994,0) -> 438979.06
A60: 1888 | B60: 0.041 | C60: 0.0157 | D60: 0.74263429 | E60: Great Power | F60: =(MIN(B60,0.02)*150)+(MIN(C60,0.04)*50)+(MIN(D60,1)*4)+(IF(E60="Great Power",1.5,IF(E60="Secondary Power",1.25,IF(E60="Westernized Nation",1,0)))) -> 8.2555371 | G60: =MIN(G59+(4*2/90/100*12),1) -> 0.91866667 | H60: 3.5 | I60: =F60*(1+H60+G60) -> 44.734004 | J60: =I60*365 -> 16327.911 | L60: 1888 | M60: =MAX((M59+K60-J60)*0.994,0) -> 420115.24
A61: 1889 | B61: 0.041 | C61: 0.0159 | D61: 0.76618171 | E61: Great Power | F61: =(MIN(B61,0.02)*150)+(MIN(C61,0.04)*50)+(MIN(D61,1)*4)+(IF(E61="Great Power",1.5,IF(E61="Secondary Power",1.25,IF(E61="Westernized Nation",1,0)))) -> 8.3597269 | G61: =MIN(G60+(4*2/90/100*12),1) -> 0.92933333 | H61: 3.5 | I61: =F61*(1+H61+G61) -> 45.387744 | J61: =I61*365 -> 16566.526 | L61: 1889 | M61: =MAX((M60+K61-J61)*0.994,0) -> 401127.42
A62: 1890 | B62: 0.041 | C62: 0.0161 | D62: 0.79007543 | E62: Great Power | F62: =(MIN(B62,0.02)*150)+(MIN(C62,0.04)*50)+(MIN(D62,1)*4)+(IF(E62="Great Power",1.5,IF(E62="Secondary Power",1.25,IF(E62="Westernized Nation",1,0)))) -> 8.4653017 | G62: =MIN(G61+(4*2/90/100*12),1) -> 0.94 | H62: 3.5 | I62: =F62*(1+H62+G62) -> 46.051241 | J62: =I62*365 -> 16808.703 | K62: 54000 | L62: 1890 | M62: =MAX((M61+K62-J62)*0.994,0) -> 435688.8
A63: 1891 | B63: 0.041 | C63: 0.0163 | D63: 0.81431543 | E63: Great Power | F63: =(MIN(B63,0.02)*150)+(MIN(C63,0.04)*50)+(MIN(D63,1)*4)+(IF(E63="Great Power",1.5,IF(E63="Secondary Power",1.25,IF(E63="Westernized Nation",1,0)))) -> 8.5722617 | G63: =MIN(G62+(4*2/90/100*12),1) -> 0.95066667 | H63: 3.5 | I63: =F63*(1+H63+G63) -> 46.724541 | J63: =I63*365 -> 17054.458 | L63: 1891 | M63: =MAX((M62+K63-J63)*0.994,0) -> 416122.54
A64: 1892 | B64: 0.041 | C64: 0.0165 | D64: 0.83855543 | E64: Great Power | F64: =(MIN(B64,0.02)*150)+(MIN(C64,0.04)*50)+(MIN(D64,1)*4)+(IF(E64="Great Power",1.5,IF(E64="Secondary Power",1.25,IF(E64="Westernized Nation",1,0)))) -> 8.6792217 | G64: =MIN(G63+(4*2/90/100*12),1) -> 0.96133333 | H64: 3.5 | I64: =F64*(1+H64+G64) -> 47.400123 | J64: =I64*365 -> 17301.045 | L64: 1892 | M64: =MAX((M63+K64-J64)*0.994,0) -> 396428.57
A65: 1893 | B65: 0.041 | C65: 0.0167 | D65: 0.86279543 | E65: Great Power | F65: =(MIN(B65,0.02)*150)+(MIN(C65,0.04)*50)+(MIN(D65,1)*4)+(IF(E65="Great Power",1.5,IF(E65="Secondary Power",1.25,IF(E65="Westernized Nation",1,0)))) -> 8.7861817 | G65: =MIN(G64+(4*2/90/100*12),1) -> 0.972 | H65: 3.5 | I65: =F65*(1+H65+G65) -> 48.077986 | J65: =I65*365 -> 17548.465 | L65: 1893 | M65: =MAX((M64+K65-J65)*0.994,0) -> 376606.82
A66: 1894 | B66: 0.041 | C66: 0.0169 | D66: 0.88703543 | E66: Great Power | F66: =(MIN(B66,0.02)*150)+(MIN(C66,0.04)*50)+(MIN(D66,1)*4)+(IF(E66="Great Power",1.5,IF(E66="Secondary Power",1.25,IF(E66="Westernized Nation",1,0)))) -> 8.8931417 | G66: =MIN(G65+(4*2/90/100*12),1) -> 0.98266667 | H66: 3.5 | I66: =F66*(1+H66+G66) -> 48.758132 | J66: =I66*365 -> 17796.718 | L66: 1894 | M66: =MAX((M65+K66-J66)*0.994,0) -> 356657.24
A67: 1895 | B67: 0.041 | C67: 0.0171 | D67: 0.91127543 | E67: Great Power | F67: =(MIN(B67,0.02)*150)+(MIN(C67,0.04)*50)+(MIN(D67,1)*4)+(IF(E67="Great Power",1.5,IF(E67="Secondary Power",1.25,IF(E67="Westernized Nation",1,0)))) -> 9.0001017 | G67: =MIN(G66+(4*2/90/100*12),1) -> 0.99333333 | H67: 3.5 | I67: =F67*(1+H67+G67) -> 49.440559 | J67: =I67*365 -> 18045.804 | K67: 18000 | L67: 1895 | M67: =MAX((M66+K67-J67)*0.994,0) -> 354471.77
A68: 1896 | B68: 0.041 | C68: 0.0173 | D68: 0.93551543 | E68: Great Power | F68: =(MIN(B68,0.02)*150)+(MIN(C68,0.04)*50)+(MIN(D68,1)*4)+(IF(E68="Great Power",1.5,IF(E68="Secondary Power",1.25,IF(E68="Westernized Nation",1,0)))) -> 9.1070617 | G68: =MIN(G67+(4*2/90/100*12),1) -> 1 | H68: 3.5 | I68: =F68*(1+H68+G68) -> 50.088839 | J68: =I68*365 -> 18282.426 | L68: 1896 | M68: =MAX((M67+K68-J68)*0.994,0) -> 334172.21
A69: 1897 | B69: 0.041 | C69: 0.0175 | D69: 0.95975543 | E69: Great Power | F69: =(MIN(B69,0.02)*150)+(MIN(C69,0.04)*50)+(MIN(D69,1)*4)+(IF(E69="Great Power",1.5,IF(E69="Secondary Power",1.25,IF(E69="Westernized Nation",1,0)))) -> 9.2140217 | G69: =MIN(G68+(4*2/90/100*12),1) -> 1 | H69: 3.5 | I69: =F69*(1+H69+G69) -> 50.677119 | J69: =I69*365 -> 18497.149 | L69: 1897 | M69: =MAX((M68+K69-J69)*0.994,0) -> 313781.01
A70: 1898 | B70: 0.041 | C70: 0.0177 | D70: 0.98399543 | E70: Great Power | F70: =(MIN(B70,0.02)*150)+(MIN(C70,0.04)*50)+(MIN(D70,1)*4)+(IF(E70="Great Power",1.5,IF(E70="Secondary Power",1.25,IF(E70="Westernized Nation",1,0)))) -> 9.3209817 | G70: =MIN(G69+(4*2/90/100*12),1) -> 1 | H70: 3.5 | I70: =F70*(1+H70+G70) -> 51.265399 | J70: =I70*365 -> 18711.871 | K70: 18000 | L70: 1898 | M70: =MAX((M69+K70-J70)*0.994,0) -> 311190.72
A71: 1899 | B71: 0.041 | C71: 0.0179 | D71: 1 | E71: Great Power | F71: =(MIN(B71,0.02)*150)+(MIN(C71,0.04)*50)+(MIN(D71,1)*4)+(IF(E71="Great Power",1.5,IF(E71="Secondary Power",1.25,IF(E71="Westernized Nation",1,0)))) -> 9.395 | G71: =MIN(G70+(4*2/90/100*12),1) -> 1 | H71: 3.5 | I71: =F71*(1+H71+G71) -> 51.6725 | J71: =I71*365 -> 18860.463 | L71: 1899 | M71: =MAX((M70+K71-J71)*0.994,0) -> 290576.28
A72: 1900 | B72: 0.041 | C72: 0.0181 | D72: 1 | E72: Great Power | F72: =(MIN(B72,0.02)*150)+(MIN(C72,0.04)*50)+(MIN(D72,1)*4)+(IF(E72="Great Power",1.5,IF(E72="Secondary Power",1.25,IF(E72="Westernized Nation",1,0)))) -> 9.405 | G72: =MIN(G71+(4*2/90/100*12),1) -> 1 | H72: 3.5 | I72: =F72*(1+H72+G72) -> 51.7275 | J72: =I72*365 -> 18880.537 | K72: 255600 | L72: 1900 | M72: =MAX((M71+K72-J72)*0.994,0) -> 524131.97
A73: 1901 | B73: 0.041 | C73: 0.0183 | D73: 1 | E73: Great Power | F73: =(MIN(B73,0.02)*150)+(MIN(C73,0.04)*50)+(MIN(D73,1)*4)+(IF(E73="Great Power",1.5,IF(E73="Secondary Power",1.25,IF(E73="Westernized Nation",1,0)))) -> 9.415 | G73: =MIN(G72+(4*2/90/100*12),1) -> 1 | H73: 4.5 | I73: =F73*(1+H73+G73) -> 61.1975 | J73: =I73*365 -> 22337.088 | L73: 1901 | M73: =MAX((M72+K73-J73)*0.994,0) -> 498784.11
A74: 1902 | B74: 0.041 | C74: 0.0185 | D74: 1 | E74: Great Power | F74: =(MIN(B74,0.02)*150)+(MIN(C74,0.04)*50)+(MIN(D74,1)*4)+(IF(E74="Great Power",1.5,IF(E74="Secondary Power",1.25,IF(E74="Westernized Nation",1,0)))) -> 9.425 | G74: =MIN(G73+(4*2/90/100*12),1) -> 1 | H74: 4.5 | I74: =F74*(1+H74+G74) -> 61.2625 | J74: =I74*365 -> 22360.812 | L74: 1902 | M74: =MAX((M73+K74-J74)*0.994,0) -> 473564.76
A75: 1903 | B75: 0.041 | C75: 0.0187 | D75: 1 | E75: Great Power | F75: =(MIN(B75,0.02)*150)+(MIN(C75,0.04)*50)+(MIN(D75,1)*4)+(IF(E75="Great Power",1.5,IF(E75="Secondary Power",1.25,IF(E75="Westernized Nation",1,0)))) -> 9.435 | G75: =MIN(G74+(4*2/90/100*12),1) -> 1 | H75: 4.5 | I75: =F75*(1+H75+G75) -> 61.3275 | J75: =I75*365 -> 22384.537 | L75: 1903 | M75: =MAX((M74+K75-J75)*0.994,0) -> 448473.14
A76: 1904 | B76: 0.041 | C76: 0.0189 | D76: 1 | E76: Great Power | F76: =(MIN(B76,0.02)*150)+(MIN(C76,0.04)*50)+(MIN(D76,1)*4)+(IF(E76="Great Power",1.5,IF(E76="Secondary Power",1.25,IF(E76="Westernized Nation",1,0)))) -> 9.445 | G76: =MIN(G75+(4*2/90/100*12),1) -> 1 | H76: 4.5 | I76: =F76*(1+H76+G76) -> 61.3925 | J76: =I76*365 -> 22408.263 | L76: 1904 | M76: =MAX((M75+K76-J76)*0.994,0) -> 423508.49
A77: 1905 | B77: 0.041 | C77: 0.0191 | D77: 1 | E77: Great Power | F77: =(MIN(B77,0.02)*150)+(MIN(C77,0.04)*50)+(MIN(D77,1)*4)+(IF(E77="Great Power",1.5,IF(E77="Secondary Power",1.25,IF(E77="Westernized Nation",1,0)))) -> 9.455 | G77: =MIN(G76+(4*2/90/100*12),1) -> 1 | H77: 4.5 | I77: =F77*(1+H77+G77) -> 61.4575 | J77: =I77*365 -> 22431.987 | K77: 21600 | L77: 1905 | M77: =MAX((M76+K77-J77)*0.994,0) -> 420140.44
A78: 1906 | B78: 0.041 | C78: 0.0193 | D78: 1 | E78: Great Power | F78: =(MIN(B78,0.02)*150)+(MIN(C78,0.04)*50)+(MIN(D78,1)*4)+(IF(E78="Great Power",1.5,IF(E78="Secondary Power",1.25,IF(E78="Westernized Nation",1,0)))) -> 9.465 | G78: =MIN(G77+(4*2/90/100*12),1) -> 1 | H78: 4.5 | I78: =F78*(1+H78+G78) -> 61.5225 | J78: =I78*365 -> 22455.713 | L78: 1906 | M78: =MAX((M77+K78-J78)*0.994,0) -> 395298.62
A79: 1907 | B79: 0.041 | C79: 0.0195 | D79: 1 | E79: Great Power | F79: =(MIN(B79,0.02)*150)+(MIN(C79,0.04)*50)+(MIN(D79,1)*4)+(IF(E79="Great Power",1.5,IF(E79="Secondary Power",1.25,IF(E79="Westernized Nation",1,0)))) -> 9.475 | G79: =MIN(G78+(4*2/90/100*12),1) -> 1 | H79: 4.5 | I79: =F79*(1+H79+G79) -> 61.5875 | J79: =I79*365 -> 22479.438 | L79: 1907 | M79: =MAX((M78+K79-J79)*0.994,0) -> 370582.27
A80: 1908 | B80: 0.041 | C80: 0.0197 | D80: 1 | E80: Great Power | F80: =(MIN(B80,0.02)*150)+(MIN(C80,0.04)*50)+(MIN(D80,1)*4)+(IF(E80="Great Power",1.5,IF(E80="Secondary Power",1.25,IF(E80="Westernized Nation",1,0)))) -> 9.485 | G80: =MIN(G79+(4*2/90/100*12),1) -> 1 | H80: 4.5 | I80: =F80*(1+H80+G80) -> 61.6525 | J80: =I80*365 -> 22503.162 | L80: 1908 | M80: =MAX((M79+K80-J80)*0.994,0) -> 345990.63
A81: 1909 | B81: 0.041 | C81: 0.0199 | D81: 1 | E81: Great Power | F81: =(MIN(B81,0.02)*150)+(MIN(C81,0.04)*50)+(MIN(D81,1)*4)+(IF(E81="Great Power",1.5,IF(E81="Secondary Power",1.25,IF(E81="Westernized Nation",1,0)))) -> 9.495 | G81: =MIN(G80+(4*2/90/100*12),1) -> 1 | H81: 4.5 | I81: =F81*(1+H81+G81) -> 61.7175 | J81: =I81*365 -> 22526.888 | L81: 1909 | M81: =MAX((M80+K81-J81)*0.994,0) -> 321522.96
A82: 1910 | B82: 0.041 | C82: 0.0201 | D82: 1 | E82: Great Power | F82: =(MIN(B82,0.02)*150)+(MIN(C82,0.04)*50)+(MIN(D82,1)*4)+(IF(E82="Great Power",1.5,IF(E82="Secondary Power",1.25,IF(E82="Westernized Nation",1,0)))) -> 9.505 | G82: =MIN(G81+(4*2/90/100*12),1) -> 1 | H82: 4.5 | I82: =F82*(1+H82+G82) -> 61.7825 | J82: =I82*365 -> 22550.612 | K82: 21600 | L82: 1910 | M82: =MAX((M81+K82-J82)*0.994,0) -> 318648.91
A83: 1911 | B83: 0.041 | C83: 0.0203 | D83: 1 | E83: Great Power | F83: =(MIN(B83,0.02)*150)+(MIN(C83,0.04)*50)+(MIN(D83,1)*4)+(IF(E83="Great Power",1.5,IF(E83="Secondary Power",1.25,IF(E83="Westernized Nation",1,0)))) -> 9.515 | G83: =MIN(G82+(4*2/90/100*12),1) -> 1 | H83: 4.5 | I83: =F83*(1+H83+G83) -> 61.8475 | J83: =I83*365 -> 22574.338 | L83: 1911 | M83: =MAX((M82+K83-J83)*0.994,0) -> 294298.13
A84: 1912 | B84: 0.041 | C84: 0.0205 | D84: 1 | E84: Great Power | F84: =(MIN(B84,0.02)*150)+(MIN(C84,0.04)*50)+(MIN(D84,1)*4)+(IF(E84="Great Power",1.5,IF(E84="Secondary Power",1.25,IF(E84="Westernized Nation",1,0)))) -> 9.525 | G84: =MIN(G83+(4*2/90/100*12),1) -> 1 | H84: 4.5 | I84: =F84*(1+H84+G84) -> 61.9125 | J84: =I84*365 -> 22598.062 | L84: 1912 | M84: =MAX((M83+K84-J84)*0.994,0) -> 270069.86
A85: 1913 | B85: 0.041 | C85: 0.0207 | D85: 1 | E85: Great Power | F85: =(MIN(B85,0.02)*150)+(MIN(C85,0.04)*50)+(MIN(D85,1)*4)+(IF(E85="Great Power",1.5,IF(E85="Secondary Power",1.25,IF(E85="Westernized Nation",1,0)))) -> 9.535 | G85: =MIN(G84+(4*2/90/100*12),1) -> 1 | H85: 4.5 | I85: =F85*(1+H85+G85) -> 61.9775 | J85: =I85*365 -> 22621.787 | L85: 1913 | M85: =MAX((M84+K85-J85)*0.994,0) -> 245963.39
A86: 1914 | B86: 0.041 | C86: 0.0209 | D86: 1 | E86: Great Power | F86: =(MIN(B86,0.02)*150)+(MIN(C86,0.04)*50)+(MIN(D86,1)*4)+(IF(E86="Great Power",1.5,IF(E86="Secondary Power",1.25,IF(E86="Westernized Nation",1,0)))) -> 9.545 | G86: =MIN(G85+(4*2/90/100*12),1) -> 1 | H86: 4.5 | I86: =F86*(1+H86+G86) -> 62.0425 | J86: =I86*365 -> 22645.513 | K86: 43200 | L86: 1914 | M86: =MAX((M85+K86-J86)*0.994,0) -> 264918.77
A87: 1915 | B87: 0.041 | C87: 0.0211 | D87: 1 | E87: Great Power | F87: =(MIN(B87,0.02)*150)+(MIN(C87,0.04)*50)+(MIN(D87,1)*4)+(IF(E87="Great Power",1.5,IF(E87="Secondary Power",1.25,IF(E87="Westernized Nation",1,0)))) -> 9.555 | G87: =MIN(G86+(4*2/90/100*12),1) -> 1 | H87: 4.5 | I87: =F87*(1+H87+G87) -> 62.1075 | J87: =I87*365 -> 22669.237 | K87: 21600 | L87: 1915 | M87: =MAX((M86+K87-J87)*0.994,0) -> 262266.43
A88: 1916 | B88: 0.041 | C88: 0.0213 | D88: 1 | E88: Great Power | F88: =(MIN(B88,0.02)*150)+(MIN(C88,0.04)*50)+(MIN(D88,1)*4)+(IF(E88="Great Power",1.5,IF(E88="Secondary Power",1.25,IF(E88="Westernized Nation",1,0)))) -> 9.565 | G88: =MIN(G87+(4*2/90/100*12),1) -> 1 | H88: 4.5 | I88: =F88*(1+H88+G88) -> 62.1725 | J88: =I88*365 -> 22692.963 | L88: 1916 | M88: =MAX((M87+K88-J88)*0.994,0) -> 238136.03
A89: 1917 | B89: 0.041 | C89: 0.0215 | D89: 1 | E89: Great Power | F89: =(MIN(B89,0.02)*150)+(MIN(C89,0.04)*50)+(MIN(D89,1)*4)+(IF(E89="Great Power",1.5,IF(E89="Secondary Power",1.25,IF(E89="Westernized Nation",1,0)))) -> 9.575 | G89: =MIN(G88+(4*2/90/100*12),1) -> 1 | H89: 4.5 | I89: =F89*(1+H89+G89) -> 62.2375 | J89: =I89*365 -> 22716.688 | L89: 1917 | M89: =MAX((M88+K89-J89)*0.994,0) -> 214126.83
A90: 1918 | B90: 0.041 | C90: 0.0217 | D90: 1 | E90: Great Power | F90: =(MIN(B90,0.02)*150)+(MIN(C90,0.04)*50)+(MIN(D90,1)*4)+(IF(E90="Great Power",1.5,IF(E90="Secondary Power",1.25,IF(E90="Westernized Nation",1,0)))) -> 9.585 | G90: =MIN(G89+(4*2/90/100*12),1) -> 1 | H90: 4.5 | I90: =F90*(1+H90+G90) -> 62.3025 | J90: =I90*365 -> 22740.412 | L90: 1918 | M90: =MAX((M89+K90-J90)*0.994,0) -> 190238.1
A91: 1919 | B91: 0.041 | C91: 0.0219 | D91: 1 | E91: Great Power | F91: =(MIN(B91,0.02)*150)+(MIN(C91,0.04)*50)+(MIN(D91,1)*4)+(IF(E91="Great Power",1.5,IF(E91="Secondary Power",1.25,IF(E91="Westernized Nation",1,0)))) -> 9.595 | G91: =MIN(G90+(4*2/90/100*12),1) -> 1 | H91: 4.5 | I91: =F91*(1+H91+G91) -> 62.3675 | J91: =I91*365 -> 22764.138 | K91: 194400 | L91: 1919 | M91: =MAX((M90+K91-J91)*0.994,0) -> 359702.72
A92: 1920 | B92: 0.041 | C92: 0.0221 | D92: 1 | E92: Great Power | F92: =(MIN(B92,0.02)*150)+(MIN(C92,0.04)*50)+(MIN(D92,1)*4)+(IF(E92="Great Power",1.5,IF(E92="Secondary Power",1.25,IF(E92="Westernized Nation",1,0)))) -> 9.605 | G92: =MIN(G91+(4*2/90/100*12),1) -> 1 | H92: 4.5 | I92: =F92*(1+H92+G92) -> 62.4325 | J92: =I92*365 -> 22787.862 | L92: 1920 | M92: =MAX((M91+K92-J92)*0.994,0) -> 334893.36
A93: 1921 | B93: 0.041 | C93: 0.0223 | D93: 1 | E93: Great Power | F93: =(MIN(B93,0.02)*150)+(MIN(C93,0.04)*50)+(MIN(D93,1)*4)+(IF(E93="Great Power",1.5,IF(E93="Secondary Power",1.25,IF(E93="Westernized Nation",1,0)))) -> 9.615 | G93: =MIN(G92+(4*2/90/100*12),1) -> 1 | H93: 4.5 | I93: =F93*(1+H93+G93) -> 62.4975 | J93: =I93*365 -> 22811.588 | L93: 1921 | M93: =MAX((M92+K93-J93)*0.994,0) -> 310209.29
A94: 1922 | B94: 0.041 | C94: 0.0225 | D94: 1 | E94: Great Power | F94: =(MIN(B94,0.02)*150)+(MIN(C94,0.04)*50)+(MIN(D94,1)*4)+(IF(E94="Great Power",1.5,IF(E94="Secondary Power",1.25,IF(E94="Westernized Nation",1,0)))) -> 9.625 | G94: =MIN(G93+(4*2/90/100*12),1) -> 1 | H94: 4.5 | I94: =F94*(1+H94+G94) -> 62.5625 | J94: =I94*365 -> 22835.312 | L94: 1922 | M94: =MAX((M93+K94-J94)*0.994,0) -> 285649.73
A95: 1923 | B95: 0.041 | C95: 0.0227 | D95: 1 | E95: Great Power | F95: =(MIN(B95,0.02)*150)+(MIN(C95,0.04)*50)+(MIN(D95,1)*4)+(IF(E95="Great Power",1.5,IF(E95="Secondary Power",1.25,IF(E95="Westernized Nation",1,0)))) -> 9.635 | G95: =MIN(G94+(4*2/90/100*12),1) -> 1 | H95: 4.5 | I95: =F95*(1+H95+G95) -> 62.6275 | J95: =I95*365 -> 22859.037 | L95: 1923 | M95: =MAX((M94+K95-J95)*0.994,0) -> 261213.95
A96: 1924 | B96: 0.041 | C96: 0.0229 | D96: 1 | E96: Great Power | F96: =(MIN(B96,0.02)*150)+(MIN(C96,0.04)*50)+(MIN(D96,1)*4)+(IF(E96="Great Power",1.5,IF(E96="Secondary Power",1.25,IF(E96="Westernized Nation",1,0)))) -> 9.645 | G96: =MIN(G95+(4*2/90/100*12),1) -> 1 | H96: 4.5 | I96: =F96*(1+H96+G96) -> 62.6925 | J96: =I96*365 -> 22882.763 | L96: 1924 | M96: =MAX((M95+K96-J96)*0.994,0) -> 236901.2
A97: 1925 | B97: 0.041 | C97: 0.0231 | D97: 1 | E97: Great Power | F97: =(MIN(B97,0.02)*150)+(MIN(C97,0.04)*50)+(MIN(D97,1)*4)+(IF(E97="Great Power",1.5,IF(E97="Secondary Power",1.25,IF(E97="Westernized Nation",1,0)))) -> 9.655 | G97: =MIN(G96+(4*2/90/100*12),1) -> 1 | H97: 4.5 | I97: =F97*(1+H97+G97) -> 62.7575 | J97: =I97*365 -> 22906.487 | L97: 1925 | M97: =MAX((M96+K97-J97)*0.994,0) -> 212710.74
A98: 1926 | B98: 0.041 | C98: 0.0233 | D98: 1 | E98: Great Power | F98: =(MIN(B98,0.02)*150)+(MIN(C98,0.04)*50)+(MIN(D98,1)*4)+(IF(E98="Great Power",1.5,IF(E98="Secondary Power",1.25,IF(E98="Westernized Nation",1,0)))) -> 9.665 | G98: =MIN(G97+(4*2/90/100*12),1) -> 1 | H98: 4.5 | I98: =F98*(1+H98+G98) -> 62.8225 | J98: =I98*365 -> 22930.213 | L98: 1926 | M98: =MAX((M97+K98-J98)*0.994,0) -> 188641.85
A99: 1927 | B99: 0.041 | C99: 0.0235 | D99: 1 | E99: Great Power | F99: =(MIN(B99,0.02)*150)+(MIN(C99,0.04)*50)+(MIN(D99,1)*4)+(IF(E99="Great Power",1.5,IF(E99="Secondary Power",1.25,IF(E99="Westernized Nation",1,0)))) -> 9.675 | G99: =MIN(G98+(4*2/90/100*12),1) -> 1 | H99: 4.5 | I99: =F99*(1+H99+G99) -> 62.8875 | J99: =I99*365 -> 22953.938 | L99: 1927 | M99: =MAX((M98+K99-J99)*0.994,0) -> 164693.78
A100: 1928 | B100: 0.041 | C100: 0.0237 | D100: 1 | E100: Great Power | F100: =(MIN(B100,0.02)*150)+(MIN(C100,0.04)*50)+(MIN(D100,1)*4)+(IF(E100="Great Power",1.5,IF(E100="Secondary Power",1.25,IF(E100="Westernized Nation",1,0)))) -> 9.685 | G100: =MIN(G99+(4*2/90/100*12),1) -> 1 | H100: 4.5 | I100: =F100*(1+H100+G100) -> 62.9525 | J100: =I100*365 -> 22977.662 | L100: 1928 | M100: =MAX((M99+K100-J100)*0.994,0) -> 140865.82
...

Sheet Tech Cost
A1: Date | B1: Total Tech Cost | D1: Name of period | E1: Amount | F1: Total Cost | H1: Date | I1: Total Technology Cost
A2: 1830 | B2: =$I$2*(1-(A2-1830)*2/300) -> 244800 | D2: 1830 first | E2: 25 x 3600 | F2: 90000 | H2: 1830 | I2: =IF(H23="Yes",SUM(F2,F3,F4),SUM(F3,F4)) -> 244800
A3: 1831 | B3: =$I$2*(1-(A3-1830)*2/300) -> 243168 | D3: 1830 second | E3: 22 x 7200 | F3: 158400 | H3: 1840 | I3: =SUM(F5,F6) -> 32400
A4: 1832 | B4: =$I$2*(1-(A4-1830)*2/300) -> 241536 | D4: 1830 third | E4: 8 x 10800 | F4: 86400 | H4: 1848 | I4: =SUM(F7) -> 10800
A5: 1833 | B5: =$I$2*(1-(A5-1830)*2/300) -> 239904 | D5: 1840 second | E5: 3 x 7200 | F5: 21600 | H5: 1850 | I5: =SUM(F8,F9) -> 259200
A6: 1834 | B6: =$I$2*(1-(A6-1830)*2/300) -> 238272 | D6: 1840 third | E6: 1 x 10800 | F6: 10800 | H6: 1855 | I6: =SUM(F10) -> 21600
A7: 1835 | B7: =$I$2*(1-(A7-1830)*2/300) -> 236640 | D7: 1848 third | E7: 1 x 10800 | F7: 10800 | H7: 1860 | I7: =SUM(F11) -> 10800
A8: 1836 | B8: =$I$2*(1-(A8-1830)*2/300) -> 235008 | D8: 1850 third | E8: 12 x 10800 | F8: 129600 | H8: 1870 | I8: =SUM(F12,F13) -> 331200
A9: 1837 | B9: =$I$2*(1-(A9-1830)*2/300) -> 233376 | D9: 1850 fourth | E9: 9 x 14400 | F9: 129600 | H9: 1872 | I9: =SUM(F14) -> 14400
A10: 1838 | B10: =$I$2*(1-(A10-1830)*2/300) -> 231744 | D10: 1855 third | E10: 2 x 10800 | F10: 21600 | H10: 1875 | I10: =SUM(F15) -> 14400
A11: 1839 | B11: =$I$2*(1-(A11-1830)*2/300) -> 230112 | D11: 1860 third | E11: 1 x 10800 | F11: 10800 | H11: 1880 | I11: =SUM(F16,F17) -> 50400
A12: 1840 | B12: =$I$2*(1-(A12-1830)*2/300)+$I$3*(1-(A12-1840)*2/300) -> 260880 | D12: 1870 fourth | E12: 13 x 14400 | F12: 187200 | H12: 1890 | I12: =SUM(F18) -> 54000
A13: 1841 | B13: =$I$2*(1-(A13-1830)*2/300)+$I$3*(1-(A13-1840)*2/300) -> 259032 | D13: 1870 fifth | E13: 8 x 18000 | F13: 144000 | H13: 1895 | I13: =SUM(F19) -> 18000
A14: 1842 | B14: =$I$2*(1-(A14-1830)*2/300)+$I$3*(1-(A14-1840)*2/300) -> 257184 | D14: 1872 fourth | E14: 1 x 14400 | F14: 14400 | H14: 1898 | I14: =SUM(F20) -> 18000
A15: 1843 | B15: =$I$2*(1-(A15-1830)*2/300)+$I$3*(1-(A15-1840)*2/300) -> 255336 | D15: 1875 fourth | E15: 1 x 14400 | F15: 14400 | H15: 1900 | I15: =SUM(F21,F22) -> 255600
A16: 1844 | B16: =$I$2*(1-(A16-1830)*2/300)+$I$3*(1-(A16-1840)*2/300) -> 253488 | D16: 1880 fourth | E16: 1 x 14400 | F16: 14400 | H16: 1905 | I16: =SUM(F23) -> 21600
A17: 1845 | B17: =$I$2*(1-(A17-1830)*2/300)+$I$3*(1-(A17-1840)*2/300) -> 251640 | D17: 1880 fifth | E17: 2 x 18000 | F17: 36000 | H17: 1910 | I17: =SUM(F24) -> 21600
A18: 1846 | B18: =$I$2*(1-(A18-1830)*2/300)+$I$3*(1-(A18-1840)*2/300) -> 249792 | D18: 1890 fifth | E18: 3 x 18000 | F18: 54000 | H18: 1914 | I18: =SUM(F25) -> 43200
A19: 1847 | B19: =$I$2*(1-(A19-1830)*2/300)+$I$3*(1-(A19-1840)*2/300) -> 247944 | D19: 1895 fifth | E19: 1 x 18000 | F19: 18000 | H19: 1915 | I19: =SUM(F26) -> 21600
A20: 1848 | B20: =$I$2*(1-(A20-1830)*2/300)+$I$3*(1-(A20-1840)*2/300)+$I$4*(1-(A20-1848)*2/300) -> 256896 | D20: 1898 fifth | E20: 1 x 18000 | F20: 18000 | H20: 1919 | I20: =SUM(F27) -> 194400
A21: 1849 | B21: =$I$2*(1-(A21-1830)*2/300)+$I$3*(1-(A21-1840)*2/300)+$I$4*(1-(A21-1848)*2/300) -> 254976 | D21: 1900 fifth | E21: 10 x 1800 | F21: 18000 | H21: SUM | I21: =SUM(I2:I20) -> 1638000
A22: 1850 | B22: =$I$2*(1-(A22-1830)*2/300)+$I$3*(1-(A22-1840)*2/300)+$I$4*(1-(A22-1848)*2/300)+$I$5*(1-(A22-1850)*2/300) -> 512256 | D22: 1900 sixth | E22: 11 x 21600 | F22: 237600
A23: 1851 | B23: =$I$2*(1-(A23-1830)*2/300)+$I$3*(1-(A23-1840)*2/300)+$I$4*(1-(A23-1848)*2/300)+$I$5*(1-(A23-1850)*2/300) -> 508608 | D23: 1905 sixth | E23: 1 x 21600 | F23: 21600 | H23: No | I23: Inc. base techs?
A24: 1852 | B24: =$I$2*(1-(A24-1830)*2/300)+$I$3*(1-(A24-1840)*2/300)+$I$4*(1-(A24-1848)*2/300)+$I$5*(1-(A24-1850)*2/300) -> 504960 | D24: 1910 sixth | E24: 1 x 21600 | F24: 21600
A25: 1853 | B25: =$I$2*(1-(A25-1830)*2/300)+$I$3*(1-(A25-1840)*2/300)+$I$4*(1-(A25-1848)*2/300)+$I$5*(1-(A25-1850)*2/300) -> 501312 | D25: 1914 sixth | E25: 2 x 21600 | F25: 43200
A26: 1854 | B26: =$I$2*(1-(A26-1830)*2/300)+$I$3*(1-(A26-1840)*2/300)+$I$4*(1-(A26-1848)*2/300)+$I$5*(1-(A26-1850)*2/300) -> 497664 | D26: 1915 sixth | E26: 1 x 21600 | F26: 21600
A27: 1855 | B27: =$I$2*(1-(A27-1830)*2/300)+$I$3*(1-(A27-1840)*2/300)+$I$4*(1-(A27-1848)*2/300)+$I$5*(1-(A27-1850)*2/300)+$I$6*(1-(A27-1855)*2/300) -> 515616 | D27: 1919 sixth | E27: 9 x 21600 | F27: 194400
A28: 1856 | B28: =$I$2*(1-(A28-1830)*2/300)+$I$3*(1-(A28-1840)*2/300)+$I$4*(1-(A28-1848)*2/300)+$I$5*(1-(A28-1850)*2/300)+$I$6*(1-(A28-1855)*2/300) -> 511824
A29: 1857 | B29: =$I$2*(1-(A29-1830)*2/300)+$I$3*(1-(A29-1840)*2/300)+$I$4*(1-(A29-1848)*2/300)+$I$5*(1-(A29-1850)*2/300)+$I$6*(1-(A29-1855)*2/300) -> 508032
A30: 1858 | B30: =$I$2*(1-(A30-1830)*2/300)+$I$3*(1-(A30-1840)*2/300)+$I$4*(1-(A30-1848)*2/300)+$I$5*(1-(A30-1850)*2/300)+$I$6*(1-(A30-1855)*2/300) -> 504240
A31: 1859 | B31: =$I$2*(1-(A31-1830)*2/300)+$I$3*(1-(A31-1840)*2/300)+$I$4*(1-(A31-1848)*2/300)+$I$5*(1-(A31-1850)*2/300)+$I$6*(1-(A31-1855)*2/300) -> 500448
A32: 1860 | B32: =$I$2*(1-(A32-1830)*2/300)+$I$3*(1-(A32-1840)*2/300)+$I$4*(1-(A32-1848)*2/300)+$I$5*(1-(A32-1850)*2/300)+$I$6*(1-(A32-1855)*2/300)+$I$2*(1-(A32-1860)*2/300) -> 741456
A33: 1861 | B33: =$I$2*(1-(A33-1830)*2/300)+$I$3*(1-(A33-1840)*2/300)+$I$4*(1-(A33-1848)*2/300)+$I$5*(1-(A33-1850)*2/300)+$I$6*(1-(A33-1855)*2/300)+$I$2*(1-(A33-1860)*2/300) -> 736032
A34: 1862 | B34: =$I$2*(1-(A34-1830)*2/300)+$I$3*(1-(A34-1840)*2/300)+$I$4*(1-(A34-1848)*2/300)+$I$5*(1-(A34-1850)*2/300)+$I$6*(1-(A34-1855)*2/300)+$I$2*(1-(A34-1860)*2/300) -> 730608
A35: 1863 | B35: =$I$2*(1-(A35-1830)*2/300)+$I$3*(1-(A35-1840)*2/300)+$I$4*(1-(A35-1848)*2/300)+$I$5*(1-(A35-1850)*2/300)+$I$6*(1-(A35-1855)*2/300)+$I$2*(1-(A35-1860)*2/300) -> 725184
A36: 1864 | B36: =$I$2*(1-(A36-1830)*2/300)+$I$3*(1-(A36-1840)*2/300)+$I$4*(1-(A36-1848)*2/300)+$I$5*(1-(A36-1850)*2/300)+$I$6*(1-(A36-1855)*2/300)+$I$2*(1-(A36-1860)*2/300) -> 719760
A37: 1865 | B37: =$I$2*(1-(A37-1830)*2/300)+$I$3*(1-(A37-1840)*2/300)+$I$4*(1-(A37-1848)*2/300)+$I$5*(1-(A37-1850)*2/300)+$I$6*(1-(A37-1855)*2/300)+$I$2*(1-(A37-1860)*2/300) -> 714336
A38: 1866 | B38: =$I$2*(1-(A38-1830)*2/300)+$I$3*(1-(A38-1840)*2/300)+$I$4*(1-(A38-1848)*2/300)+$I$5*(1-(A38-1850)*2/300)+$I$6*(1-(A38-1855)*2/300)+$I$2*(1-(A38-1860)*2/300) -> 708912
A39: 1867 | B39: =$I$2*(1-(A39-1830)*2/300)+$I$3*(1-(A39-1840)*2/300)+$I$4*(1-(A39-1848)*2/300)+$I$5*(1-(A39-1850)*2/300)+$I$6*(1-(A39-1855)*2/300)+$I$2*(1-(A39-1860)*2/300) -> 703488
A40: 1868 | B40: =$I$2*(1-(A40-1830)*2/300)+$I$3*(1-(A40-1840)*2/300)+$I$4*(1-(A40-1848)*2/300)+$I$5*(1-(A40-1850)*2/300)+$I$6*(1-(A40-1855)*2/300)+$I$2*(1-(A40-1860)*2/300) -> 698064
A41: 1869 | B41: =$I$2*(1-(A41-1830)*2/300)+$I$3*(1-(A41-1840)*2/300)+$I$4*(1-(A41-1848)*2/300)+$I$5*(1-(A41-1850)*2/300)+$I$6*(1-(A41-1855)*2/300)+$I$2*(1-(A41-1860)*2/300) -> 692640
A42: 1870 | B42: =$I$2*(1-(A42-1830)*2/300)+$I$3*(1-(A42-1840)*2/300)+$I$4*(1-(A42-1848)*2/300)+$I$5*(1-(A42-1850)*2/300)+$I$6*(1-(A42-1855)*2/300)+$I$7*(1-(A42-1860)*2/300)+$I$8*(1-(A42-1870)*2/300) -> 800016
A43: 1871 | B43: =$I$2*(1-(A43-1830)*2/300)+$I$3*(1-(A43-1840)*2/300)+$I$4*(1-(A43-1848)*2/300)+$I$5*(1-(A43-1850)*2/300)+$I$6*(1-(A43-1855)*2/300)+$I$7*(1-(A43-1860)*2/300)+$I$8*(1-(A43-1870)*2/300) -> 793944
A44: 1872 | B44: =$I$2*(1-(A44-1830)*2/300)+$I$3*(1-(A44-1840)*2/300)+$I$4*(1-(A44-1848)*2/300)+$I$5*(1-(A44-1850)*2/300)+$I$6*(1-(A44-1855)*2/300)+$I$7*(1-(A44-1860)*2/300)+$I$8*(1-(A44-1870)*2/300)+$I$9*(1-(A44-1872)*2/300) -> 802272
A45: 1873 | B45: =$I$2*(1-(A45-1830)*2/300)+$I$3*(1-(A45-1840)*2/300)+$I$4*(1-(A45-1848)*2/300)+$I$5*(1-(A45-1850)*2/300)+$I$6*(1-(A45-1855)*2/300)+$I$7*(1-(A45-1860)*2/300)+$I$8*(1-(A45-1870)*2/300)+$I$9*(1-(A45-1872)*2/300) -> 796104
A46: 1874 | B46: =$I$2*(1-(A46-1830)*2/300)+$I$3*(1-(A46-1840)*2/300)+$I$4*(1-(A46-1848)*2/300)+$I$5*(1-(A46-1850)*2/300)+$I$6*(1-(A46-1855)*2/300)+$I$7*(1-(A46-1860)*2/300)+$I$8*(1-(A46-1870)*2/300)+$I$9*(1-(A46-1872)*2/300) -> 789936
A47: 1875 | B47: =$I$2*(1-(A47-1830)*2/300)+$I$3*(1-(A47-1840)*2/300)+$I$4*(1-(A47-1848)*2/300)+$I$5*(1-(A47-1850)*2/300)+$I$6*(1-(A47-1855)*2/300)+$I$7*(1-(A47-1860)*2/300)+$I$8*(1-(A47-1870)*2/300)+$I$9*(1-(A47-1872)*2/300)+$I$10*(1-(A47-1875)*2/300) -> 798168
A48: 1876 | B48: =$I$2*(1-(A48-1830)*2/300)+$I$3*(1-(A48-1840)*2/300)+$I$4*(1-(A48-1848)*2/300)+$I$5*(1-(A48-1850)*2/300)+$I$6*(1-(A48-1855)*2/300)+$I$7*(1-(A48-1860)*2/300)+$I$8*(1-(A48-1870)*2/300)+$I$9*(1-(A48-1872)*2/300)+$I$10*(1-(A48-1875)*2/300) -> 791904
A49: 1877 | B49: =$I$2*(1-(A49-1830)*2/300)+$I$3*(1-(A49-1840)*2/300)+$I$4*(1-(A49-1848)*2/300)+$I$5*(1-(A49-1850)*2/300)+$I$6*(1-(A49-1855)*2/300)+$I$7*(1-(A49-1860)*2/300)+$I$8*(1-(A49-1870)*2/300)+$I$9*(1-(A49-1872)*2/300)+$I$10*(1-(A49-1875)*2/300) -> 785640
A50: 1878 | B50: =$I$2*(1-(A50-1830)*2/300)+$I$3*(1-(A50-1840)*2/300)+$I$4*(1-(A50-1848)*2/300)+$I$5*(1-(A50-1850)*2/300)+$I$6*(1-(A50-1855)*2/300)+$I$7*(1-(A50-1860)*2/300)+$I$8*(1-(A50-1870)*2/300)+$I$9*(1-(A50-1872)*2/300)+$I$10*(1-(A50-1875)*2/300) -> 779376
A51: 1879 | B51: =$I$2*(1-(A51-1830)*2/300)+$I$3*(1-(A51-1840)*2/300)+$I$4*(1-(A51-1848)*2/300)+$I$5*(1-(A51-1850)*2/300)+$I$6*(1-(A51-1855)*2/300)+$I$7*(1-(A51-1860)*2/300)+$I$8*(1-(A51-1870)*2/300)+$I$9*(1-(A51-1872)*2/300)+$I$10*(1-(A51-1875)*2/300) -> 773112
A52: 1880 | B52: =$I$2*(1-(A52-1830)*2/300)+$I$3*(1-(A52-1840)*2/300)+$I$4*(1-(A52-1848)*2/300)+$I$5*(1-(A52-1850)*2/300)+$I$6*(1-(A52-1855)*2/300)+$I$7*(1-(A52-1860)*2/300)+$I$8*(1-(A52-1870)*2/300)+$I$9*(1-(A52-1872)*2/300)+$I$10*(1-(A52-1875)*2/300)+$I$11*(1-(A52-1880)*2/300) -> 817248
A53: 1881 | B53: =$I$2*(1-(A53-1830)*2/300)+$I$3*(1-(A53-1840)*2/300)+$I$4*(1-(A53-1848)*2/300)+$I$5*(1-(A53-1850)*2/300)+$I$6*(1-(A53-1855)*2/300)+$I$7*(1-(A53-1860)*2/300)+$I$8*(1-(A53-1870)*2/300)+$I$9*(1-(A53-1872)*2/300)+$I$10*(1-(A53-1875)*2/300)+$I$11*(1-(A53-1880)*2/300) -> 810648
A54: 1882 | B54: =$I$2*(1-(A54-1830)*2/300)+$I$3*(1-(A54-1840)*2/300)+$I$4*(1-(A54-1848)*2/300)+$I$5*(1-(A54-1850)*2/300)+$I$6*(1-(A54-1855)*2/300)+$I$7*(1-(A54-1860)*2/300)+$I$8*(1-(A54-1870)*2/300)+$I$9*(1-(A54-1872)*2/300)+$I$10*(1-(A54-1875)*2/300)+$I$11*(1-(A54-1880)*2/300) -> 804048
A55: 1883 | B55: =$I$2*(1-(A55-1830)*2/300)+$I$3*(1-(A55-1840)*2/300)+$I$4*(1-(A55-1848)*2/300)+$I$5*(1-(A55-1850)*2/300)+$I$6*(1-(A55-1855)*2/300)+$I$7*(1-(A55-1860)*2/300)+$I$8*(1-(A55-1870)*2/300)+$I$9*(1-(A55-1872)*2/300)+$I$10*(1-(A55-1875)*2/300)+$I$11*(1-(A55-1880)*2/300) -> 797448
A56: 1884 | B56: =$I$2*(1-(A56-1830)*2/300)+$I$3*(1-(A56-1840)*2/300)+$I$4*(1-(A56-1848)*2/300)+$I$5*(1-(A56-1850)*2/300)+$I$6*(1-(A56-1855)*2/300)+$I$7*(1-(A56-1860)*2/300)+$I$8*(1-(A56-1870)*2/300)+$I$9*(1-(A56-1872)*2/300)+$I$10*(1-(A56-1875)*2/300)+$I$11*(1-(A56-1880)*2/300) -> 790848
A57: 1885 | B57: =$I$2*(1-(A57-1830)*2/300)+$I$3*(1-(A57-1840)*2/300)+$I$4*(1-(A57-1848)*2/300)+$I$5*(1-(A57-1850)*2/300)+$I$6*(1-(A57-1855)*2/300)+$I$7*(1-(A57-1860)*2/300)+$I$8*(1-(A57-1870)*2/300)+$I$9*(1-(A57-1872)*2/300)+$I$10*(1-(A57-1875)*2/300)+$I$11*(1-(A57-1880)*2/300) -> 784248
A58: 1886 | B58: =$I$2*(1-(A58-1830)*2/300)+$I$3*(1-(A58-1840)*2/300)+$I$4*(1-(A58-1848)*2/300)+$I$5*(1-(A58-1850)*2/300)+$I$6*(1-(A58-1855)*2/300)+$I$7*(1-(A58-1860)*2/300)+$I$8*(1-(A58-1870)*2/300)+$I$9*(1-(A58-1872)*2/300)+$I$10*(1-(A58-1875)*2/300)+$I$11*(1-(A58-1880)*2/300) -> 777648
A59: 1887 | B59: =$I$2*(1-(A59-1830)*2/300)+$I$3*(1-(A59-1840)*2/300)+$I$4*(1-(A59-1848)*2/300)+$I$5*(1-(A59-1850)*2/300)+$I$6*(1-(A59-1855)*2/300)+$I$7*(1-(A59-1860)*2/300)+$I$8*(1-(A59-1870)*2/300)+$I$9*(1-(A59-1872)*2/300)+$I$10*(1-(A59-1875)*2/300)+$I$11*(1-(A59-1880)*2/300) -> 771048
A60: 1888 | B60: =$I$2*(1-(A60-1830)*2/300)+$I$3*(1-(A60-1840)*2/300)+$I$4*(1-(A60-1848)*2/300)+$I$5*(1-(A60-1850)*2/300)+$I$6*(1-(A60-1855)*2/300)+$I$7*(1-(A60-1860)*2/300)+$I$8*(1-(A60-1870)*2/300)+$I$9*(1-(A60-1872)*2/300)+$I$10*(1-(A60-1875)*2/300)+$I$11*(1-(A60-1880)*2/300) -> 764448
A61: 1889 | B61: =$I$2*(1-(A61-1830)*2/300)+$I$3*(1-(A61-1840)*2/300)+$I$4*(1-(A61-1848)*2/300)+$I$5*(1-(A61-1850)*2/300)+$I$6*(1-(A61-1855)*2/300)+$I$7*(1-(A61-1860)*2/300)+$I$8*(1-(A61-1870)*2/300)+$I$9*(1-(A61-1872)*2/300)+$I$10*(1-(A61-1875)*2/300)+$I$11*(1-(A61-1880)*2/300) -> 757848
A62: 1890 | B62: =$I$2*(1-(A62-1830)*2/300)+$I$3*(1-(A62-1840)*2/300)+$I$4*(1-(A62-1848)*2/300)+$I$5*(1-(A62-1850)*2/300)+$I$6*(1-(A62-1855)*2/300)+$I$7*(1-(A62-1860)*2/300)+$I$8*(1-(A62-1870)*2/300)+$I$9*(1-(A62-1872)*2/300)+$I$10*(1-(A62-1875)*2/300)+$I$11*(1-(A62-1880)*2/300)+$I$12*(1-(A62-1890)*2/300) -> 805248
A63: 1891 | B63: =$I$2*(1-(A63-1830)*2/300)+$I$3*(1-(A63-1840)*2/300)+$I$4*(1-(A63-1848)*2/300)+$I$5*(1-(A63-1850)*2/300)+$I$6*(1-(A63-1855)*2/300)+$I$7*(1-(A63-1860)*2/300)+$I$8*(1-(A63-1870)*2/300)+$I$9*(1-(A63-1872)*2/300)+$I$10*(1-(A63-1875)*2/300)+$I$11*(1-(A63-1880)*2/300)+$I$12*(1-(A63-1890)*2/300) -> 798288
A64: 1892 | B64: =$I$2*(1-(A64-1830)*2/300)+$I$3*(1-(A64-1840)*2/300)+$I$4*(1-(A64-1848)*2/300)+$I$5*(1-(A64-1850)*2/300)+$I$6*(1-(A64-1855)*2/300)+$I$7*(1-(A64-1860)*2/300)+$I$8*(1-(A64-1870)*2/300)+$I$9*(1-(A64-1872)*2/300)+$I$10*(1-(A64-1875)*2/300)+$I$11*(1-(A64-1880)*2/300)+$I$12*(1-(A64-1890)*2/300) -> 791328
A65: 1893 | B65: =$I$2*(1-(A65-1830)*2/300)+$I$3*(1-(A65-1840)*2/300)+$I$4*(1-(A65-1848)*2/300)+$I$5*(1-(A65-1850)*2/300)+$I$6*(1-(A65-1855)*2/300)+$I$7*(1-(A65-1860)*2/300)+$I$8*(1-(A65-1870)*2/300)+$I$9*(1-(A65-1872)*2/300)+$I$10*(1-(A65-1875)*2/300)+$I$11*(1-(A65-1880)*2/300)+$I$12*(1-(A65-1890)*2/300) -> 784368
A66: 1894 | B66: =$I$2*(1-(A66-1830)*2/300)+$I$3*(1-(A66-1840)*2/300)+$I$4*(1-(A66-1848)*2/300)+$I$5*(1-(A66-1850)*2/300)+$I$6*(1-(A66-1855)*2/300)+$I$7*(1-(A66-1860)*2/300)+$I$8*(1-(A66-1870)*2/300)+$I$9*(1-(A66-1872)*2/300)+$I$10*(1-(A66-1875)*2/300)+$I$11*(1-(A66-1880)*2/300)+$I$12*(1-(A66-1890)*2/300) -> 777408
A67: 1895 | B67: =$I$2*(1-(A67-1830)*2/300)+$I$3*(1-(A67-1840)*2/300)+$I$4*(1-(A67-1848)*2/300)+$I$5*(1-(A67-1850)*2/300)+$I$6*(1-(A67-1855)*2/300)+$I$7*(1-(A67-1860)*2/300)+$I$8*(1-(A67-1870)*2/300)+$I$9*(1-(A67-1872)*2/300)+$I$10*(1-(A67-1875)*2/300)+$I$11*(1-(A67-1880)*2/300)+$I$12*(1-(A67-1890)*2/300)+$I$13*(1-(A67-1895)*2/300) -> 788448
A68: 1896 | B68: =$I$2*(1-(A68-1830)*2/300)+$I$3*(1-(A68-1840)*2/300)+$I$4*(1-(A68-1848)*2/300)+$I$5*(1-(A68-1850)*2/300)+$I$6*(1-(A68-1855)*2/300)+$I$7*(1-(A68-1860)*2/300)+$I$8*(1-(A68-1870)*2/300)+$I$9*(1-(A68-1872)*2/300)+$I$10*(1-(A68-1875)*2/300)+$I$11*(1-(A68-1880)*2/300)+$I$12*(1-(A68-1890)*2/300)+$I$13*(1-(A68-1895)*2/300) -> 781368
A69: 1897 | B69: =$I$2*(1-(A69-1830)*2/300)+$I$3*(1-(A69-1840)*2/300)+$I$4*(1-(A69-1848)*2/300)+$I$5*(1-(A69-1850)*2/300)+$I$6*(1-(A69-1855)*2/300)+$I$7*(1-(A69-1860)*2/300)+$I$8*(1-(A69-1870)*2/300)+$I$9*(1-(A69-1872)*2/300)+$I$10*(1-(A69-1875)*2/300)+$I$11*(1-(A69-1880)*2/300)+$I$12*(1-(A69-1890)*2/300)+$I$13*(1-(A69-1895)*2/300) -> 774288
A70: 1898 | B70: =$I$2*(1-(A70-1830)*2/300)+$I$3*(1-(A70-1840)*2/300)+$I$4*(1-(A70-1848)*2/300)+$I$5*(1-(A70-1850)*2/300)+$I$6*(1-(A70-1855)*2/300)+$I$7*(1-(A70-1860)*2/300)+$I$8*(1-(A70-1870)*2/300)+$I$9*(1-(A70-1872)*2/300)+$I$10*(1-(A70-1875)*2/300)+$I$11*(1-(A70-1880)*2/300)+$I$12*(1-(A70-1890)*2/300)+$I$13*(1-(A70-1895)*2/300)+$I$14*(1-(A70-1898)*2/300) -> 785208
A71: 1899 | B71: =$I$2*(1-(A71-1830)*2/300)+$I$3*(1-(A71-1840)*2/300)+$I$4*(1-(A71-1848)*2/300)+$I$5*(1-(A71-1850)*2/300)+$I$6*(1-(A71-1855)*2/300)+$I$7*(1-(A71-1860)*2/300)+$I$8*(1-(A71-1870)*2/300)+$I$9*(1-(A71-1872)*2/300)+$I$10*(1-(A71-1875)*2/300)+$I$11*(1-(A71-1880)*2/300)+$I$12*(1-(A71-1890)*2/300)+$I$13*(1-(A71-1895)*2/300)+$I$14*(1-(A71-1898)*2/300) -> 778008
A72: 1900 | B72: =$I$2*(1-(A72-1830)*2/300)+$I$3*(1-(A72-1840)*2/300)+$I$4*(1-(A72-1848)*2/300)+$I$5*(1-(A72-1850)*2/300)+$I$6*(1-(A72-1855)*2/300)+$I$7*(1-(A72-1860)*2/300)+$I$8*(1-(A72-1870)*2/300)+$I$9*(1-(A72-1872)*2/300)+$I$10*(1-(A72-1875)*2/300)+$I$11*(1-(A72-1880)*2/300)+$I$12*(1-(A72-1890)*2/300)+$I$13*(1-(A72-1895)*2/300)+$I$14*(1-(A72-1898)*2/300)+$I$15*(1-(A72-1900)*2/300) -> 1026408
A73: 1901 | B73: =$I$2*(1-(A73-1830)*2/300)+$I$3*(1-(A73-1840)*2/300)+$I$4*(1-(A73-1848)*2/300)+$I$5*(1-(A73-1850)*2/300)+$I$6*(1-(A73-1855)*2/300)+$I$7*(1-(A73-1860)*2/300)+$I$8*(1-(A73-1870)*2/300)+$I$9*(1-(A73-1872)*2/300)+$I$10*(1-(A73-1875)*2/300)+$I$11*(1-(A73-1880)*2/300)+$I$12*(1-(A73-1890)*2/300)+$I$13*(1-(A73-1895)*2/300)+$I$14*(1-(A73-1898)*2/300)+$I$15*(1-(A73-1900)*2/300) -> 1017504
A74: 1902 | B74: =$I$2*(1-(A74-1830)*2/300)+$I$3*(1-(A74-1840)*2/300)+$I$4*(1-(A74-1848)*2/300)+$I$5*(1-(A74-1850)*2/300)+$I$6*(1-(A74-1855)*2/300)+$I$7*(1-(A74-1860)*2/300)+$I$8*(1-(A74-1870)*2/300)+$I$9*(1-(A74-1872)*2/300)+$I$10*(1-(A74-1875)*2/300)+$I$11*(1-(A74-1880)*2/300)+$I$12*(1-(A74-1890)*2/300)+$I$13*(1-(A74-1895)*2/300)+$I$14*(1-(A74-1898)*2/300)+$I$15*(1-(A74-1900)*2/300) -> 1008600
A75: 1903 | B75: =$I$2*(1-(A75-1830)*2/300)+$I$3*(1-(A75-1840)*2/300)+$I$4*(1-(A75-1848)*2/300)+$I$5*(1-(A75-1850)*2/300)+$I$6*(1-(A75-1855)*2/300)+$I$7*(1-(A75-1860)*2/300)+$I$8*(1-(A75-1870)*2/300)+$I$9*(1-(A75-1872)*2/300)+$I$10*(1-(A75-1875)*2/300)+$I$11*(1-(A75-1880)*2/300)+$I$12*(1-(A75-1890)*2/300)+$I$13*(1-(A75-1895)*2/300)+$I$14*(1-(A75-1898)*2/300)+$I$15*(1-(A75-1900)*2/300) -> 999696
A76: 1904 | B76: =$I$2*(1-(A76-1830)*2/300)+$I$3*(1-(A76-1840)*2/300)+$I$4*(1-(A76-1848)*2/300)+$I$5*(1-(A76-1850)*2/300)+$I$6*(1-(A76-1855)*2/300)+$I$7*(1-(A76-1860)*2/300)+$I$8*(1-(A76-1870)*2/300)+$I$9*(1-(A76-1872)*2/300)+$I$10*(1-(A76-1875)*2/300)+$I$11*(1-(A76-1880)*2/300)+$I$12*(1-(A76-1890)*2/300)+$I$13*(1-(A76-1895)*2/300)+$I$14*(1-(A76-1898)*2/300)+$I$15*(1-(A76-1900)*2/300) -> 990792
A77: 1905 | B77: =$I$2*(1-(A77-1830)*2/300)+$I$3*(1-(A77-1840)*2/300)+$I$4*(1-(A77-1848)*2/300)+$I$5*(1-(A77-1850)*2/300)+$I$6*(1-(A77-1855)*2/300)+$I$7*(1-(A77-1860)*2/300)+$I$8*(1-(A77-1870)*2/300)+$I$9*(1-(A77-1872)*2/300)+$I$10*(1-(A77-1875)*2/300)+$I$11*(1-(A77-1880)*2/300)+$I$12*(1-(A77-1890)*2/300)+$I$13*(1-(A77-1895)*2/300)+$I$14*(1-(A77-1898)*2/300)+$I$15*(1-(A77-1900)*2/300)+$I$16*(1-(A77-1905)*2/300) -> 1003488
A78: 1906 | B78: =$I$2*(1-(A78-1830)*2/300)+$I$3*(1-(A78-1840)*2/300)+$I$4*(1-(A78-1848)*2/300)+$I$5*(1-(A78-1850)*2/300)+$I$6*(1-(A78-1855)*2/300)+$I$7*(1-(A78-1860)*2/300)+$I$8*(1-(A78-1870)*2/300)+$I$9*(1-(A78-1872)*2/300)+$I$10*(1-(A78-1875)*2/300)+$I$11*(1-(A78-1880)*2/300)+$I$12*(1-(A78-1890)*2/300)+$I$13*(1-(A78-1895)*2/300)+$I$14*(1-(A78-1898)*2/300)+$I$15*(1-(A78-1900)*2/300)+$I$16*(1-(A78-1905)*2/300) -> 994440
A79: 1907 | B79: =$I$2*(1-(A79-1830)*2/300)+$I$3*(1-(A79-1840)*2/300)+$I$4*(1-(A79-1848)*2/300)+$I$5*(1-(A79-1850)*2/300)+$I$6*(1-(A79-1855)*2/300)+$I$7*(1-(A79-1860)*2/300)+$I$8*(1-(A79-1870)*2/300)+$I$9*(1-(A79-1872)*2/300)+$I$10*(1-(A79-1875)*2/300)+$I$11*(1-(A79-1880)*2/300)+$I$12*(1-(A79-1890)*2/300)+$I$13*(1-(A79-1895)*2/300)+$I$14*(1-(A79-1898)*2/300)+$I$15*(1-(A79-1900)*2/300)+$I$16*(1-(A79-1905)*2/300) -> 985392
A80: 1908 | B80: =$I$2*(1-(A80-1830)*2/300)+$I$3*(1-(A80-1840)*2/300)+$I$4*(1-(A80-1848)*2/300)+$I$5*(1-(A80-1850)*2/300)+$I$6*(1-(A80-1855)*2/300)+$I$7*(1-(A80-1860)*2/300)+$I$8*(1-(A80-1870)*2/300)+$I$9*(1-(A80-1872)*2/300)+$I$10*(1-(A80-1875)*2/300)+$I$11*(1-(A80-1880)*2/300)+$I$12*(1-(A80-1890)*2/300)+$I$13*(1-(A80-1895)*2/300)+$I$14*(1-(A80-1898)*2/300)+$I$15*(1-(A80-1900)*2/300)+$I$16*(1-(A80-1905)*2/300) -> 976344
A81: 1909 | B81: =$I$2*(1-(A81-1830)*2/300)+$I$3*(1-(A81-1840)*2/300)+$I$4*(1-(A81-1848)*2/300)+$I$5*(1-(A81-1850)*2/300)+$I$6*(1-(A81-1855)*2/300)+$I$7*(1-(A81-1860)*2/300)+$I$8*(1-(A81-1870)*2/300)+$I$9*(1-(A81-1872)*2/300)+$I$10*(1-(A81-1875)*2/300)+$I$11*(1-(A81-1880)*2/300)+$I$12*(1-(A81-1890)*2/300)+$I$13*(1-(A81-1895)*2/300)+$I$14*(1-(A81-1898)*2/300)+$I$15*(1-(A81-1900)*2/300)+$I$16*(1-(A81-1905)*2/300) -> 967296
A82: 1910 | B82: =$I$2*(1-(A82-1830)*2/300)+$I$3*(1-(A82-1840)*2/300)+$I$4*(1-(A82-1848)*2/300)+$I$5*(1-(A82-1850)*2/300)+$I$6*(1-(A82-1855)*2/300)+$I$7*(1-(A82-1860)*2/300)+$I$8*(1-(A82-1870)*2/300)+$I$9*(1-(A82-1872)*2/300)+$I$10*(1-(A82-1875)*2/300)+$I$11*(1-(A82-1880)*2/300)+$I$12*(1-(A82-1890)*2/300)+$I$13*(1-(A82-1895)*2/300)+$I$14*(1-(A82-1898)*2/300)+$I$15*(1-(A82-1900)*2/300)+$I$16*(1-(A82-1905)*2/300)+$I$17*(1-(A82-1910)*2/300) -> 979848
A83: 1911 | B83: =$I$2*(1-(A83-1830)*2/300)+$I$3*(1-(A83-1840)*2/300)+$I$4*(1-(A83-1848)*2/300)+$I$5*(1-(A83-1850)*2/300)+$I$6*(1-(A83-1855)*2/300)+$I$7*(1-(A83-1860)*2/300)+$I$8*(1-(A83-1870)*2/300)+$I$9*(1-(A83-1872)*2/300)+$I$10*(1-(A83-1875)*2/300)+$I$11*(1-(A83-1880)*2/300)+$I$12*(1-(A83-1890)*2/300)+$I$13*(1-(A83-1895)*2/300)+$I$14*(1-(A83-1898)*2/300)+$I$15*(1-(A83-1900)*2/300)+$I$16*(1-(A83-1905)*2/300)+$I$17*(1-(A83-1910)*2/300) -> 970656
A84: 1912 | B84: =$I$2*(1-(A84-1830)*2/300)+$I$3*(1-(A84-1840)*2/300)+$I$4*(1-(A84-1848)*2/300)+$I$5*(1-(A84-1850)*2/300)+$I$6*(1-(A84-1855)*2/300)+$I$7*(1-(A84-1860)*2/300)+$I$8*(1-(A84-1870)*2/300)+$I$9*(1-(A84-1872)*2/300)+$I$10*(1-(A84-1875)*2/300)+$I$11*(1-(A84-1880)*2/300)+$I$12*(1-(A84-1890)*2/300)+$I$13*(1-(A84-1895)*2/300)+$I$14*(1-(A84-1898)*2/300)+$I$15*(1-(A84-1900)*2/300)+$I$16*(1-(A84-1905)*2/300)+$I$17*(1-(A84-1910)*2/300) -> 961464
A85: 1913 | B85: =$I$2*(1-(A85-1830)*2/300)+$I$3*(1-(A85-1840)*2/300)+$I$4*(1-(A85-1848)*2/300)+$I$5*(1-(A85-1850)*2/300)+$I$6*(1-(A85-1855)*2/300)+$I$7*(1-(A85-1860)*2/300)+$I$8*(1-(A85-1870)*2/300)+$I$9*(1-(A85-1872)*2/300)+$I$10*(1-(A85-1875)*2/300)+$I$11*(1-(A85-1880)*2/300)+$I$12*(1-(A85-1890)*2/300)+$I$13*(1-(A85-1895)*2/300)+$I$14*(1-(A85-1898)*2/300)+$I$15*(1-(A85-1900)*2/300)+$I$16*(1-(A85-1905)*2/300)+$I$17*(1-(A85-1910)*2/300) -> 952272
A86: 1914 | B86: =$I$2*(1-(A86-1830)*2/300)+$I$3*(1-(A86-1840)*2/300)+$I$4*(1-(A86-1848)*2/300)+$I$5*(1-(A86-1850)*2/300)+$I$6*(1-(A86-1855)*2/300)+$I$7*(1-(A86-1860)*2/300)+$I$8*(1-(A86-1870)*2/300)+$I$9*(1-(A86-1872)*2/300)+$I$10*(1-(A86-1875)*2/300)+$I$11*(1-(A86-1880)*2/300)+$I$12*(1-(A86-1890)*2/300)+$I$13*(1-(A86-1895)*2/300)+$I$14*(1-(A86-1898)*2/300)+$I$15*(1-(A86-1900)*2/300)+$I$16*(1-(A86-1905)*2/300)+$I$17*(1-(A86-1910)*2/300)+$I$18*(1-(A86-1914)*2/300) -> 986280
A87: 1915 | B87: =$I$2*(1-(A87-1830)*2/300)+$I$3*(1-(A87-1840)*2/300)+$I$4*(1-(A87-1848)*2/300)+$I$5*(1-(A87-1850)*2/300)+$I$6*(1-(A87-1855)*2/300)+$I$7*(1-(A87-1860)*2/300)+$I$8*(1-(A87-1870)*2/300)+$I$9*(1-(A87-1872)*2/300)+$I$10*(1-(A87-1875)*2/300)+$I$11*(1-(A87-1880)*2/300)+$I$12*(1-(A87-1890)*2/300)+$I$13*(1-(A87-1895)*2/300)+$I$14*(1-(A87-1898)*2/300)+$I$15*(1-(A87-1900)*2/300)+$I$16*(1-(A87-1905)*2/300)+$I$17*(1-(A87-1910)*2/300)+$I$18*(1-(A87-1914)*2/300)+$I$19*(1-(A87-1915)*2/300) -> 998400
A88: 1916 | B88: =$I$2*(1-(A88-1830)*2/300)+$I$3*(1-(A88-1840)*2/300)+$I$4*(1-(A88-1848)*2/300)+$I$5*(1-(A88-1850)*2/300)+$I$6*(1-(A88-1855)*2/300)+$I$7*(1-(A88-1860)*2/300)+$I$8*(1-(A88-1870)*2/300)+$I$9*(1-(A88-1872)*2/300)+$I$10*(1-(A88-1875)*2/300)+$I$11*(1-(A88-1880)*2/300)+$I$12*(1-(A88-1890)*2/300)+$I$13*(1-(A88-1895)*2/300)+$I$14*(1-(A88-1898)*2/300)+$I$15*(1-(A88-1900)*2/300)+$I$16*(1-(A88-1905)*2/300)+$I$17*(1-(A88-1910)*2/300)+$I$18*(1-(A88-1914)*2/300)+$I$19*(1-(A88-1915)*2/300) -> 988776
A89: 1917 | B89: =$I$2*(1-(A89-1830)*2/300)+$I$3*(1-(A89-1840)*2/300)+$I$4*(1-(A89-1848)*2/300)+$I$5*(1-(A89-1850)*2/300)+$I$6*(1-(A89-1855)*2/300)+$I$7*(1-(A89-1860)*2/300)+$I$8*(1-(A89-1870)*2/300)+$I$9*(1-(A89-1872)*2/300)+$I$10*(1-(A89-1875)*2/300)+$I$11*(1-(A89-1880)*2/300)+$I$12*(1-(A89-1890)*2/300)+$I$13*(1-(A89-1895)*2/300)+$I$14*(1-(A89-1898)*2/300)+$I$15*(1-(A89-1900)*2/300)+$I$16*(1-(A89-1905)*2/300)+$I$17*(1-(A89-1910)*2/300)+$I$18*(1-(A89-1914)*2/300)+$I$19*(1-(A89-1915)*2/300) -> 979152
A90: 1918 | B90: =$I$2*(1-(A90-1830)*2/300)+$I$3*(1-(A90-1840)*2/300)+$I$4*(1-(A90-1848)*2/300)+$I$5*(1-(A90-1850)*2/300)+$I$6*(1-(A90-1855)*2/300)+$I$7*(1-(A90-1860)*2/300)+$I$8*(1-(A90-1870)*2/300)+$I$9*(1-(A90-1872)*2/300)+$I$10*(1-(A90-1875)*2/300)+$I$11*(1-(A90-1880)*2/300)+$I$12*(1-(A90-1890)*2/300)+$I$13*(1-(A90-1895)*2/300)+$I$14*(1-(A90-1898)*2/300)+$I$15*(1-(A90-1900)*2/300)+$I$16*(1-(A90-1905)*2/300)+$I$17*(1-(A90-1910)*2/300)+$I$18*(1-(A90-1914)*2/300)+$I$19*(1-(A90-1915)*2/300) -> 969528
A91: 1919 | B91: =$I$2*(1-(A91-1830)*2/300)+$I$3*(1-(A91-1840)*2/300)+$I$4*(1-(A91-1848)*2/300)+$I$5*(1-(A91-1850)*2/300)+$I$6*(1-(A91-1855)*2/300)+$I$7*(1-(A91-1860)*2/300)+$I$8*(1-(A91-1870)*2/300)+$I$9*(1-(A91-1872)*2/300)+$I$10*(1-(A91-1875)*2/300)+$I$11*(1-(A91-1880)*2/300)+$I$12*(1-(A91-1890)*2/300)+$I$13*(1-(A91-1895)*2/300)+$I$14*(1-(A91-1898)*2/300)+$I$15*(1-(A91-1900)*2/300)+$I$16*(1-(A91-1905)*2/300)+$I$17*(1-(A91-1910)*2/300)+$I$18*(1-(A91-1914)*2/300)+$I$19*(1-(A91-1915)*2/300)+$I$20*(1-(A91-1919)*2/300) -> 1154304
A92: 1920 | B92: =$I$2*(1-(A92-1830)*2/300)+$I$3*(1-(A92-1840)*2/300)+$I$4*(1-(A92-1848)*2/300)+$I$5*(1-(A92-1850)*2/300)+$I$6*(1-(A92-1855)*2/300)+$I$7*(1-(A92-1860)*2/300)+$I$8*(1-(A92-1870)*2/300)+$I$9*(1-(A92-1872)*2/300)+$I$10*(1-(A92-1875)*2/300)+$I$11*(1-(A92-1880)*2/300)+$I$12*(1-(A92-1890)*2/300)+$I$13*(1-(A92-1895)*2/300)+$I$14*(1-(A92-1898)*2/300)+$I$15*(1-(A92-1900)*2/300)+$I$16*(1-(A92-1905)*2/300)+$I$17*(1-(A92-1910)*2/300)+$I$18*(1-(A92-1914)*2/300)+$I$19*(1-(A92-1915)*2/300)+$I$20*(1-(A92-1919)*2/300) -> 1143384
A93: 1921 | B93: =$I$2*(1-(A93-1830)*2/300)+$I$3*(1-(A93-1840)*2/300)+$I$4*(1-(A93-1848)*2/300)+$I$5*(1-(A93-1850)*2/300)+$I$6*(1-(A93-1855)*2/300)+$I$7*(1-(A93-1860)*2/300)+$I$8*(1-(A93-1870)*2/300)+$I$9*(1-(A93-1872)*2/300)+$I$10*(1-(A93-1875)*2/300)+$I$11*(1-(A93-1880)*2/300)+$I$12*(1-(A93-1890)*2/300)+$I$13*(1-(A93-1895)*2/300)+$I$14*(1-(A93-1898)*2/300)+$I$15*(1-(A93-1900)*2/300)+$I$16*(1-(A93-1905)*2/300)+$I$17*(1-(A93-1910)*2/300)+$I$18*(1-(A93-1914)*2/300)+$I$19*(1-(A93-1915)*2/300)+$I$20*(1-(A93-1919)*2/300) -> 1132464
A94: 1922 | B94: =$I$2*(1-(A94-1830)*2/300)+$I$3*(1-(A94-1840)*2/300)+$I$4*(1-(A94-1848)*2/300)+$I$5*(1-(A94-1850)*2/300)+$I$6*(1-(A94-1855)*2/300)+$I$7*(1-(A94-1860)*2/300)+$I$8*(1-(A94-1870)*2/300)+$I$9*(1-(A94-1872)*2/300)+$I$10*(1-(A94-1875)*2/300)+$I$11*(1-(A94-1880)*2/300)+$I$12*(1-(A94-1890)*2/300)+$I$13*(1-(A94-1895)*2/300)+$I$14*(1-(A94-1898)*2/300)+$I$15*(1-(A94-1900)*2/300)+$I$16*(1-(A94-1905)*2/300)+$I$17*(1-(A94-1910)*2/300)+$I$18*(1-(A94-1914)*2/300)+$I$19*(1-(A94-1915)*2/300)+$I$20*(1-(A94-1919)*2/300) -> 1121544
A95: 1923 | B95: =$I$2*(1-(A95-1830)*2/300)+$I$3*(1-(A95-1840)*2/300)+$I$4*(1-(A95-1848)*2/300)+$I$5*(1-(A95-1850)*2/300)+$I$6*(1-(A95-1855)*2/300)+$I$7*(1-(A95-1860)*2/300)+$I$8*(1-(A95-1870)*2/300)+$I$9*(1-(A95-1872)*2/300)+$I$10*(1-(A95-1875)*2/300)+$I$11*(1-(A95-1880)*2/300)+$I$12*(1-(A95-1890)*2/300)+$I$13*(1-(A95-1895)*2/300)+$I$14*(1-(A95-1898)*2/300)+$I$15*(1-(A95-1900)*2/300)+$I$16*(1-(A95-1905)*2/300)+$I$17*(1-(A95-1910)*2/300)+$I$18*(1-(A95-1914)*2/300)+$I$19*(1-(A95-1915)*2/300)+$I$20*(1-(A95-1919)*2/300) -> 1110624
A96: 1924 | B96: =$I$2*(1-(A96-1830)*2/300)+$I$3*(1-(A96-1840)*2/300)+$I$4*(1-(A96-1848)*2/300)+$I$5*(1-(A96-1850)*2/300)+$I$6*(1-(A96-1855)*2/300)+$I$7*(1-(A96-1860)*2/300)+$I$8*(1-(A96-1870)*2/300)+$I$9*(1-(A96-1872)*2/300)+$I$10*(1-(A96-1875)*2/300)+$I$11*(1-(A96-1880)*2/300)+$I$12*(1-(A96-1890)*2/300)+$I$13*(1-(A96-1895)*2/300)+$I$14*(1-(A96-1898)*2/300)+$I$15*(1-(A96-1900)*2/300)+$I$16*(1-(A96-1905)*2/300)+$I$17*(1-(A96-1910)*2/300)+$I$18*(1-(A96-1914)*2/300)+$I$19*(1-(A96-1915)*2/300)+$I$20*(1-(A96-1919)*2/300) -> 1099704
A97: 1925 | B97: =$I$2*(1-(A97-1830)*2/300)+$I$3*(1-(A97-1840)*2/300)+$I$4*(1-(A97-1848)*2/300)+$I$5*(1-(A97-1850)*2/300)+$I$6*(1-(A97-1855)*2/300)+$I$7*(1-(A97-1860)*2/300)+$I$8*(1-(A97-1870)*2/300)+$I$9*(1-(A97-1872)*2/300)+$I$10*(1-(A97-1875)*2/300)+$I$11*(1-(A97-1880)*2/300)+$I$12*(1-(A97-1890)*2/300)+$I$13*(1-(A97-1895)*2/300)+$I$14*(1-(A97-1898)*2/300)+$I$15*(1-(A97-1900)*2/300)+$I$16*(1-(A97-1905)*2/300)+$I$17*(1-(A97-1910)*2/300)+$I$18*(1-(A97-1914)*2/300)+$I$19*(1-(A97-1915)*2/300)+$I$20*(1-(A97-1919)*2/300) -> 1088784
A98: 1926 | B98: =$I$2*(1-(A98-1830)*2/300)+$I$3*(1-(A98-1840)*2/300)+$I$4*(1-(A98-1848)*2/300)+$I$5*(1-(A98-1850)*2/300)+$I$6*(1-(A98-1855)*2/300)+$I$7*(1-(A98-1860)*2/300)+$I$8*(1-(A98-1870)*2/300)+$I$9*(1-(A98-1872)*2/300)+$I$10*(1-(A98-1875)*2/300)+$I$11*(1-(A98-1880)*2/300)+$I$12*(1-(A98-1890)*2/300)+$I$13*(1-(A98-1895)*2/300)+$I$14*(1-(A98-1898)*2/300)+$I$15*(1-(A98-1900)*2/300)+$I$16*(1-(A98-1905)*2/300)+$I$17*(1-(A98-1910)*2/300)+$I$18*(1-(A98-1914)*2/300)+$I$19*(1-(A98-1915)*2/300)+$I$20*(1-(A98-1919)*2/300) -> 1077864
A99: 1927 | B99: =$I$2*(1-(A99-1830)*2/300)+$I$3*(1-(A99-1840)*2/300)+$I$4*(1-(A99-1848)*2/300)+$I$5*(1-(A99-1850)*2/300)+$I$6*(1-(A99-1855)*2/300)+$I$7*(1-(A99-1860)*2/300)+$I$8*(1-(A99-1870)*2/300)+$I$9*(1-(A99-1872)*2/300)+$I$10*(1-(A99-1875)*2/300)+$I$11*(1-(A99-1880)*2/300)+$I$12*(1-(A99-1890)*2/300)+$I$13*(1-(A99-1895)*2/300)+$I$14*(1-(A99-1898)*2/300)+$I$15*(1-(A99-1900)*2/300)+$I$16*(1-(A99-1905)*2/300)+$I$17*(1-(A99-1910)*2/300)+$I$18*(1-(A99-1914)*2/300)+$I$19*(1-(A99-1915)*2/300)+$I$20*(1-(A99-1919)*2/300) -> 1066944
A100: 1928 | B100: =$I$2*(1-(A100-1830)*2/300)+$I$3*(1-(A100-1840)*2/300)+$I$4*(1-(A100-1848)*2/300)+$I$5*(1-(A100-1850)*2/300)+$I$6*(1-(A100-1855)*2/300)+$I$7*(1-(A100-1860)*2/300)+$I$8*(1-(A100-1870)*2/300)+$I$9*(1-(A100-1872)*2/300)+$I$10*(1-(A100-1875)*2/300)+$I$11*(1-(A100-1880)*2/300)+$I$12*(1-(A100-1890)*2/300)+$I$13*(1-(A100-1895)*2/300)+$I$14*(1-(A100-1898)*2/300)+$I$15*(1-(A100-1900)*2/300)+$I$16*(1-(A100-1905)*2/300)+$I$17*(1-(A100-1910)*2/300)+$I$18*(1-(A100-1914)*2/300)+$I$19*(1-(A100-1915)*2/300)+$I$20*(1-(A100-1919)*2/300) -> 1056024
...

Sheet Education Efficiency
A1: Date | B1: Tech Education Efficiency | C1: Reforms | D1: Intellectualists | E1: Literacy | F1: Literacy Change
A2: 1830 | B2: 0.1 | C2: -0.1 | D2: 0.01 | E2: 0.512 | F2: =(D2-0.005)*0.1/0.035*(1+B2+C2)*0.01*120 -> 0.017142857
A3: 1840 | B3: 0.2 | C3: -0.03 | D3: 0.02 | E3: =MIN(1,E2+F2) -> 0.52914286 | F3: =(D3-0.005)*0.1/0.035*(1+B3+C3)*0.01*120 -> 0.060171429
A4: 1850 | B4: 0.7 | C4: 0.02 | D4: 0.025 | E4: =MIN(1,E3+F3) -> 0.58931429 | F4: =(D4-0.005)*0.1/0.035*(1+B4+C4)*0.01*120 -> 0.11794286
A5: 1860 | B5: 0.7 | C5: 0.17 | D5: 0.03 | E5: =MIN(1,E4+F4) -> 0.70725714 | F5: =(D5-0.005)*0.1/0.035*(1+B5+C5)*0.01*120 -> 0.16028571
A6: 1870 | B6: 0.9 | C6: 0.32 | D6: 0.04 | E6: =MIN(1,E5+F5) -> 0.86754286 | F6: =(D6-0.005)*0.1/0.035*(1+B6+C6)*0.01*120 -> 0.2664
A7: 1880 | B7: 0.9 | C7: 0.32 | D7: 0.04 | E7: =MIN(1,E6+F6) -> 1 | F7: =(D7-0.005)*0.1/0.035*(1+B7+C7)*0.01*120 -> 0.2664
A8: 1890 | B8: 1.15 | C8: 0.32 | D8: 0.04 | E8: =MIN(1,E7+F7) -> 1 | F8: =(D8-0.005)*0.1/0.035*(1+B8+C8)*0.01*120 -> 0.2964
A9: 1900 | B9: 1.35 | C9: 0.32 | D9: 0.04 | E9: =MIN(1,E8+F8) -> 1 | F9: =(D9-0.005)*0.1/0.035*(1+B9+C9)*0.01*120 -> 0.3204
A10: 1910 | B10: 1.35 | C10: 0.32 | D10: 0.04 | E10: =MIN(1,E9+F9) -> 1 | F10: =(D10-0.005)*0.1/0.035*(1+B10+C10)*0.01*120 -> 0.3204
A11: 1920 | B11: 1.35 | C11: 0.32 | D11: 0.04 | E11: =MIN(1,E10+F10) -> 1 | F11: =(D11-0.005)*0.1/0.035*(1+B11+C11)*0.01*120 -> 0.3204
A12: 1930 | B12: 1.35 | C12: 0.32 | D12: 0.04 | E12: =MIN(1,E11+F11) -> 1 | F12: =(D12-0.005)*0.1/0.035*(1+B12+C12)*0.01*120 -> 0.3204
A14: TEST | B14: 0 | C14: 0 | D14: 0.04 | E14: 0.01 | F14: =(D14-0.005)*0.1/0.035*(1+B14+C14)*0.01*120 -> 0.12
A15: TEST | B15: 0 | C15: 0 | D15: 0.04 | E15: =SUM(E14,F14) -> 0.13 | F15: =(D15-0.005)*0.1/0.035*(1+B15+C15)*0.01*120 -> 0.12
A17: TEST | B17: 1 | C17: 0 | D17: 0.01 | E17: 0.01 | F17: =(D17-0.005)*0.1/0.035*(1+B17+C17)*0.01*120 -> 0.034285714
A18: TEST | B18: 1 | C18: 0 | D18: 0.04 | E18: =SUM(E17,F17) -> 0.044285714 | F18: =(D18-0.005)*0.1/0.035*(1+B18+C18)*0.01*120 -> 0.24
A20: Date | B20: Tech Education Efficiency | C20: Reforms | D20: Intellectualists | E20: Literacy | F20: Literacy Change
A21: 1830 | B21: 0.1 | C21: -0.1 | D21: 0.01 | E21: 0.1 | F21: =(D21-0.005)*0.1/0.035*(1+B21+C21)*0.01*12 -> 0.0017142857
A22: 1831 | B22: 0.1 | C22: -0.1 | D22: 0.0105 | E22: =MIN(1,E21+F21) -> 0.10171429 | F22: =(D22-0.005)*0.1/0.035*(1+B22+C22)*0.01*12 -> 0.0018857143
A23: 1832 | B23: 0.1 | C23: -0.1 | D23: 0.011 | E23: =MIN(1,E22+F22) -> 0.1036 | F23: =(D23-0.005)*0.1/0.035*(1+B23+C23)*0.01*12 -> 0.0020571429
A24: 1833 | B24: 0.1 | C24: -0.1 | D24: 0.0115 | E24: =MIN(1,E23+F23) -> 0.10565714 | F24: =(D24-0.005)*0.1/0.035*(1+B24+C24)*0.01*12 -> 0.0022285714
A25: 1834 | B25: 0.1 | C25: -0.1 | D25: 0.012 | E25: =MIN(1,E24+F24) -> 0.10788571 | F25: =(D25-0.005)*0.1/0.035*(1+B25+C25)*0.01*12 -> 0.0024
A26: 1835 | B26: 0.1 | C26: -0.1 | D26: 0.0125 | E26: =MIN(1,E25+F25) -> 0.11028571 | F26: =(D26-0.005)*0.1/0.035*(1+B26+C26)*0.01*12 -> 0.0025714286
A27: 1836 | B27: 0.1 | C27: -0.1 | D27: 0.013 | E27: =MIN(1,E26+F26) -> 0.11285714 | F27: =(D27-0.005)*0.1/0.035*(1+B27+C27)*0.01*12 -> 0.0027428571
A28: 1837 | B28: 0.1 | C28: -0.1 | D28: 0.0135 | E28: =MIN(1,E27+F27) -> 0.1156 | F28: =(D28-0.005)*0.1/0.035*(1+B28+C28)*0.01*12 -> 0.0029142857
A29: 1838 | B29: 0.1 | C29: -0.1 | D29: 0.014 | E29: =MIN(1,E28+F28) -> 0.11851429 | F29: =(D29-0.005)*0.1/0.035*(1+B29+C29)*0.01*12 -> 0.0030857143
A30: 1839 | B30: 0.1 | C30: -0.1 | D30: 0.0145 | E30: =MIN(1,E29+F29) -> 0.1216 | F30: =(D30-0.005)*0.1/0.035*(1+B30+C30)*0.01*12 -> 0.0032571429
A31: 1840 | B31: 0.1 | C31: -0.1 | D31: 0.015 | E31: =MIN(1,E30+F30) -> 0.12485714 | F31: =(D31-0.005)*0.1/0.035*(1+B31+C31)*0.01*12 -> 0.0034285714
A32: 1841 | B32: 0.1 | C32: -0.1 | D32: 0.0155 | E32: =MIN(1,E31+F31) -> 0.12828571 | F32: =(D32-0.005)*0.1/0.035*(1+B32+C32)*0.01*12 -> 0.0036
A33: 1842 | B33: 0.1 | C33: -0.1 | D33: 0.016 | E33: =MIN(1,E32+F32) -> 0.13188571 | F33: =(D33-0.005)*0.1/0.035*(1+B33+C33)*0.01*12 -> 0.0037714286
... A127: 1936 | B127: 1.35 | C127: 0.32 | D127: 0.04 | E127: =MIN(1,E126+F126) -> 1 | F127: =(D127-0.005)*0.1/0.035*(1+B127+C127)*0.01*12 -> 0.03204

Sheet State Sim
A1: Date | B1: POPs | C1: Intellectuals | D1: Bureaucrats | E1: Intellectuals % | F1: Bureaucrats % | G1: Literacy | H1: Administrative Efficiency | I1: Admin Eff. Bonus | J1: Reforms Taken | K1: Promotions | L1: To Intellectualists | M1: To Bureaucrats | N1: Slave State? | O1: Edu Spending | P1: Admin Spending | Q1: Life Rating | R1: POP Growth | V1: Promotion - General
A2: 1830 | B2: 100000 | C2: 0 | D2: 0 | E2: =C2/B2 -> 0 | F2: =D2/B2 -> 0 | G2: 0.01 | H2: =MIN((D2/B2)/(0.01+(J2*0.001))+I2,1) -> 0.4 | I2: 0.4 | J2: 0 | K2: =B2/500/4*(0.3-IF($N$2="Yes",0.1,0)+VLOOKUP(G2,$V$3:$W$11,2,1))*H2*12 -> 72 | L2: =(VLOOKUP(G2,$T$15:$U$21,2,1)+VLOOKUP($O$2,$T$26:$U$36,2,1)-0.12)*IF(E2>0.041,0,1) -> 0.14 | M2: =VLOOKUP(G2,$X$15:$Y$22,2,1)+VLOOKUP($P$2,$X$26:$Y$37,2,1)*IF(F2>0.04,0,1) -> 0.02 | N2: No | O2: 1 | P2: 0.1 | Q2: 35 | R2: 0 | V2: Literacy | W2: Total Bonus | X2: Bonus
A3: 1831 | B3: =B2*(1+MAX(($Q$2-30)*0.0001+0.0001+$R$2,0))-K2 -> 99988 | C3: =C2*(1+MAX(($Q$2-30)*0.0001+0.0001+$R$2,0))+K2*IF(M2=0,1,L2/M2) -> 504 | D3: =D2*(1+MAX(($Q$2-30)*0.0001+0.0001+$R$2,0))+K2*IF(L2=0,1,M2/L2) -> 10.285714 | E3: =C3/B3 -> 0.0050406049 | F3: =D3/B3 -> 0.00010286949 | G3: 0.01 | H3: =MIN((D3/B3)/(0.01+(J3*0.001))+I3,1) -> 0.41028695 | I3: 0.4 | J3: 0 | K3: =B3/500/4*(0.3-IF($N$2="Yes",0.1,0)+VLOOKUP(G3,$V$3:$W$11,2,TRUE()))*H3*12 -> 73.842789 | L3: =(VLOOKUP(G3,$T$15:$U$21,2,1)+VLOOKUP($O$2,$T$26:$U$36,2,1)-0.12)*IF(E3>0.041,0,1) -> 0.14 | M3: =VLOOKUP(G3,$X$15:$Y$22,2,1)+VLOOKUP($P$2,$X$26:$Y$37,2,1)*IF(F3>0.04,0,1) -> 0.02 | V3: 0 | W3: =SUM(X3) -> 0 | X3: 0
A4: 1832 | B4: =B3*(1+MAX(($Q$2-30)*0.0001+0.0001+$R$2,0))-K3 -> 99974.15 | C4: =C3*(1+MAX(($Q$2-30)*0.0001+0.0001+$R$2,0))+K3*IF(M3=0,1,L3/M3) -> 1021.2019 | D4: =D3*(1+MAX(($Q$2-30)*0.0001+0.0001+$R$2,0))+K3*IF(L3=0,1,M3/L3) -> 20.840856 | E4: =C4/B4 -> 0.01021466 | F4: =D4/B4 -> 0.00020846244 | G4: 0.01 | H4: =MIN((D4/B4)/(0.01+(J4*0.001))+I4,1) -> 0.42084624 | I4: 0.4 | J4: 0 | K4: =B4/500/4*(0.3-IF($N$2="Yes",0.1,0)+VLOOKUP(G4,$V$3:$W$11,2,TRUE()))*H4*12 -> 75.732742 | L4: =(VLOOKUP(G4,$T$15:$U$21,2,1)+VLOOKUP($O$2,$T$26:$U$36,2,1)-0.12)*IF(E4>0.041,0,1) -> 0.14 | M4: =VLOOKUP(G4,$X$15:$Y$22,2,1)+VLOOKUP($P$2,$X$26:$Y$37,2,1)*IF(F4>0.04,0,1) -> 0.02 | V4: 0.1 | W4: =SUM(X3:X4) -> 0.032 | X4: 0.032
A5: 1833 | B5: =B4*(1+MAX(($Q$2-30)*0.0001+0.0001+$R$2,0))-K4 -> 99958.402 | C5: =C4*(1+MAX(($Q$2-30)*0.0001+0.0001+$R$2,0))+K4*IF(M4=0,1,L4/M4) -> 1551.9438 | D5: =D4*(1+MAX(($Q$2-30)*0.0001+0.0001+$R$2,0))+K4*IF(L4=0,1,M4/L4) -> 31.672323 | E5: =C5/B5 -> 0.015525897 | F5: =D5/B5 -> 0.00031685504 | G5: 0.01 | H5: =MIN((D5/B5)/(0.01+(J5*0.001))+I5,1) -> 0.4316855 | I5: 0.4 | J5: 0 | K5: =B5/500/4*(0.3-IF($N$2="Yes",0.1,0)+VLOOKUP(G5,$V$3:$W$11,2,TRUE()))*H5*12 -> 77.671067 | L5: =(VLOOKUP(G5,$T$15:$U$21,2,1)+VLOOKUP($O$2,$T$26:$U$36,2,1)-0.12)*IF(E5>0.041,0,1) -> 0.14 | M5: =VLOOKUP(G5,$X$15:$Y$22,2,1)+VLOOKUP($P$2,$X$26:$Y$37,2,1)*IF(F5>0.04,0,1) -> 0.02 | V5: 0.2 | W5: =SUM(X3:X5) -> 0.055 | X5: 0.023
A6: 1834 | B6: =B5*(1+MAX(($Q$2-30)*0.0001+0.0001+$R$2,0))-K5 -> 99940.706 | C6: =C5*(1+MAX(($Q$2-30)*0.0001+0.0001+$R$2,0))+K5*IF(M5=0,1,L5/M5) -> 2096.5725 | D6: =D5*(1+MAX(($Q$2-30)*0.0001+0.0001+$R$2,0))+K5*IF(L5=0,1,M5/L5) -> 42.787193 | E6: =C6/B6 -> 0.020978164 | F6: =D6/B6 -> 0.00042812579 | G6: 0.01 | H6: =MIN((D6/B6)/(0.01+(J6*0.001))+I6,1) -> 0.44281258 | I6: 0.4 | J6: 0 | K6: =B6/500/4*(0.3-IF($N$2="Yes",0.1,0)+VLOOKUP(G6,$V$3:$W$11,2,TRUE()))*H6*12 -> 79.659003 | L6: =(VLOOKUP(G6,$T$15:$U$21,2,1)+VLOOKUP($O$2,$T$26:$U$36,2,1)-0.12)*IF(E6>0.041,0,1) -> 0.14 | M6: =VLOOKUP(G6,$X$15:$Y$22,2,1)+VLOOKUP($P$2,$X$26:$Y$37,2,1)*IF(F6>0.04,0,1) -> 0.02 | V6: 0.3 | W6: =SUM(X3:X6) -> 0.076 | X6: 0.021
A7: 1835 | B7: =B6*(1+MAX(($Q$2-30)*0.0001+0.0001+$R$2,0))-K6 -> 99921.011 | C7: =C6*(1+MAX(($Q$2-30)*0.0001+0.0001+$R$2,0))+K6*IF(M6=0,1,L6/M6) -> 2655.4434 | D7: =D6*(1+MAX(($Q$2-30)*0.0001+0.0001+$R$2,0))+K6*IF(L6=0,1,M6/L6) -> 54.192723 | E7: =C7/B7 -> 0.026575426 | F7: =D7/B7 -> 0.00054235563 | G7: 0.01 | H7: =MIN((D7/B7)/(0.01+(J7*0.001))+I7,1) -> 0.45423556 | I7: 0.4 | J7: 0 | K7: =B7/500/4*(0.3-IF($N$2="Yes",0.1,0)+VLOOKUP(G7,$V$3:$W$11,2,TRUE()))*H7*12 -> 81.697818 | L7: =(VLOOKUP(G7,$T$15:$U$21,2,1)+VLOOKUP($O$2,$T$26:$U$36,2,1)-0.12)*IF(E7>0.041,0,1) -> 0.14 | M7: =VLOOKUP(G7,$X$15:$Y$22,2,1)+VLOOKUP($P$2,$X$26:$Y$37,2,1)*IF(F7>0.04,0,1) -> 0.02 | V7: 0.4 | W7: =SUM(X3:X7) -> 0.096 | X7: 0.02
A8: 1836 | B8: =B7*(1+MAX(($Q$2-30)*0.0001+0.0001+$R$2,0))-K7 -> 99899.266 | C8: =C7*(1+MAX(($Q$2-30)*0.0001+0.0001+$R$2,0))+K7*IF(M7=0,1,L7/M7) -> 3228.9214 | D8: =D7*(1+MAX(($Q$2-30)*0.0001+0.0001+$R$2,0))+K7*IF(L7=0,1,M7/L7) -> 65.896356 | E8: =C8/B8 -> 0.032321773 | F8: =D8/B8 -> 0.00065962803 | G8: 0.01 | H8: =MIN((D8/B8)/(0.01+(J8*0.001))+I8,1) -> 0.4659628 | I8: 0.4 | J8: 0 | K8: =B8/500/4*(0.3-IF($N$2="Yes",0.1,0)+VLOOKUP(G8,$V$3:$W$11,2,TRUE()))*H8*12 -> 83.788816 | L8: =(VLOOKUP(G8,$T$15:$U$21,2,1)+VLOOKUP($O$2,$T$26:$U$36,2,1)-0.12)*IF(E8>0.041,0,1) -> 0.14 | M8: =VLOOKUP(G8,$X$15:$Y$22,2,1)+VLOOKUP($P$2,$X$26:$Y$37,2,1)*IF(F8>0.04,0,1) -> 0.02 | V8: 0.51 | W8: =SUM(X3:X8) -> 0.117 | X8: 0.021
A9: 1837 | B9: =B8*(1+MAX(($Q$2-30)*0.0001+0.0001+$R$2,0))-K8 -> 99875.417 | C9: =C8*(1+MAX(($Q$2-30)*0.0001+0.0001+$R$2,0))+K8*IF(M8=0,1,L8/M8) -> 3817.3805 | D9: =D8*(1+MAX(($Q$2-30)*0.0001+0.0001+$R$2,0))+K8*IF(L8=0,1,M8/L8) -> 77.905724 | E9: =C9/B9 -> 0.038221422 | F9: =D9/B9 -> 0.00078002903 | G9: 0.01 | H9: =MIN((D9/B9)/(0.01+(J9*0.001))+I9,1) -> 0.4780029 | I9: 0.4 | J9: 0 | K9: =B9/500/4*(0.3-IF($N$2="Yes",0.1,0)+VLOOKUP(G9,$V$3:$W$11,2,TRUE()))*H9*12 -> 85.93333 | L9: =(VLOOKUP(G9,$T$15:$U$21,2,1)+VLOOKUP($O$2,$T$26:$U$36,2,1)-0.12)*IF(E9>0.041,0,1) -> 0.14 | M9: =VLOOKUP(G9,$X$15:$Y$22,2,1)+VLOOKUP($P$2,$X$26:$Y$37,2,1)*IF(F9>0.04,0,1) -> 0.02 | V9: 0.62 | W9: =SUM(X3:X9) -> 0.139 | X9: 0.022
A10: 1838 | B10: =B9*(1+MAX(($Q$2-30)*0.0001+0.0001+$R$2,0))-K9 -> 99849.409 | C10: =C9*(1+MAX(($Q$2-30)*0.0001+0.0001+$R$2,0))+K9*IF(M9=0,1,L9/M9) -> 4421.2042 | D10: =D9*(1+MAX(($Q$2-30)*0.0001+0.0001+$R$2,0))+K9*IF(L9=0,1,M9/L9) -> 90.228658 | E10: =C10/B10 -> 0.044278722 | F10: =D10/B10 -> 0.00090364739 | G10: 0.01 | H10: =MIN((D10/B10)/(0.01+(J10*0.001))+I10,1) -> 0.49036474 | I10: 0.4 | J10: 0 | K10: =B10/500/4*(0.3-IF($N$2="Yes",0.1,0)+VLOOKUP(G10,$V$3:$W$11,2,TRUE()))*H10*12 -> 88.132733 | L10: =(VLOOKUP(G10,$T$15:$U$21,2,1)+VLOOKUP($O$2,$T$26:$U$36,2,1)-0.12)*IF(E10>0.041,0,1) -> 0 | M10: =VLOOKUP(G10,$X$15:$Y$22,2,1)+VLOOKUP($P$2,$X$26:$Y$37,2,1)*IF(F10>0.04,0,1) -> 0.02 | V10: 0.75 | W10: =SUM(X3:X10) -> 0.162 | X10: 0.023
A11: 1839 | B11: =B10*(1+MAX(($Q$2-30)*0.0001+0.0001+$R$2,0))-K10 -> 99821.186 | C11: =C10*(1+MAX(($Q$2-30)*0.0001+0.0001+$R$2,0))+K10*IF(M10=0,1,L10/M10) -> 4423.857 | D11: =D10*(1+MAX(($Q$2-30)*0.0001+0.0001+$R$2,0))+K10*IF(L10=0,1,M10/L10) -> 178.41553 | E11: =C11/B11 -> 0.044317816 | F11: =D11/B11 -> 0.0017873513 | G11: 0.01 | H11: =MIN((D11/B11)/(0.01+(J11*0.001))+I11,1) -> 0.57873513 | I11: 0.4 | J11: 0 | K11: =B11/500/4*(0.3-IF($N$2="Yes",0.1,0)+VLOOKUP(G11,$V$3:$W$11,2,TRUE()))*H11*12 -> 103.98605 | L11: =(VLOOKUP(G11,$T$15:$U$21,2,1)+VLOOKUP($O$2,$T$26:$U$36,2,1)-0.12)*IF(E11>0.041,0,1) -> 0 | M11: =VLOOKUP(G11,$X$15:$Y$22,2,1)+VLOOKUP($P$2,$X$26:$Y$37,2,1)*IF(F11>0.04,0,1) -> 0.02 | V11: 0.9 | W11: =SUM(X3:X11) -> 0.186 | X11: 0.024
A12: 1840 | B12: =B11*(1+MAX(($Q$2-30)*0.0001+0.0001+$R$2,0))-K11 -> 99777.092 | C12: =C11*(1+MAX(($Q$2-30)*0.0001+0.0001+$R$2,0))+K11*IF(M11=0,1,L11/M11) -> 4426.5113 | D12: =D11*(1+MAX(($Q$2-30)*0.0001+0.0001+$R$2,0))+K11*IF(L11=0,1,M11/L11) -> 282.50863 | E12: =C12/B12 -> 0.044364004 | F12: =D12/B12 -> 0.0028313977 | G12: 0.01 | H12: =MIN((D12/B12)/(0.01+(J12*0.001))+I12,1) -> 0.68313977 | I12: 0.4 | J12: 0 | K12: =B12/500/4*(0.3-IF($N$2="Yes",0.1,0)+VLOOKUP(G12,$V$3:$W$11,2,TRUE()))*H12*12 -> 122.69106 | L12: =(VLOOKUP(G12,$T$15:$U$21,2,1)+VLOOKUP($O$2,$T$26:$U$36,2,1)-0.12)*IF(E12>0.041,0,1) -> 0 | M12: =VLOOKUP(G12,$X$15:$Y$22,2,1)+VLOOKUP($P$2,$X$26:$Y$37,2,1)*IF(F12>0.04,0,1) -> 0.02
A13: 1841 | B13: =B12*(1+MAX(($Q$2-30)*0.0001+0.0001+$R$2,0))-K12 -> 99714.267 | C13: =C12*(1+MAX(($Q$2-30)*0.0001+0.0001+$R$2,0))+K12*IF(M12=0,1,L12/M12) -> 4429.1672 | D13: =D12*(1+MAX(($Q$2-30)*0.0001+0.0001+$R$2,0))+K12*IF(L12=0,1,M12/L12) -> 405.36919 | E13: =C13/B13 -> 0.04441859 | F13: =D13/B13 -> 0.0040653078 | G13: 0.01 | H13: =MIN((D13/B13)/(0.01+(J13*0.001))+I13,1) -> 0.80653078 | I13: 0.4 | J13: 0 | K13: =B13/500/4*(0.3-IF($N$2="Yes",0.1,0)+VLOOKUP(G13,$V$3:$W$11,2,TRUE()))*H13*12 -> 144.76073 | L13: =(VLOOKUP(G13,$T$15:$U$21,2,1)+VLOOKUP($O$2,$T$26:$U$36,2,1)-0.12)*IF(E13>0.041,0,1) -> 0 | M13: =VLOOKUP(G13,$X$15:$Y$22,2,1)+VLOOKUP($P$2,$X$26:$Y$37,2,1)*IF(F13>0.04,0,1) -> 0.02 | T13: Promotion - Intellectualists | X13: Promotion – Bureaucrats
A14: 1842 | B14: =B13*(1+MAX(($Q$2-30)*0.0001+0.0001+$R$2,0))-K13 -> 99629.335 | C14: =C13*(1+MAX(($Q$2-30)*0.0001+0.0001+$R$2,0))+K13*IF(M13=0,1,L13/M13) -> 4431.8247 | D14: =D13*(1+MAX(($Q$2-30)*0.0001+0.0001+$R$2,0))+K13*IF(L13=0,1,M13/L13) -> 550.37314 | E14: =C14/B14 -> 0.04448313 | F14: =D14/B14 -> 0.0055242077 | G14: 0.01 | H14: =MIN((D14/B14)/(0.01+(J14*0.001))+I14,1) -> 0.95242077 | I14: 0.4 | J14: 0 | K14: =B14/500/4*(0.3-IF($N$2="Yes",0.1,0)+VLOOKUP(G14,$V$3:$W$11,2,TRUE()))*H14*12 -> 170.80029 | L14: =(VLOOKUP(G14,$T$15:$U$21,2,1)+VLOOKUP($O$2,$T$26:$U$36,2,1)-0.12)*IF(E14>0.041,0,1) -> 0 | M14: =VLOOKUP(G14,$X$15:$Y$22,2,1)+VLOOKUP($P$2,$X$26:$Y$37,2,1)*IF(F14>0.04,0,1) -> 0.02 | T14: Literacy | U14: Total Bonus | V14: Bonus | X14: Literacy | Y14: Total Bonus | Z14: Bonus
A15: 1843 | B15: =B14*(1+MAX(($Q$2-30)*0.0001+0.0001+$R$2,0))-K14 -> 99518.313 | C15: =C14*(1+MAX(($Q$2-30)*0.0001+0.0001+$R$2,0))+K14*IF(M14=0,1,L14/M14) -> 4434.4838 | D15: =D14*(1+MAX(($Q$2-30)*0.0001+0.0001+$R$2,0))+K14*IF(L14=0,1,M14/L14) -> 721.50365 | E15: =C15/B15 -> 0.044559475 | F15: =D15/B15 -> 0.0072499586 | G15: 0.01 | H15: =MIN((D15/B15)/(0.01+(J15*0.001))+I15,1) -> 1 | I15: 0.4 | J15: 0 | K15: =B15/500/4*(0.3-IF($N$2="Yes",0.1,0)+VLOOKUP(G15,$V$3:$W$11,2,TRUE()))*H15*12 -> 179.13296 | L15: =(VLOOKUP(G15,$T$15:$U$21,2,1)+VLOOKUP($O$2,$T$26:$U$36,2,1)-0.12)*IF(E15>0.041,0,1) -> 0 | M15: =VLOOKUP(G15,$X$15:$Y$22,2,1)+VLOOKUP($P$2,$X$26:$Y$37,2,1)*IF(F15>0.04,0,1) -> 0.02 | T15: 0 | U15: =SUM(V15) -> 0 | V15: 0 | X15: 0 | Y15: =SUM(Z15) -> 0 | Z15: 0
A16: 1844 | B16: =B15*(1+MAX(($Q$2-30)*0.0001+0.0001+$R$2,0))-K15 -> 99398.891 | C16: =C15*(1+MAX(($Q$2-30)*0.0001+0.0001+$R$2,0))+K15*IF(M15=0,1,L15/M15) -> 4437.1445 | D16: =D15*(1+MAX(($Q$2-30)*0.0001+0.0001+$R$2,0))+K15*IF(L15=0,1,M15/L15) -> 901.06951 | E16: =C16/B16 -> 0.044639779 | F16: =D16/B16 -> 0.0090651868 | G16: 0.01 | H16: =MIN((D16/B16)/(0.01+(J16*0.001))+I16,1) -> 1 | I16: 0.4 | J16: 0 | K16: =B16/500/4*(0.3-IF($N$2="Yes",0.1,0)+VLOOKUP(G16,$V$3:$W$11,2,TRUE()))*H16*12 -> 178.918 | L16: =(VLOOKUP(G16,$T$15:$U$21,2,1)+VLOOKUP($O$2,$T$26:$U$36,2,1)-0.12)*IF(E16>0.041,0,1) -> 0 | M16: =VLOOKUP(G16,$X$15:$Y$22,2,1)+VLOOKUP($P$2,$X$26:$Y$37,2,1)*IF(F16>0.04,0,1) -> 0.02 | T16: 0.3 | U16: =SUM(V15:V16) -> 0.005 | V16: 0.005 | X16: 0.4 | Y16: =SUM(Z15:Z16) -> 0.0025 | Z16: 0.0025
A17: 1845 | B17: =B16*(1+MAX(($Q$2-30)*0.0001+0.0001+$R$2,0))-K16 -> 99279.612 | C17: =C16*(1+MAX(($Q$2-30)*0.0001+0.0001+$R$2,0))+K16*IF(M16=0,1,L16/M16) -> 4439.8067 | D17: =D16*(1+MAX(($Q$2-30)*0.0001+0.0001+$R$2,0))+K16*IF(L16=0,1,M16/L16) -> 1080.5282 | E17: =C17/B17 -> 0.044720227 | F17: =D17/B17 -> 0.010883686 | G17: 0.01 | H17: =MIN((D17/B17)/(0.01+(J17*0.001))+I17,1) -> 1 | I17: 0.4 | J17: 0 | K17: =B17/500/4*(0.3-IF($N$2="Yes",0.1,0)+VLOOKUP(G17,$V$3:$W$11,2,TRUE()))*H17*12 -> 178.7033 | L17: =(VLOOKUP(G17,$T$15:$U$21,2,1)+VLOOKUP($O$2,$T$26:$U$36,2,1)-0.12)*IF(E17>0.041,0,1) -> 0 | M17: =VLOOKUP(G17,$X$15:$Y$22,2,1)+VLOOKUP($P$2,$X$26:$Y$37,2,1)*IF(F17>0.04,0,1) -> 0.02 | T17: 0.4 | U17: =SUM(V15:V17) -> 0.0075 | V17: 0.0025 | X17: 0.5 | Y17: =SUM(Z15:Z17) -> 0.005 | Z17: 0.0025
A18: 1846 | B18: =B17*(1+MAX(($Q$2-30)*0.0001+0.0001+$R$2,0))-K17 -> 99160.476 | C18: =C17*(1+MAX(($Q$2-30)*0.0001+0.0001+$R$2,0))+K17*IF(M17=0,1,L17/M17) -> 4442.4706 | D18: =D17*(1+MAX(($Q$2-30)*0.0001+0.0001+$R$2,0))+K17*IF(L17=0,1,M17/L17) -> 1259.8798 | E18: =C18/B18 -> 0.04480082 | F18: =D18/B18 -> 0.012705463 | G18: 0.01 | H18: =MIN((D18/B18)/(0.01+(J18*0.001))+I18,1) -> 1 | I18: 0.4 | J18: 0 | K18: =B18/500/4*(0.3-IF($N$2="Yes",0.1,0)+VLOOKUP(G18,$V$3:$W$11,2,TRUE()))*H18*12 -> 178.48886 | L18: =(VLOOKUP(G18,$T$15:$U$21,2,1)+VLOOKUP($O$2,$T$26:$U$36,2,1)-0.12)*IF(E18>0.041,0,1) -> 0 | M18: =VLOOKUP(G18,$X$15:$Y$22,2,1)+VLOOKUP($P$2,$X$26:$Y$37,2,1)*IF(F18>0.04,0,1) -> 0.02 | T18: 0.5 | U18: =SUM(V15:V18) -> 0.01 | V18: 0.0025 | X18: 0.6 | Y18: =SUM(Z15:Z18) -> 0.01 | Z18: 0.005
A19: 1847 | B19: =B18*(1+MAX(($Q$2-30)*0.0001+0.0001+$R$2,0))-K18 -> 99041.484 | C19: =C18*(1+MAX(($Q$2-30)*0.0001+0.0001+$R$2,0))+K18*IF(M18=0,1,L18/M18) -> 4445.1361 | D19: =D18*(1+MAX(($Q$2-30)*0.0001+0.0001+$R$2,0))+K18*IF(L18=0,1,M18/L18) -> 1439.1246 | E19: =C19/B19 -> 0.044881558 | F19: =D19/B19 -> 0.014530523 | G19: 0.01 | H19: =MIN((D19/B19)/(0.01+(J19*0.001))+I19,1) -> 1 | I19: 0.4 | J19: 0 | K19: =B19/500/4*(0.3-IF($N$2="Yes",0.1,0)+VLOOKUP(G19,$V$3:$W$11,2,TRUE()))*H19*12 -> 178.27467 | L19: =(VLOOKUP(G19,$T$15:$U$21,2,1)+VLOOKUP($O$2,$T$26:$U$36,2,1)-0.12)*IF(E19>0.041,0,1) -> 0 | M19: =VLOOKUP(G19,$X$15:$Y$22,2,1)+VLOOKUP($P$2,$X$26:$Y$37,2,1)*IF(F19>0.04,0,1) -> 0.02 | T19: 0.6 | U19: =SUM(V15:V19) -> 0.0125 | V19: 0.0025 | X19: 0.7 | Y19: =SUM(Z15:Z19) -> 0.015 | Z19: 0.005
A20: 1848 | B20: =B19*(1+MAX(($Q$2-30)*0.0001+0.0001+$R$2,0))-K19 -> 98922.634 | C20: =C19*(1+MAX(($Q$2-30)*0.0001+0.0001+$R$2,0))+K19*IF(M19=0,1,L19/M19) -> 4447.8032 | D20: =D19*(1+MAX(($Q$2-30)*0.0001+0.0001+$R$2,0))+K19*IF(L19=0,1,M19/L19) -> 1618.2627 | E20: =C20/B20 -> 0.044962442 | F20: =D20/B20 -> 0.016358872 | G20: 0.01 | H20: =MIN((D20/B20)/(0.01+(J20*0.001))+I20,1) -> 1 | I20: 0.4 | J20: 0 | K20: =B20/500/4*(0.3-IF($N$2="Yes",0.1,0)+VLOOKUP(G20,$V$3:$W$11,2,TRUE()))*H20*12 -> 178.06074 | L20: =(VLOOKUP(G20,$T$15:$U$21,2,1)+VLOOKUP($O$2,$T$26:$U$36,2,1)-0.12)*IF(E20>0.041,0,1) -> 0 | M20: =VLOOKUP(G20,$X$15:$Y$22,2,1)+VLOOKUP($P$2,$X$26:$Y$37,2,1)*IF(F20>0.04,0,1) -> 0.02 | T20: 0.7 | U20: =SUM(V15:V20) -> 0.015 | V20: 0.0025 | X20: 0.8 | Y20: =SUM(Z15:Z20) -> 0.025 | Z20: 0.01
A21: 1849 | B21: =B20*(1+MAX(($Q$2-30)*0.0001+0.0001+$R$2,0))-K20 -> 98803.927 | C21: =C20*(1+MAX(($Q$2-30)*0.0001+0.0001+$R$2,0))+K20*IF(M20=0,1,L20/M20) -> 4450.4719 | D21: =D20*(1+MAX(($Q$2-30)*0.0001+0.0001+$R$2,0))+K20*IF(L20=0,1,M20/L20) -> 1797.2944 | E21: =C21/B21 -> 0.045043472 | F21: =D21/B21 -> 0.018190516 | G21: 0.01 | H21: =MIN((D21/B21)/(0.01+(J21*0.001))+I21,1) -> 1 | I21: 0.4 | J21: 0 | K21: =B21/500/4*(0.3-IF($N$2="Yes",0.1,0)+VLOOKUP(G21,$V$3:$W$11,2,TRUE()))*H21*12 -> 177.84707 | L21: =(VLOOKUP(G21,$T$15:$U$21,2,1)+VLOOKUP($O$2,$T$26:$U$36,2,1)-0.12)*IF(E21>0.041,0,1) -> 0 | M21: =VLOOKUP(G21,$X$15:$Y$22,2,1)+VLOOKUP($P$2,$X$26:$Y$37,2,1)*IF(F21>0.04,0,1) -> 0.02 | T21: 0.8 | U21: =SUM(V15:V21) -> 0.0175 | V21: 0.0025 | X21: 0.9 | Y21: =SUM(Z15:Z21) -> 0.035 | Z21: 0.01
A22: 1850 | B22: =B21*(1+MAX(($Q$2-30)*0.0001+0.0001+$R$2,0))-K21 -> 98685.362 | C22: =C21*(1+MAX(($Q$2-30)*0.0001+0.0001+$R$2,0))+K21*IF(M21=0,1,L21/M21) -> 4453.1422 | D22: =D21*(1+MAX(($Q$2-30)*0.0001+0.0001+$R$2,0))+K21*IF(L21=0,1,M21/L21) -> 1976.2199 | E22: =C22/B22 -> 0.045124647 | F22: =D22/B22 -> 0.020025461 | G22: 0.01 | H22: =MIN((D22/B22)/(0.01+(J22*0.001))+I22,1) -> 1 | I22: 0.4 | J22: 0 | K22: =B22/500/4*(0.3-IF($N$2="Yes",0.1,0)+VLOOKUP(G22,$V$3:$W$11,2,TRUE()))*H22*12 -> 177.63365 | L22: =(VLOOKUP(G22,$T$15:$U$21,2,1)+VLOOKUP($O$2,$T$26:$U$36,2,1)-0.12)*IF(E22>0.041,0,1) -> 0 | M22: =VLOOKUP(G22,$X$15:$Y$22,2,1)+VLOOKUP($P$2,$X$26:$Y$37,2,1)*IF(F22>0.04,0,1) -> 0.02 | X22: 1 | Y22: =SUM(Z15:Z22) -> 0.055 | Z22: 0.02
T24: Intellectualists - MONEY | X24: Bureaucrats - MONEY
T25: Cash | U25: Total Bonus | V25: Bonus | X25: Cash | Y25: Total Bonus | Z25: Bonus
T26: 0 | U26: =SUM(V26) -> 0 | V26: 0 | X26: 0 | Y26: =SUM(Z26) -> 0 | Z26: 0
T27: 0.1 | U27: =SUM(V26:V27) -> 0.02 | V27: 0.02 | X27: 0.1 | Y27: =SUM(Z26:Z27) -> 0.02 | Z27: 0.02
T28: 0.2 | U28: =SUM(V26:V28) -> 0.04 | V28: 0.02 | X28: 0.2 | Y28: =SUM(Z26:Z28) -> 0.04 | Z28: 0.02
T29: 0.3 | U29: =SUM(V26:V29) -> 0.06 | V29: 0.02 | X29: 0.3 | Y29: =SUM(Z26:Z29) -> 0.06 | Z29: 0.02
T30: 0.4 | U30: =SUM(V26:V30) -> 0.082 | V30: 0.022 | X30: 0.4 | Y30: =SUM(Z26:Z30) -> 0.08 | Z30: 0.02
T31: 0.5 | U31: =SUM(V26:V31) -> 0.105 | V31: 0.023 | X31: 0.5 | Y31: =SUM(Z26:Z31) -> 0.1 | Z31: 0.02
T32: 0.6 | U32: =SUM(V26:V32) -> 0.13 | V32: 0.025 | X32: 0.6 | Y32: =SUM(Z26:Z32) -> 0.12 | Z32: 0.02
T33: 0.75 | U33: =SUM(V26:V33) -> 0.2 | V33: 0.07 | X33: 0.7 | Y33: =SUM(Z26:Z33) -> 0.14 | Z33: 0.02
T34: 0.8 | U34: =SUM(V26:V34) -> 0.22 | V34: 0.02 | X34: 0.75 | Y34: =SUM(Z26:Z34) -> 0.2 | Z34: 0.06
T35: 0.9 | U35: =SUM(V26:V35) -> 0.24 | V35: 0.02 | X35: 0.8 | Y35: =SUM(Z26:Z35) -> 0.22 | Z35: 0.02
T36: 1 | U36: =SUM(V26:V36) -> 0.26 | V36: 0.02 | X36: 0.9 | Y36: =SUM(Z26:Z36) -> 0.24 | Z36: 0.02
X37: 1 | Y37: =SUM(Z27:Z37) -> 0.26 | Z37: 0.02

Sheet Treaty Ports
A1: Treaty Port | B1: POPs | C1: Provinces in state | D1: Terrain | E1: Infrastructure | F1: Naval Base | G1: Life Rating | H1: Output | I1: Base Income | K1: Max Infrastructure | L1: Good Output | M1: Admin Efficiency | N1: Tax Efficiency | O1: Date
A2: Ningpo | B2: =249000 -> 249000 | C2: 1 | D2: 0 | E2: -1 | F2: 2 | G2: 32 | H2: =B2/40000*'Goods values'!$B$3*(1+D2+$L$2+MAX(($K$2+E2)*0.16,0)) -> 43.326 | I2: =H2*'Goods values'!$C$3*3*MAX($M$2-(C2*0.075),0)*$N$2+H2 -> 133.40075 | K2: 3 | L2: 1 | M2: 0.35 | N2: 0.14 | O2: 1830
A3: Shanghai | B3: 188250 | C3: 1 | D3: 0 | E3: -1 | F3: 6 | G3: 32 | H3: =B3/40000*'Goods values'!$B$3*(1+D3+$L$2+MAX(($K$2+E3)*0.16,0)) -> 32.7555 | I3: =H3*'Goods values'!$C$3*3*MAX($M$2-(C3*0.075),0)*$N$2+H3 -> 100.85418
A4: Kashing | B4: 78300 | C4: 1 | D4: 0 | E4: -1 | F4: 2 | G4: 32 | H4: =B4/40000*'Goods values'!$B$3*(1+D4+$L$2+MAX(($K$2+E4)*0.16,0)) -> 13.6242 | I4: =H4*'Goods values'!$C$3*3*MAX($M$2-(C4*0.075),0)*$N$2+H4 -> 41.948912
A5: Sanmen | B5: 83125 | C5: 1 | D5: 0 | E5: -2 | F5: 6 | G5: 32 | H5: =B5/40000*'Goods values'!$B$3*(1+D5+$L$2+MAX(($K$2+E5)*0.16,0)) -> 13.46625 | I5: =H5*'Goods values'!$C$3*3*MAX($M$2-(C5*0.075),0)*$N$2+H5 -> 41.462584
A6: Cheju | B6: =53731+10486 -> 64217 | C6: 1 | D6: 0 | E6: -2 | F6: 6 | G6: 30 | H6: =B6/40000*'Goods values'!$B$3*(1+D6+$L$2+MAX(($K$2+E6)*0.16,0)) -> 10.403154 | I6: =H6*'Goods values'!$C$3*3*MAX($M$2-(C6*0.075),0)*$N$2+H6 -> 32.031311
A7: Zanzibar | B7: =23725+19000 -> 42725 | C7: 1 | D7: 0 | E7: -2 | F7: 6 | G7: 40 | H7: =B7/40000*'Goods values'!$B$3*(1+D7+$L$2+MAX(($K$2+E7)*0.16,0)) -> 6.92145 | I7: =H7*'Goods values'!$C$3*3*MAX($M$2-(C7*0.075),0)*$N$2+H7 -> 21.311145
A8: Old Tientsin | B8: 34540 | C8: 1 | D8: 0 | E8: 0 | F8: 6 | G8: 32 | H8: =B8/40000*'Goods values'!$B$3*(1+D8+$L$2+MAX(($K$2+E8)*0.16,0)) -> 6.42444 | I8: =H8*'Goods values'!$C$3*3*MAX($M$2-(C8*0.075),0)*$N$2+H8 -> 19.780851
A9: Kwangchowan | B9: 25000 | C9: 1 | D9: 0 | E9: -1 | F9: 3 | G9: 32 | H9: =B9/40000*'Goods values'!$B$3*(1+D9+$L$2+MAX(($K$2+E9)*0.16,0)) -> 4.35 | I9: =H9*'Goods values'!$C$3*3*MAX($M$2-(C9*0.075),0)*$N$2+H9 -> 13.39365
A10: Lushun | B10: 22231 | C10: 1 | D10: 0 | E10: 0 | F10: 6 | G10: 32 | H10: =B10/40000*'Goods values'!$B$3*(1+D10+$L$2+MAX(($K$2+E10)*0.16,0)) -> 4.134966 | I10: =H10*'Goods values'!$C$3*3*MAX($M$2-(C10*0.075),0)*$N$2+H10 -> 12.73156
A11: Muqdisho | B11: =14800+5500 -> 20300 | C11: 1 | D11: 0 | E11: -1 | F11: 6 | G11: 35 | H11: =B11/40000*'Goods values'!$B$3*(1+D11+$L$2+MAX(($K$2+E11)*0.16,0)) -> 3.5322 | I11: =H11*'Goods values'!$C$3*3*MAX($M$2-(C11*0.075),0)*$N$2+H11 -> 10.875644
A12: Sado | B12: =18400+1750 -> 20150 | C12: 1 | D12: 0 | E12: -2 | F12: 6 | G12: 30 | H12: =B12/40000*'Goods values'!$B$3*(1+D12+$L$2+MAX(($K$2+E12)*0.16,0)) -> 3.2643 | I12: =H12*'Goods values'!$C$3*3*MAX($M$2-(C12*0.075),0)*$N$2+H12 -> 10.05078
A13: Chusan Islands | B13: 12150 | C13: 1 | D13: 0 | E13: -2 | F13: 2 | G13: 32 | H13: =B13/40000*'Goods values'!$B$3*(1+D13+$L$2+MAX(($K$2+E13)*0.16,0)) -> 1.9683 | I13: =H13*'Goods values'!$C$3*3*MAX($M$2-(C13*0.075),0)*$N$2+H13 -> 6.0603957
A14: Macao | B14: =6580+450 -> 7030 | C14: 1 | D14: 0.25 | E14: 0 | F14: 3 | G14: 35 | H14: =B14/40000*'Goods values'!$B$3*(1+D14+$L$2+MAX(($K$2+E14)*0.16,0)) -> 1.4393925 | I14: =H14*'Goods values'!$C$3*3*MAX($M$2-(C14*0.075),0)*$N$2+H14 -> 4.4318895
A15: Socotra | B15: 7562 | C15: 1 | D15: 0 | E15: -2 | F15: 6 | G15: 20 | H15: =B15/40000*'Goods values'!$B$3*(1+D15+$L$2+MAX(($K$2+E15)*0.16,0)) -> 1.225044 | I15: =H15*'Goods values'!$C$3*3*MAX($M$2-(C15*0.075),0)*$N$2+H15 -> 3.7719105
A16: Weihaiwei | B16: 6375 | C16: 1 | D16: 0 | E16: 0 | F16: 6 | G16: 32 | H16: =B16/40000*'Goods values'!$B$3*(1+D16+$L$2+MAX(($K$2+E16)*0.16,0)) -> 1.18575 | I16: =H16*'Goods values'!$C$3*3*MAX($M$2-(C16*0.075),0)*$N$2+H16 -> 3.6509243
A17: Tsingtao | B17: 5475 | C17: 1 | D17: 0 | E17: 0 | F17: 6 | G17: 32 | H17: =B17/40000*'Goods values'!$B$3*(1+D17+$L$2+MAX(($K$2+E17)*0.16,0)) -> 1.01835 | I17: =H17*'Goods values'!$C$3*3*MAX($M$2-(C17*0.075),0)*$N$2+H17 -> 3.1354996
A18: Brunei | B18: =5375+500 -> 5875 | C18: 1 | D18: 0 | E18: -3 | F18: 6 | G18: 31 | H18: =B18/40000*'Goods values'!$B$3*(1+D18+$L$2+MAX(($K$2+E18)*0.16,0)) -> 0.88125 | I18: =H18*'Goods values'!$C$3*3*MAX($M$2-(C18*0.075),0)*$N$2+H18 -> 2.7133687
A19: Barbara | B19: 5000 | C19: 1 | D19: 0 | E19: -2 | F19: 6 | G19: 31 | H19: =B19/40000*'Goods values'!$B$3*(1+D19+$L$2+MAX(($K$2+E19)*0.16,0)) -> 0.81 | I19: =H19*'Goods values'!$C$3*3*MAX($M$2-(C19*0.075),0)*$N$2+H19 -> 2.49399
A20: Sidi Infi | B20: 4325 | C20: 1 | D20: 0 | E20: -3 | F20: 6 | G20: 30 | H20: =B20/40000*'Goods values'!$B$3*(1+D20+$L$2+MAX(($K$2+E20)*0.16,0)) -> 0.64875 | I20: =H20*'Goods values'!$C$3*3*MAX($M$2-(C20*0.075),0)*$N$2+H20 -> 1.9975013
A21: Hong Kong | B21: 2750 | C21: 1 | D21: 0.25 | E21: 0 | F21: 3 | G21: 32 | H21: =B21/40000*'Goods values'!$B$3*(1+D21+$L$2+MAX(($K$2+E21)*0.16,0)) -> 0.5630625 | I21: =H21*'Goods values'!$C$3*3*MAX($M$2-(C21*0.075),0)*$N$2+H21 -> 1.7336694
A22: Tsushima | B22: 3263 | C22: 1 | D22: 0 | E22: -2 | F22: 6 | G22: 31 | H22: =B22/40000*'Goods values'!$B$3*(1+D22+$L$2+MAX(($K$2+E22)*0.16,0)) -> 0.528606 | I22: =H22*'Goods values'!$C$3*3*MAX($M$2-(C22*0.075),0)*$N$2+H22 -> 1.6275779
A23: Oki Islands | B23: 1950 | C23: 1 | D23: 0 | E23: -2 | F23: 6 | G23: 35 | H23: =B23/40000*'Goods values'!$B$3*(1+D23+$L$2+MAX(($K$2+E23)*0.16,0)) -> 0.3159 | I23: =H23*'Goods values'!$C$3*3*MAX($M$2-(C23*0.075),0)*$N$2+H23 -> 0.9726561
A24: Gwadar | B24: =1250+200 -> 1450 | C24: 1 | D24: 0 | E24: -2 | F24: 6 | G24: 35 | H24: =B24/40000*'Goods values'!$B$3*(1+D24+$L$2+MAX(($K$2+E24)*0.16,0)) -> 0.2349 | I24: =H24*'Goods values'!$C$3*3*MAX($M$2-(C24*0.075),0)*$N$2+H24 -> 0.7232571
A25: Qeshm | B25: 1250 | C25: 1 | D25: 0 | E25: -2 | F25: 6 | G25: 35 | H25: =B25/40000*'Goods values'!$B$3*(1+D25+$L$2+MAX(($K$2+E25)*0.16,0)) -> 0.2025 | I25: =H25*'Goods values'!$C$3*3*MAX($M$2-(C25*0.075),0)*$N$2+H25 -> 0.6234975
A26: Tarfaya | B26: 555 | C26: 1 | D26: 0.25 | E26: 0 | F26: 6 | G26: 15 | H26: =B26/40000*'Goods values'!$B$3*(1+D26+$L$2+MAX(($K$2+E26)*0.16,0)) -> 0.11363625 | I26: =H26*'Goods values'!$C$3*3*MAX($M$2-(C26*0.075),0)*$N$2+H26 -> 0.34988601
A27: Juzur Khuriya Muriya | B27: 35 | C27: 1 | D27: 0 | E27: -2 | F27: 6 | G27: 10 | H27: =B27/40000*'Goods values'!$B$3*(1+D27+$L$2+MAX(($K$2+E27)*0.16,0)) -> 0.00567 | I27: =H27*'Goods values'!$C$3*3*MAX($M$2-(C27*0.075),0)*$N$2+H27 -> 0.01745793
A29: Hainan | B29: =632620+146420 -> 779040 | C29: 1 | D29: 0 | E29: -3 | F29: 3 | H29: =B29/40000*'Goods values'!$B$3*(1+D29+MAX(($K$2+E29)*0.16,0)) -> 58.428 | I29: =H29*'Goods values'!$C$24*MAX($M$2-(C29*0.075),0)*$N$2 -> 3.374217
A30: al-Jazair | B30: 48171 | C30: 1 | D30: 0 | E30: 0 | F30: 6 | H30: =B30/40000*'Goods values'!$B$3*(1+D30+MAX(($K$2+E30)*0.16,0)) -> 5.346981 | I30: =H30*'Goods values'!$C$24*MAX($M$2-(C30*0.075),0)*$N$2 -> 0.30878815
A31: Wahran | B31: 42720 | C31: 1 | D31: 0 | E31: -2 | F31: 6 | H31: =B31/40000*'Goods values'!$B$3*(1+D31+MAX(($K$2+E31)*0.16,0)) -> 3.71664 | I31: =H31*'Goods values'!$C$24*MAX($M$2-(C31*0.075),0)*$N$2 -> 0.21463596
A32: Ennab | B32: 21165 | C32: 1 | D32: 0 | E32: -2 | F32: 3 | H32: =B32/40000*'Goods values'!$B$3*(1+D32+MAX(($K$2+E32)*0.16,0)) -> 1.841355 | I32: =H32*'Goods values'!$C$24*MAX($M$2-(C32*0.075),0)*$N$2 -> 0.10633825
A33: Bijaya | B33: 20505 | C33: 1 | D33: 0 | E33: -2 | F33: 3 | H33: =B33/40000*'Goods values'!$B$3*(1+D33+MAX(($K$2+E33)*0.16,0)) -> 1.783935 | I33: =H33*'Goods values'!$C$24*MAX($M$2-(C33*0.075),0)*$N$2 -> 0.10302225
A34: Taiwan | B34: =243850+397100+16000+41000 -> 697950 | C34: 5 | D34: 0.01 | E34: =-11/5 -> -2.2 | F34: 6 | H34: =B34/40000*'Goods values'!$B$3*(1+D34+MAX(($K$2+E34)*0.16,0)) -> 59.570033 | I34: =H34*'Goods values'!$C$24*MAX($M$2-(C34*0.075),0)*$N$2 -> 0

Sheet Goods values
A1: RGO Name | B1: Value | C1: Price | D1: Price per boi | F1: Date | G1: £ Output | H1: Farming Output | I1: Mining Output | J1: Goods Output | K1: Goods Throughput | L1: Railroad lvl | M1: Terrain Modifier
A2: Gold | B2: 3 | C2: 20 | D2: =B2*C2*3 -> 180 | F2: Bida | G2: =$D$3*(1+I2+J2+(L2*0.16)+$M$2)*(1+K2) -> 162 | I2: 0 | J2: 0 | K2: 0 | L2: 0 | M2: 0
A3: Precious Goods | B3: 3 | C3: 18 | D3: =B3*C3*3 -> 162 | F3: Base | G3: =$D$3*(1+I3+J3+(L3*0.16)+$M$2)*(1+K3) -> 309.42 | I3: 0.65 | J3: 0.1 | K3: 0 | L3: 1
A4: Gems | B4: 3 | C4: 18 | D4: =B4*C4*3 -> 162 | F4: 1830 | G4: =$D$3*(1+I4+J4+(L4*0.16)+$M$2)*(1+K4) -> 447.12 | I4: 1.05 | J4: 0.55 | K4: 0 | L4: 1
A5: Pearls | B5: 3 | C5: 18 | D5: =B5*C5*3 -> 162 | F5: 1840 | G5: =$D$3*(1+I5+J5+(L5*0.16)+$M$2)*(1+K5) -> 473.04 | I5: 1.05 | J5: 0.55 | K5: 0 | L5: 2
A6: Mercury | B6: 3 | C6: 18 | D6: =B6*C6*3 -> 162 | F6: 1850 | G6: =$D$3*(1+I6+J6+(L6*0.16)+$M$2)*(1+K6) -> 563.76 | I6: 1.2 | J6: 0.8 | K6: 0 | L6: 3
A7: Precious Metal | B7: 2.25 | C7: 20 | D7: =B7*C7*3 -> 135 | F7: 1870 | G7: =$D$3*(1+I7+J7+(L7*0.16)+$M$2)*(1+K7) -> 654.48 | I7: 1.2 | J7: 1.2 | K7: 0 | L7: 4
A8: Slave Trade | B8: 3 | C8: 13 | D8: =B8*C8*3 -> 117 | F8: 1880 | G8: =$D$3*(1+I8+J8+(L8*0.16)+$M$2)*(1+K8) -> 678.78 | I8: 1.35 | J8: 1.2 | K8: 0 | L8: 4
A9: Ivory | B9: 3 | C9: 10 | D9: =B9*C9*3 -> 90 | F9: 1898 | G9: =$D$3*(1+I9+J9+(L9*0.16)+$M$2)*(1+K9) -> 704.7 | I9: 1.35 | J9: 1.2 | K9: 0 | L9: 5
A10: Tropical Wood | B10: 4 | C10: 5.4 | D10: =B10*C10 -> 21.6 | F10: 1900 | G10: =$D$3*(1+I10+J10+(L10*0.16)+$M$2)*(1+K10) -> 907.2 | I10: 2.2 | J10: 1.6 | K10: 0 | L10: 5
A11: Sulphur | B11: 3 | C11: 6 | D11: =B11*C11 -> 18 | F11: 1915 | G11: =$D$3*(1+I11+J11+(L11*0.16)+$M$2)*(1+K11) -> 933.12 | I11: 2.2 | J11: 1.6 | K11: 0 | L11: 6
A12: Oil | B12: 1 | C12: 12 | D12: =B12*C12 -> 12
A13: Wood | B13: 8 | C13: 0.9 | D13: =B13*C13 -> 7.2
A14: Iron | B14: 2 | C14: 3.5 | D14: =B14*C14 -> 7
A15: Coal | B15: 2.4 | C15: 2.3 | D15: =B15*C15 -> 5.52
A16: Rubber | B16: 0.75 | C16: 7 | D16: =B16*C16 -> 5.25
A17: Fruit | B17: 2.7 | C17: 1.8 | D17: =B17*C17 -> 4.86
A18: Tea | B18: 1.75 | C18: 2.6 | D18: =B18*C18 -> 4.55
A19: Grain | B19: 1.7 | C19: 2.2 | D19: =B19*C19 -> 3.74
A20: Cotton | B20: 1.8 | C20: 2 | D20: =B20*C20 -> 3.6
A21: Cattle | B21: 1.7 | C21: 2 | D21: =B21*C21 -> 3.4
A22: Wool | B22: 4.8 | C22: 0.7 | D22: =B22*C22 -> 3.36
A23: Sugar | B23: 1 | C23: 3.2 | D23: =B23*C23 -> 3.2
... A29: Opium | B29: 0.7 | C29: 3.2 | D29: =B29*C29 -> 2.24

Sheet POP Growth
A1: Date | B1: POP | C1: POP Growth | E1: Life Rating | F1: Starting POP
A2: 1830 | B2: =F2 -> 452530 | C2: 0 | E2: 30 | F2: 452530
A3: 1831 | B3: =B2*(1+0.0001+MAX(($E$2-36),0)*0.0001+C2) -> 452575.25 | C3: 0
A4: 1832 | B4: =B3*(1+0.0001+MAX(($E$2-36),0)*0.0001+C3) -> 452620.51 | C4: 0
A5: 1833 | B5: =B4*(1+0.0001+MAX(($E$2-36),0)*0.0001+C4) -> 452665.77 | C5: 0
A6: 1834 | B6: =B5*(1+0.0001+MAX(($E$2-36),0)*0.0001+C5) -> 452711.04 | C6: 0.0001
A7: 1835 | B7: =B6*(1+0.0001+MAX(($E$2-36),0)*0.0001+C6) -> 452801.58 | C7: 0.0001
A8: 1836 | B8: =B7*(1+0.0001+MAX(($E$2-36),0)*0.0001+C7) -> 452892.14 | C8: 0.0002
A9: 1837 | B9: =B8*(1+0.0001+MAX(($E$2-36),0)*0.0001+C8) -> 453028.01 | C9: 0.0003
A10: 1838 | B10: =B9*(1+0.0001+MAX(($E$2-36),0)*0.0001+C9) -> 453209.22 | C10: 0.0004
A11: 1839 | B11: =B10*(1+0.0001+MAX(($E$2-36),0)*0.0001+C10) -> 453435.83 | C11: 0.0004
A12: 1840 | B12: =B11*(1+0.0001+MAX(($E$2-36),0)*0.0001+C11) -> 453662.54 | C12: 0.0005
A13: 1841 | B13: =B12*(1+0.0001+MAX(($E$2-36),0)*0.0001+C12) -> 453934.74 | C13: 0.0005
A14: 1842 | B14: =B13*(1+0.0001+MAX(($E$2-36),0)*0.0001+C13) -> 454207.1 | C14: 0.0005
... A108: 1936 | B108: =B107*(1+0.0001+MAX(($E$2-36),0)*0.0001+C107) -> 486058.11 | C108: 0.0008

Sheet Military
A1: Attacker | D1: Modifier | E1: Mil. Tac. | F1: Fort lvl | G1: Siege | H1: Exp | I1: Roll | K1: Attacker Damage | N1: Real Stats | O1: Mil. Tac. | P1: Exp | R1: Roll | S1: Casualties
A2: Frontline Unit | D2: 1 | E2: 1.5 | F2: 0 | G2: 5 | H2: 30 | I2: 5 | K2: Frontline | L2: Backline | N2: Frontline Attack | O2: =IF(E2=0,1,E2+1.5) -> 3 | P2: =H2/100 -> 0.3 | R2: 0 | S2: 36
A3: Attack | B3: Discipline | K3: =3000/3000*VLOOKUP(MAX(D2+I2,0),R2:S23,2,TRUE())*N3/10/(O10+IF(F10=0,0,(F10-G2)/10)/(1+P10)) -> 224.25 | L3: =3000/3000*VLOOKUP(MAX(D2+I2,0),R2:S23,2,TRUE())*N6/10/(O10+IF(F10=0,0,(F10-G2)/10)/(1+P10)) -> 401.45625 | N3: =A4+10 -> 46 | R3: 1 | S3: 48
A4: 36 | B4: 1 | K4: =K3+L3 -> 625.70625 | R4: 2 | S4: 60
A5: Backline Unit | N5: Backline Attack | R5: 3 | S5: 72
A6: Attack | B6: Support | C6: Discipline | N6: =(A7+10)*B7 -> 82.35 | R6: 4 | S6: 96
A7: 8.3 | B7: 4.5 | C7: 1 | K7: =K4/K12 -> 0.56676291 | R7: 5 | S7: 120
R8: 6 | S8: 150
A9: Defender | D9: Modifier | E9: Mil. Tac. | F9: Fort lvl | G9: Siege | H9: Exp | I9: Roll | K9: Defender Damage | N9: Real Stats | O9: Mil. Tac. | P9: Exp | R9: 7 | S9: 180
A10: Frontline Unit | D10: 2 | E10: 1.5 | F10: 6 | G10: 0 | H10: 30 | I10: 5 | K10: Frontline | L10: Backline | N10: Frontline Defence | O10: =IF(E10=0,1,E10+1.5) -> 3 | P10: =H10/100 -> 0.3 | R10: 8 | S10: 210
A11: Defence | B11: Discipline | K11: =3000/3000*VLOOKUP(MAX(D10+I10,0),R2:S23,2,TRUE())*N11/10/(O2+IF(F2=0,0,(F2-G10)/10)/(1+P2)) -> 204 | L11: =3000/3000*VLOOKUP(MAX(D10+I10,0),R2:S23,2,TRUE())*N14/10/(O2+IF(F2=0,0,(F2-G10)/10)/(1+P2)) -> 900 | N11: =A12+10 -> 34 | R11: 9 | S11: 240
A12: 24 | B12: 1 | K12: =K11+L11 -> 1104 | R12: 10 | S12: 270
A13: Backline Unit | N13: Backline Defence | R13: 11 | S13: 300
A14: Defence | B14: Support | C14: Discipline | N14: =(A15+10)*B15 -> 150 | R14: 12 | S14: 330
A15: 15 | B15: 6 | C15: 0.1 | K15: =K12/K4 -> 1.7644062 | R15: 13 | S15: 360
R16: 14 | S16: 390
J17: 0 | K17: 216 | L17: 216 | R17: 15 | S17: 420
J18: 1 | K18: 309 | L18: 422 | R18: 16 | S18: 450
J19: 2 | R19: 17 | S19: 480
J20: 3 | R20: 18 | S20: 510
J21: 4 | K21: 399 | L21: 540 | R21: 19 | S21: 540
J22: 5 | K22: 463 | L22: 753 | R22: 20 | S22: 570
J23: 6 | K23: 626 | L23: 1104 | R23: 21 | S23: 600

Sheet Navy
A1: Attacker | T1: Dice | U1: Modifier | W1: Date
A2: Dice | B2: Attack | C2: Hull | D2: Experience | E2: Evasion | F2: Strength | H2: Attack | I2: Org Damage | J2: Str Damage | T2: -5 | U2: 2 | W2: Base Stats
A3: 7 | B3: 17 | C3: 13 | D3: 0 | E3: 0 | F3: 1 | H3: =B3*VLOOKUP(A3,$T$2:$U$21,2)/C6*(1-(D6/100))*(1-E6)*F3 -> 46.363636 | I3: =H3*0.4 -> 18.545455 | J3: =H3*0.2 -> 9.2727273 | T3: -4 | U3: 2 | W3: No reforms
A4: Defender | T4: -3 | U4: 2 | W4: Unciv Reforms
A5: Dice | B5: Attack | C5: Hull | D5: Experience | E5: Evasion | F5: Strength | H5: Attack | I5: Org Damage | J5: Str Damage | T5: -2 | U5: 2 | W5: Base Techs
A6: 7 | B6: 25 | C6: 11 | D6: 0 | E6: 0 | F6: 1 | H6: =B6*VLOOKUP(A6,$T$2:$U$21,2)/C3*(1-(D3/100))*(1-E3)*F6 -> 57.692308 | I6: =H6*0.4 -> 23.076923 | J6: =H6*0.2 -> 11.538462 | T6: -1 | U6: 4 | W6: 2 row
T7: 0 | U7: 6
T8: 1 | U8: 8
T9: 2 | U9: 10
T10: 3 | U10: 12
T11: 4 | U11: 16
T12: 5 | U12: 20
T13: 6 | U13: 25
T14: 7 | U14: 30
T15: 8 | U15: 35
T16: 9 | U16: 40
T17: 10 | U17: 45
T18: 11 | U18: 50
... T21: 14 | U21: 80

Sheet Stocks
A1: Date | B1: Tax Efficiency | C1: Tariff Efficiency | D1: Admin Efficiency | E1: RGO Output | F1: RGO Throughput | G1: Mining Output | H1: Farming Output | I1: Farm Size | J1: Mine Size | K1: Factory Input | L1: Factory Output | M1: Factory Throughput | N1: Factory Cost | O1: POP Growth | P1: Mobilisation Impact | Q1: Armies Supply Consumption | R1: Railroad lvl | S1: Inventions | T1: Max Loan Amount | U1: Loan Interest | V1: Cotton Output | W1: Wool Output | X1: Silk Output | Y1: Coal Output | Z1: Coal Size | AA1: Sulfur Output | AB1: Sulfur Size | AC1: Sulfur Throughput | AD1: Iron Output | AE1: Iron Size | AF1: Wood Output | AG1: Tropical Wood Output | AH1: Sugar Output | AI1: Rubber Output | AJ1: Oil Output | AK1: Steel Output | AL1: Cement Output | AM1: Machine Parts Output | AN1: Glass Output | AO1: Fertilizer Output | AP1: Explosives Output | AQ1: Clipper Convoys Throughput | AR1: Streamer Convoys Throughput | AS1: Fabric Output | AT1: Fabric Throughput | AU1: Lumber Output | AV1: Fuel Output | AW1: Electric Gear Output | AX1: Paper Output | AY1: Livestock Output | AZ1: Fish Output | BA1: Fruit Output | BB1: Grain Output | BC1: Grain Throughput | BD1: Tobacco Output | BE1: Tea Output | BF1: Coffee Output | BG1: Opium Output | BH1: Wine Output | BI1: Beverages Output | BJ1: Beverages Throughput | BK1: Regular Clothes Output | BL1: Luxury Clothes Output | BM1: Furniture Output | BN1: Luxury Furniture | BO1: Telephones Output | BP1: Automobiles Output | BQ1: Radios Output | BR1: Ammunition Output | BS1: Small Arms Output | BT1: Artillery Output | BU1: Canned Food Output | BV1: Aeroplanes Output | BW1: Tanks Output | BX1: Precious Goods Output | BY1: Precious Goods Size | BZ1: Silver Output | CA1: Gold Output | CB1: Ivory Output | CC1: Ivory Size | CD1: Pearls Output | CE1: Pearls Size
A2: Base Values | B2: 0.2 | C2: 0.1 | D2: 0.2 | E2: 1 | F2: 1 | G2: 1 | H2: 1 | I2: 1 | J2: 1 | K2: 1 | L2: 1 | M2: 1 | N2: 1 | O2: 0.0001 | P2: 1 | Q2: 1 | T2: 1 | U2: 1 | V2: 1 | W2: 1 | X2: 1 | Y2: 1 | Z2: 1 | AA2: 1 | AB2: 1 | AC2: 1 | AD2: 1 | AE2: 1 | AF2: 1 | AG2: 1 | AH2: 1 | AI2: 1 | AJ2: 1 | AK2: 1 | AL2: 1 | AM2: 1 | AN2: 1 | AO2: 1 | AP2: 1 | AQ2: 1 | AR2: 1 | AS2: 1 | AT2: 1 | AU2: 1 | AV2: 1 | AW2: 1 | AX2: 1 | AY2: 1 | AZ2: 1 | BA2: 1 | BB2: 1 | BC2: 1 | BD2: 1 | BE2: 1 | BF2: 1 | BG2: 1 | BH2: 1 | BI2: 1 | BJ2: 1 | BK2: 1 | BL2: 1 | BM2: 1 | BN2: 1 | BO2: 1 | BP2: 1 | BQ2: 1 | BR2: 1 | BS2: 1 | BT2: 1 | BU2: 1 | BV2: 1 | BW2: 1 | BX2: 1 | BY2: 1 | BZ2: 1 | CA2: 1 | CB2: 1 | CC2: 1 | CD2: 1 | CE2: 1 | CW2: 500000 | CX2: =CZ2/$CW$2 -> 0.0076 | CY2: 1 | CZ2: 3800 | DA2: =CZ2-CZ1 -> 3800 | DB2: =CZ2/$CZ$52 -> 0.019701982
A3: No Reforms | I3: 0.25 | J3: 0.25 | Q3: =-0.05-0.05-0.1-0.15 -> -0.35 | T3: -1 | CX3: =CZ3/$CW$2 -> 0.015202 | CY3: 2 | CZ3: 7601 | DA3: =CZ3-CZ2 -> 3801 | DB3: =CZ3/$CZ$52 -> 0.039409148
A4: Unciv Reforms | B4: =0.1+0.05 -> 0.15 | C4: 0.2 | D4: =0.1+0.05 -> 0.15 | G4: =0.25+0.25+0.05 -> 0.55 | H4: =0.25+0.25+0.25 -> 0.75 | I4: -0.25 | J4: -0.25 | K4: -0.01 | L4: 0.01 | Q4: =0.05+0.05+0.1+0.1+0.1+0.1 -> 0.5 | R4: 1 | T4: 0.8 | AH4: 0.1 | BD4: 0.1 | BE4: 0.1 | BF4: 0.1 | BX4: 0.1 | BY4: 0.05 | CX4: =CZ4/$CW$2 -> 0.022802 | CY4: 3 | CZ4: 11401 | DA4: =CZ4-CZ3 -> 3800 | DB4: =CZ4/$CZ$52 -> 0.05911113
A5: Base Techs | B5: =-0.1-0.05+0.01+0.05 -> -0.09 | C5: -0.2 | D5: =-0.1+0.05 -> -0.05 | F5: 0.25 | G5: =-0.25-0.25+0.1 -> -0.4 | H5: =-0.25-0.25+0.1 -> -0.4 | M5: 0.25 | Q5: =0.15-0.05 -> 0.1 | S5: =6+10+9 -> 25 | T5: 0.2 | Y5: 0.5 | AA5: 0.1 | AH5: 0.3 | AQ5: 0.1 | BA5: 0.1 | BB5: 0.1 | BF5: 0.1 | BJ5: 0.05 | BT5: 0.05 | CX5: =CZ5/$CW$2 -> 0.030404 | CY5: 4 | CZ5: 15202 | DA5: =CZ5-CZ4 -> 3801 | DB5: =CZ5/$CZ$52 -> 0.078818296
A6: 1830 2 row | B6: =0.05+0.01+0.01 -> 0.07 | D6: 0.05 | G6: =0.1+0.1 -> 0.2 | H6: =0.1+0.25 -> 0.35 | K6: -0.01 | L6: =0.01+0.01+0.01+0.01 -> 0.04 | M6: =0.05+0.05 -> 0.1 | O6: =0.0001+0.0001+0.0001+0.0001 -> 0.0004 | P6: -0.1 | Q6: =0.1+0.1+0.1+0.1 -> 0.4 | S6: =9+13+12+19+21 -> 74 | U6: =-0.002-0.002 -> -0.004 | W6: =0.2+0.2+0.1 -> 0.5 | X6: 0.2 | AF6: =0.15+0.15 -> 0.3 | AG6: 0.1 | AH6: =0.1+0.15 -> 0.25 | AN6: 0.1 | AR6: 0.1 | AS6: 0.1 | AY6: 0.2 | AZ6: 0.5 | BA6: 0.15 | BB6: =0.1+0.15 -> 0.25 | BC6: 0.1 | BD6: 0.1 | BE6: =0.1+0.15 -> 0.25 | BF6: 0.1 | BI6: 0.1 | BR6: 0.1 | BX6: =0.1+0.1 -> 0.2 | BY6: =0.05+0.05 -> 0.1 | CX6: =CZ6/$CW$2 -> 0.038004 | CY6: 5 | CZ6: 19002 | DA6: =CZ6-CZ5 -> 3800 | DB6: =CZ6/$CZ$52 -> 0.098520277
A7: 1830 all | B7: =0.01+0.01+0.01+0.01 -> 0.04 | D7: 0.05 | G7: =0.05+0.1+0.5+0.5 -> 1.15 | H7: =0.1+0.25+0.02 -> 0.37 | K7: -0.01 | L7: =0.01+0.01+0.01+0.01 -> 0.04 | M7: =0.05+0.05 -> 0.1 | N7: =-0.03-0.02 -> -0.05 | O7: 0.0001 | S7: =16+2+20 -> 38 | V7: 0.5 | X7: 0.2 | AH7: =0.1+0.25 -> 0.35 | AI7: 1 | AL7: 0.1 | AM7: 0.02 | AO7: 0.05 | AP7: =0.25+0.02 -> 0.27 | AS7: =0.1+0.05 -> 0.15 | AX7: 0.01 | BD7: 0.1 | BE7: 0.1 | BF7: 0.1 | BH7: 0.02 | BI7: 0.1 | BM7: 0.02 | BN7: 0.02 | BS7: 0.02 | BU7: 0.02 | BX7: =0.1+0.05+0.1 -> 0.25 | BY7: =0.05+0.05 -> 0.1 | CX7: =CZ7/$CW$2 -> 0.045606 | CY7: 6 | CZ7: 22803 | DA7: =CZ7-CZ6 -> 3801 | DB7: =CZ7/$CZ$52 -> 0.11822744
A8: 1840 | R8: 1 | S8: =4+3 -> 7 | Y8: =0.2+0.5+0.5 -> 1.2 | Z8: 0.25 | AA8: =0.2+0.1 -> 0.3 | AB8: 0.25 | AD8: =0.15+0.1 -> 0.25 | AE8: 0.25 | BZ8: 0.1 | CA8: 0.1 | CX8: =CZ8/$CW$2 -> 0.053206 | CY8: 7 | CZ8: 26603 | DA8: =CZ8-CZ7 -> 3800 | DB8: =CZ8/$CZ$52 -> 0.13792943
A9: 1848 | S9: 3 | CX9: =CZ9/$CW$2 -> 0.060808 | CY9: 8 | CZ9: 30404 | DA9: =CZ9-CZ8 -> 3801 | DB9: =CZ9/$CZ$52 -> 0.15763659
A10: 1850 | B10: =0.05+0.01+0.01+0.01+0.01+0.01 -> 0.1 | D10: 0.05 | G10: =0.05+0.1 -> 0.15 | H10: =0.3+0.1+0.25+0.05 -> 0.7 | K10: -0.01 | L10: =0.01+0.01+0.025+0.025 -> 0.07 | M10: =0.1+0.05 -> 0.15 | N10: =-0.01-0.01-0.01-0.1+0.05 -> -0.08 | Q10: =0.2+0.05+0.2+0.05+0.05+0.05+0.2 -> 0.8 | R10: 1 | Y10: =0.2+0.2+0.25 -> 0.65 | Z10: 0.25 | AA10: =0.15+0.1 -> 0.25 | AB10: 0.25 | AD10: =0.2+0.1+0.3+0.4+0.25+0.25 -> 1.5 | AE10: 0.25 | AF10: =0.15+0.15 -> 0.3 | AH10: =0.1+0.1+0.1+0.05+0.1+0.15 -> 0.6 | AJ10: 0.1 | AK10: =0.3+0.05+0.05 -> 0.4 | AL10: 0.15 | AY10: 0.3 | AZ10: 0.1 | BD10: =0.1+0.25 -> 0.35 | BE10: =0.1+0.2+0.2 -> 0.5 | BF10: =0.1+0.2+0.3+0.2+0.05 -> 0.85 | BG10: 0.2 | BH10: 0.05 | BI10: =0.2+0.1 -> 0.3 | BK10: 0.1 | BT10: 0.1 | BU10: 0.05 | BX10: =0.1+0.05+0.1 -> 0.25 | BY10: =0.05+0.05 -> 0.1 | BZ10: 0.1 | CA10: 0.1 | CB10: 0.5 | CC10: 0.2 | CD10: 0.1 | CE10: 0.5 | CX10: =CZ10/$CW$2 -> 0.068408 | CY10: 9 | CZ10: 34204 | DA10: =CZ10-CZ9 -> 3800 | DB10: =CZ10/$CZ$52 -> 0.17733857
A11: 1855 | CX11: =CZ11/$CW$2 -> 0.07601 | CY11: 10 | CZ11: 38005 | DA11: =CZ11-CZ10 -> 3801 | DB11: =CZ11/$CZ$52 -> 0.19704574
A12: 1860 | AC12: 0.05 | AO12: 0.05 | AV12: 0.05 | CX12: =CZ12/$CW$2 -> 0.08361 | CY12: 11 | CZ12: 41805 | DA12: =CZ12-CZ11 -> 3800 | DB12: =CZ12/$CZ$52 -> 0.21674772
A13: 1870 | B13: =0.05+0.01+0.01 -> 0.07 | D13: 0.05 | K13: =-0.01-0.01-0.01-0.01 -> -0.04 | L13: 0.01 | M13: =0.1+0.05 -> 0.15 | N13: =-0.01-0.01-0.01-0.01-0.01-0.01-0.1 -> -0.16 | O13: 0.0001 | P13: -0.2 | Q13: =0.2+0.05+0.2+0.05+0.05+0.05+0.2 -> 0.8 | R13: 1 | V13: 0.2 | W13: 0.2 | X13: 0.2 | Y13: =0.3+0.25+0.25+0.1+0.25 -> 1.15 | Z13: =0.75+0.25 -> 1 | AA13: 0.2 | AB13: =0.75+0.25 -> 1 | AD13: =0.25+0.3+0.1 -> 0.65 | AE13: =0.75+0.25 -> 1 | AH13: =0.1+0.25 -> 0.35 | AP13: 0.03 | AR13: 0.05 | AS13: 0.05 | AT13: 0.05 | AY13: =0.2+0.2 -> 0.4 | AZ13: 0.15 | BA13: 0.2 | BD13: =0.1+0.5+0.25 -> 0.85 | BE13: =0.1+0.2 -> 0.3 | BF13: =0.1+0.1+0.2+0.1 -> 0.5 | BH13: 0.02 | BI13: 0.05 | BO13: 0.03 | BP13: 0.03 | BR13: 0.03 | BS13: 0.03 | BT13: 0.07 | BV13: 0.03 | BX13: =0.1+0.2+0.1 -> 0.4 | BY13: =0.05+0.05 -> 0.1 | BZ13: 0.2 | CA13: 0.2 | CX13: =CZ13/$CW$2 -> 0.091212 | CY13: 12 | CZ13: 45606 | DA13: =CZ13-CZ12 -> 3801 | DB13: =CZ13/$CZ$52 -> 0.23645489
A14: 1872 | CX14: =CZ14/$CW$2 -> 0.098808 | CY14: 13 | CZ14: 49404 | DA14: =CZ14-CZ13 -> 3798 | DB14: =CZ14/$CZ$52 -> 0.2561465
A15: 1875 | CX15: =CZ15/$CW$2 -> 0.106414 | CY15: 14 | CZ15: 53207 | DA15: =CZ15-CZ14 -> 3803 | DB15: =CZ15/$CZ$52 -> 0.27586404
A16: 1880 | G16: 0.15 | H16: =0.15+0.3 -> 0.45 | Q16: 0.05 | AF16: 0.15 | AH16: 0.3 | AL16: 0.15 | AM16: =0.01+0.02 -> 0.03 | AY16: 0.2 | BF16: 0.3 | BR16: 0.1 | CX16: =CZ16/$CW$2 -> 0.114014 | CY16: 15 | CZ16: 57007 | DA16: =CZ16-CZ15 -> 3800 | DB16: =CZ16/$CZ$52 -> 0.29556602
A17: 1890 | Y17: 0.35 | AA17: 0.2 | AD17: 0.2 | AK17: =0.02+0.02 -> 0.04 | BD17: 0.25 | BZ17: 0.05 | CA17: 0.05 | CX17: =CZ17/$CW$2 -> 0.121616 | CY17: 16 | CZ17: 60808 | DA17: =CZ17-CZ16 -> 3801 | DB17: =CZ17/$CZ$52 -> 0.31527318
A18: 1895 | CX18: =CZ18/$CW$2 -> 0.129216 | CY18: 17 | CZ18: 64608 | DA18: =CZ18-CZ17 -> 3800 | DB18: =CZ18/$CZ$52 -> 0.33497517
A19: 1898 | R19: 1 | AF19: 0.15 | CX19: =CZ19/$CW$2 -> 0.136816 | CY19: 18 | CZ19: 68408 | DA19: =CZ19-CZ18 -> 3800 | DB19: =CZ19/$CZ$52 -> 0.35467715
A20: 1900 | B20: 0.05 | D20: =0.05+0.05 -> 0.1 | E20: =0.05+0.05+0.05 -> 0.15 | G20: =0.15+0.5 -> 0.65 | H20: =0.15 -> 0.15 | K20: -0.01 | L20: 0.03 | M20: =0.1+0.05+0.02+0.02+0.1 -> 0.29 | N20: =0.1-0.01 -> 0.09 | Q20: =0.35+0.3+0.2 -> 0.85 | U20: =-0.005-0.005-0.005 -> -0.015 | AF20: 0.15 | AH20: =0.1+0.4 -> 0.5 | AN20: 0.05 | AQ20: 0.1 | AS20: =0.05+0.05 -> 0.1 | AW20: 0.03 | AZ20: 0.3 | BD20: =0.1+0.25 -> 0.35 | BE20: =0.1+0.3+0.2 -> 0.6 | BF20: =0.1+0.1+0.1+0.1 -> 0.4 | BL20: 1 | BO20: 0.03 | BQ20: 0.03 | BX20: =0.1+0.2+0.1 -> 0.4 | BY20: =0.05+0.05 -> 0.1 | CB20: 0.3 | CX20: =CZ20/$CW$2 -> 0.144418 | CY20: 19 | CZ20: 72209 | DA20: =CZ20-CZ19 -> 3801 | DB20: =CZ20/$CZ$52 -> 0.37438431
A21: 1905 | O21: 0.0001 | Y21: =0.4+0.4+0.5 -> 1.3 | AA21: =0.25+0.3 -> 0.55 | AD21: =0.25+0.3+0.5 -> 1.05 | AK21: 0.05 | CX21: =CZ21/$CW$2 -> 0.152018 | CY21: 20 | CZ21: 76009 | DA21: =CZ21-CZ20 -> 3800 | DB21: =CZ21/$CZ$52 -> 0.39408629
A22: 1910 | O22: 0.0001 | CX22: =CZ22/$CW$2 -> 0.159602 | CY22: 21 | CZ22: 79801 | DA22: =CZ22-CZ21 -> 3792 | DB22: =CZ22/$CZ$52 -> 0.4137468
A23: 1914 | Q23: 0.2 | CX23: =CZ23/$CW$2 -> 0.167202 | CY23: 22 | CZ23: 83601 | DA23: =CZ23-CZ22 -> 3800 | DB23: =CZ23/$CZ$52 -> 0.43344878
A24: 1915 | R24: 1 | CX24: =CZ24/$CW$2 -> 0.174822 | CY24: 23 | CZ24: 87411 | DA24: =CZ24-CZ23 -> 3810 | DB24: =CZ24/$CZ$52 -> 0.45320261
A25: 1919 | B25: 0.05 | N25: -0.01 | Q25: =0.2-0.3-0.3+0.2 -> -0.2 | CX25: =CZ25/$CW$2 -> 0.182422 | CY25: 24 | CZ25: 91211 | DA25: =CZ25-CZ24 -> 3800 | DB25: =CZ25/$CZ$52 -> 0.47290459
CX26: =CZ26/$CW$2 -> 0.190024 | CY26: 25 | CZ26: 95012 | DA26: =CZ26-CZ25 -> 3801 | DB26: =CZ26/$CZ$52 -> 0.49261176
CX27: =CZ27/$CW$2 -> 0.197624 | CY27: 26 | CZ27: 98812 | DA27: =CZ27-CZ26 -> 3800 | DB27: =CZ27/$CZ$52 -> 0.51231374
A28: Date | B28: Tax Efficiency | C28: Tariff Efficiency | D28: Admin Efficiency | E28: RGO Output | F28: RGO Throughput | G28: Mining Output | H28: Farming Output | I28: Farm Size | J28: Mine Size | K28: Factory Input | L28: Factory Output | M28: Factory Throughput | N28: Factory Cost | O28: POP Growth | P28: Mobilisation Impact | Q28: Armies Supply Consumption | R28: Railroad lvl | S28: Inventions | T28: Max Loan Amount | U28: Loan Interest | V28: Cotton Output | W28: Wool Output | X28: Silk Output | Y28: Coal Output | Z28: Coal Size | AA28: Sulfur Output | AB28: Sulfur Size | AC28: Sulfur Throughput | AD28: Iron Output | AE28: Iron Size | AF28: Wood Output | AG28: Tropical Wood Output | AH28: Sugar Output | AI28: Rubber Output | AJ28: Oil Output | AK28: Steel Output | AL28: Cement Output | AM28: Machine Parts Output | AN28: Glass Output | AO28: Fertilizer Output | AP28: Explosives Output | AQ28: Clipper Convoys Throughput | AR28: Streamer Convoys Throughput | AS28: Fabric Output | AT28: Fabric Throughput | AU28: Lumber Output | AV28: Fuel Output | AW28: Electric Gear Output | AX28: Paper Output | AY28: Livestock Output | AZ28: Fish Output | BA28: Fruit Output | BB28: Grain Output | BC28: Grain Throughput | BD28: Tobacco Output | BE28: Tea Output | BF28: Coffee Output | BG28: Opium Output | BH28: Wine Output | BI28: Beverages Output | BJ28: Beverages Throughput | BK28: Regular Clothes Output | BL28: Luxury Clothes Output | BM28: Furniture Output | BN28: Luxury Furniture | BO28: Telephones Output | BP28: Automobiles Output | BQ28: Radios Output | BR28: Ammunition Output | BS28: Small Arms Output | BT28: Artillery Output | BU28: Canned Food Output | BV28: Aeroplanes Output | BW28: Tanks Output | BX28: Precious Goods Output | BY28: Precious Goods Size | BZ28: Silver Output | CA28: Gold Output | CB28: Ivory Output | CC28: Ivory Size | CD28: Pearls Output | CE28: Pearls Size | CX28: =CZ28/$CW$2 -> 0.205226 | CY28: 27 | CZ28: 102613 | DA28: =CZ28-CZ27 -> 3801 | DB28: =CZ28/$CZ$52 -> 0.5320209
A29: Base Values | B29: =SUM(B2) -> 0.2 | C29: =SUM(C2) -> 0.1 | D29: =SUM(D2) -> 0.2 | E29: =SUM(E2) -> 1 | F29: =SUM(F2) -> 1 | G29: =SUM(G2) -> 1 | H29: =SUM(H2) -> 1 | I29: =SUM(I2) -> 1 | ... CE29: =SUM(CE2) -> 1 | CX29: =CZ29/$CW$2 -> 0.212826 | CY29: 28 | CZ29: 106413 | DA29: =CZ29-CZ28 -> 3800 | DB29: =CZ29/$CZ$52 -> 0.55172289
A30: No Reforms | B30: =SUM(B2:B3) -> 0.2 | C30: =SUM(C2:C3) -> 0.1 | D30: =SUM(D2:D3) -> 0.2 | E30: =SUM(E2:E3) -> 1 | F30: =SUM(F2:F3) -> 1 | G30: =SUM(G2:G3) -> 1 | H30: =SUM(H2:H3) -> 1 | I30: =SUM(I2:I3) -> 1.25 | ... CE30: =SUM(CE2:CE3) -> 1 | CX30: =CZ30/$CW$2 -> 0.220428 | CY30: 29 | CZ30: 110214 | DA30: =CZ30-CZ29 -> 3801 | DB30: =CZ30/$CZ$52 -> 0.57143005
A31: Unciv Reforms | B31: =SUM(B2:B4) -> 0.35 | C31: =SUM(C2:C4) -> 0.3 | D31: =SUM(D2:D4) -> 0.35 | E31: =SUM(E2:E4) -> 1 | F31: =SUM(F2:F4) -> 1 | G31: =SUM(G2:G4) -> 1.55 | H31: =SUM(H2:H4) -> 1.75 | I31: =SUM(I2:I4) -> 1 | ... CE31: =SUM(CE2:CE4) -> 1 | CX31: =CZ31/$CW$2 -> 0.228028 | CY31: 30 | CZ31: 114014 | DA31: =CZ31-CZ30 -> 3800 | DB31: =CZ31/$CZ$52 -> 0.59113203
A32: Base Techs | B32: =SUM(B2:B5) -> 0.26 | C32: =SUM(C2:C5) -> 0.1 | D32: =SUM(D2:D5) -> 0.3 | E32: =SUM(E2:E5) -> 1 | F32: =SUM(F2:F5) -> 1.25 | G32: =SUM(G2:G5) -> 1.15 | H32: =SUM(H2:H5) -> 1.35 | I32: =SUM(I2:I5) -> 1 | ... CE32: =SUM(CE2:CE5) -> 1 | CO32: China | CP32: Bavaria | CQ32: Darfur | CR32: Egypt | CS32: Nassau | CT32: Russia | CU32: France | CV32: UK | CX32: =CZ32/$CW$2 -> 0.23563 | CY32: 31 | CZ32: 117815 | DA32: =CZ32-CZ31 -> 3801 | DB32: =CZ32/$CZ$52 -> 0.6108392
A33: 1830 2 row | B33: =SUM(B2:B6) -> 0.33 | C33: =SUM(C2:C6) -> 0.1 | D33: =SUM(D2:D6) -> 0.35 | E33: =SUM(E2:E6) -> 1 | F33: =SUM(F2:F6) -> 1.25 | G33: =SUM(G2:G6) -> 1.35 | H33: =SUM(H2:H6) -> 1.7 | I33: =SUM(I2:I6) -> 1 | ... CE33: =SUM(CE2:CE6) -> 1 | CO33: 1110000 | CP33: 16510 | CQ33: 3656 | CR33: 55800 | CS33: 4112 | CT33: 500000 | CU33: 131640 | CV33: 148620 | CX33: =CZ33/$CW$2 -> 0.24323 | CY33: 32 | CZ33: 121615 | DA33: =CZ33-CZ32 -> 3800 | DB33: =CZ33/$CZ$52 -> 0.63054118
A34: 1830 all | B34: =SUM(B2:B7) -> 0.37 | C34: =SUM(C2:C7) -> 0.1 | D34: =SUM(D2:D7) -> 0.4 | E34: =SUM(E2:E7) -> 1 | F34: =SUM(F2:F7) -> 1.25 | G34: =SUM(G2:G7) -> 2.5 | H34: =SUM(H2:H7) -> 2.07 | I34: =SUM(I2:I7) -> 1 | ... CE34: =SUM(CE2:CE7) -> 1 | CO34: 68.699 | CP34: 3.959 | CQ34: 0.671 | CR34: 8.951 | CS34: 0.005 | CT34: 209.677 | CU34: 66.508 | CV34: 57.006 | CX34: =CZ34/$CW$2 -> 0.250832 | CY34: 33 | CZ34: 125416 | DA34: =CZ34-CZ33 -> 3801 | DB34: =CZ34/$CZ$52 -> 0.65024835
A35: 1840 | B35: =SUM(B2:B8) -> 0.37 | C35: =SUM(C2:C8) -> 0.1 | D35: =SUM(D2:D8) -> 0.4 | E35: =SUM(E2:E8) -> 1 | F35: =SUM(F2:F8) -> 1.25 | G35: =SUM(G2:G8) -> 2.5 | H35: =SUM(H2:H8) -> 2.07 | I35: =SUM(I2:I8) -> 1 | ... CE35: =SUM(CE2:CE8) -> 1 | CO35: =CO34/CO33 -> 6.1890991e-05 | CP35: =CP34/CP33 -> 0.00023979406 | CQ35: =CQ34/CQ33 -> 0.00018353392 | CR35: =CR34/CR33 -> 0.00016041219 | CS35: =CS34/CS33 -> 1.2159533e-06 | CT35: =CT34/CT33 -> 0.000419354 | CU35: =CU34/CU33 -> 0.00050522637 | CV35: =CV34/CV33 -> 0.00038356883 | CX35: =CZ35/$CW$2 -> 0.258432 | CY35: 34 | CZ35: 129216 | DA35: =CZ35-CZ34 -> 3800 | DB35: =CZ35/$CZ$52 -> 0.66995033
A36: 1848 | B36: =SUM(B2:B9) -> 0.37 | C36: =SUM(C2:C9) -> 0.1 | D36: =SUM(D2:D9) -> 0.4 | E36: =SUM(E2:E9) -> 1 | F36: =SUM(F2:F9) -> 1.25 | G36: =SUM(G2:G9) -> 2.5 | H36: =SUM(H2:H9) -> 2.07 | I36: =SUM(I2:I9) -> 1 | ... CE36: =SUM(CE2:CE9) -> 1 | CX36: =CZ36/$CW$2 -> 0.266032 | CY36: 35 | CZ36: 133016 | DA36: =CZ36-CZ35 -> 3800 | DB36: =CZ36/$CZ$52 -> 0.68965231
A37: 1850 | B37: =SUM(B2:B10) -> 0.47 | C37: =SUM(C2:C10) -> 0.1 | D37: =SUM(D2:D10) -> 0.45 | E37: =SUM(E2:E10) -> 1 | F37: =SUM(F2:F10) -> 1.25 | G37: =SUM(G2:G10) -> 2.65 | H37: =SUM(H2:H10) -> 2.77 | I37: =SUM(I2:I10) -> 1 | ... CE37: =SUM(CE2:CE10) -> 1.5 | CX37: =CZ37/$CW$2 -> 0.273634 | CY37: 36 | CZ37: 136817 | DA37: =CZ37-CZ36 -> 3801 | DB37: =CZ37/$CZ$52 -> 0.70935948
A38: 1855 | B38: =SUM(B2:B11) -> 0.47 | C38: =SUM(C2:C11) -> 0.1 | D38: =SUM(D2:D11) -> 0.45 | E38: =SUM(E2:E11) -> 1 | F38: =SUM(F2:F11) -> 1.25 | G38: =SUM(G2:G11) -> 2.65 | H38: =SUM(H2:H11) -> 2.77 | I38: =SUM(I2:I11) -> 1 | ... CE38: =SUM(CE2:CE11) -> 1.5 | CX38: =CZ38/$CW$2 -> 0.280834 | CY38: 37 | CZ38: 140417 | DA38: =CZ38-CZ37 -> 3600 | DB38: =CZ38/$CZ$52 -> 0.72802451
A39: 1860 | B39: =SUM(B2:B12) -> 0.47 | C39: =SUM(C2:C12) -> 0.1 | D39: =SUM(D2:D12) -> 0.45 | E39: =SUM(E2:E12) -> 1 | F39: =SUM(F2:F12) -> 1.25 | G39: =SUM(G2:G12) -> 2.65 | H39: =SUM(H2:H12) -> 2.77 | I39: =SUM(I2:I12) -> 1 | ... CE39: =SUM(CE2:CE12) -> 1.5 | CX39: =CZ39/$CW$2 -> 0.288836 | CY39: 38 | CZ39: 144418 | DA39: =CZ39-CZ38 -> 4001 | DB39: =CZ39/$CZ$52 -> 0.74876863
A40: 1870 | B40: =SUM(B2:B13) -> 0.54 | C40: =SUM(C2:C13) -> 0.1 | D40: =SUM(D2:D13) -> 0.5 | E40: =SUM(E2:E13) -> 1 | F40: =SUM(F2:F13) -> 1.25 | G40: =SUM(G2:G13) -> 2.65 | H40: =SUM(H2:H13) -> 2.77 | I40: =SUM(I2:I13) -> 1 | ... CE40: =SUM(CE2:CE13) -> 1.5 | CQ40: Soldier POPs | CR40: Supply | CS40: Score | CU40: 0.15 | CV40: 9.697 | CW40: =CV40/CV41 -> 0.71427519 | CX40: =CZ40/$CW$2 -> 0.296436 | CY40: 39 | CZ40: 148218 | DA40: =CZ40-CZ39 -> 3800 | DB40: =CZ40/$CZ$52 -> 0.76847061
A41: 1872 | B41: =SUM(B2:B14) -> 0.54 | C41: =SUM(C2:C14) -> 0.1 | D41: =SUM(D2:D14) -> 0.5 | E41: =SUM(E2:E14) -> 1 | F41: =SUM(F2:F14) -> 1.25 | G41: =SUM(G2:G14) -> 2.65 | H41: =SUM(H2:H14) -> 2.77 | I41: =SUM(I2:I14) -> 1 | ... CE41: =SUM(CE2:CE14) -> 1.5 | CP41: 56000 | CQ41: 35.8 | CR41: 0.35 | CS41: =CQ41*CR41 -> 12.53 | CU41: 0.35 | CV41: 13.576 | CW41: =CV41/CV40 -> 1.4000206 | CX41: =CZ41/$CW$2 -> 0.304038 | CY41: 40 | CZ41: 152019 | DA41: =CZ41-CZ40 -> 3801 | DB41: =CZ41/$CZ$52 -> 0.78817777
A42: 1875 | B42: =SUM(B2:B15) -> 0.54 | C42: =SUM(C2:C15) -> 0.1 | D42: =SUM(D2:D15) -> 0.5 | E42: =SUM(E2:E15) -> 1 | F42: =SUM(F2:F15) -> 1.25 | G42: =SUM(G2:G15) -> 2.65 | H42: =SUM(H2:H15) -> 2.77 | I42: =SUM(I2:I15) -> 1 | ... CE42: =SUM(CE2:CE15) -> 1.5 | CP42: =CQ41/CP41 -> 0.00063928571 | CU42: 1 | CV42: =CV40/0.15 -> 64.646667 | CX42: =CZ42/$CW$2 -> 0.311638 | CY42: 41 | CZ42: 155819 | DA42: =CZ42-CZ41 -> 3800 | DB42: =CZ42/$CZ$52 -> 0.80787976
A43: 1880 | B43: =SUM(B2:B16) -> 0.54 | C43: =SUM(C2:C16) -> 0.1 | D43: =SUM(D2:D16) -> 0.5 | E43: =SUM(E2:E16) -> 1 | F43: =SUM(F2:F16) -> 1.25 | G43: =SUM(G2:G16) -> 2.8 | H43: =SUM(H2:H16) -> 3.22 | I43: =SUM(I2:I16) -> 1 | ... CE43: =SUM(CE2:CE16) -> 1.5 | CX43: =CZ43/$CW$2 -> 0.31924 | CY43: 42 | CZ43: 159620 | DA43: =CZ43-CZ42 -> 3801 | DB43: =CZ43/$CZ$52 -> 0.82758692
A44: 1890 | B44: =SUM(B2:B17) -> 0.54 | C44: =SUM(C2:C17) -> 0.1 | D44: =SUM(D2:D17) -> 0.5 | E44: =SUM(E2:E17) -> 1 | F44: =SUM(F2:F17) -> 1.25 | G44: =SUM(G2:G17) -> 2.8 | H44: =SUM(H2:H17) -> 3.22 | I44: =SUM(I2:I17) -> 1 | ... CE44: =SUM(CE2:CE17) -> 1.5 | CP44: 502530 | CQ44: 0.6 | CR44: 193.543 | CX44: =CZ44/$CW$2 -> 0.32684 | CY44: 43 | CZ44: 163420 | DA44: =CZ44-CZ43 -> 3800 | DB44: =CZ44/$CZ$52 -> 0.8472889
A45: 1895 | B45: =SUM(B2:B18) -> 0.54 | C45: =SUM(C2:C18) -> 0.1 | D45: =SUM(D2:D18) -> 0.5 | E45: =SUM(E2:E18) -> 1 | F45: =SUM(F2:F18) -> 1.25 | G45: =SUM(G2:G18) -> 2.8 | H45: =SUM(H2:H18) -> 3.22 | I45: =SUM(I2:I18) -> 1 | ... CE45: =SUM(CE2:CE18) -> 1.5 | CP45: 502530 | CQ45: 0.5 | CR45: 161.284 | CX45: =CZ45/$CW$2 -> 0.334442 | CY45: 44 | CZ45: 167221 | DA45: =CZ45-CZ44 -> 3801 | DB45: =CZ45/$CZ$52 -> 0.86699607
A46: 1898 | B46: =SUM(B2:B19) -> 0.54 | C46: =SUM(C2:C19) -> 0.1 | D46: =SUM(D2:D19) -> 0.5 | E46: =SUM(E2:E19) -> 1 | F46: =SUM(F2:F19) -> 1.25 | G46: =SUM(G2:G19) -> 2.8 | H46: =SUM(H2:H19) -> 3.22 | I46: =SUM(I2:I19) -> 1 | ... CE46: =SUM(CE2:CE19) -> 1.5 | CP46: 502530 | CQ46: 1 | CR46: =CR45*2 -> 322.568 | CX46: =CZ46/$CW$2 -> 0.342042 | CY46: 45 | CZ46: 171021 | DA46: =CZ46-CZ45 -> 3800 | DB46: =CZ46/$CZ$52 -> 0.88669805
A47: 1900 | B47: =SUM(B2:B20) -> 0.59 | C47: =SUM(C2:C20) -> 0.1 | D47: =SUM(D2:D20) -> 0.6 | E47: =SUM(E2:E20) -> 1.15 | F47: =SUM(F2:F20) -> 1.25 | G47: =SUM(G2:G20) -> 3.45 | H47: =SUM(H2:H20) -> 3.37 | I47: =SUM(I2:I20) -> 1 | ... CE47: =SUM(CE2:CE20) -> 1.5 | CR47: =CR46/CP46 -> 0.00064188805 | CX47: =CZ47/$CW$2 -> 0.349644 | CY47: 46 | CZ47: 174822 | DA47: =CZ47-CZ46 -> 3801 | DB47: =CZ47/$CZ$52 -> 0.90640522
A48: 1905 | B48: =SUM(B2:B21) -> 0.59 | C48: =SUM(C2:C21) -> 0.1 | D48: =SUM(D2:D21) -> 0.6 | E48: =SUM(E2:E21) -> 1.15 | F48: =SUM(F2:F21) -> 1.25 | G48: =SUM(G2:G21) -> 3.45 | H48: =SUM(H2:H21) -> 3.37 | I48: =SUM(I2:I21) -> 1 | ... CE48: =SUM(CE2:CE21) -> 1.5 | CX48: =CZ48/$CW$2 -> 0.357244 | CY48: 47 | CZ48: 178622 | DA48: =CZ48-CZ47 -> 3800 | DB48: =CZ48/$CZ$52 -> 0.9261072
A49: 1910 | B49: =SUM(B2:B22) -> 0.59 | C49: =SUM(C2:C22) -> 0.1 | D49: =SUM(D2:D22) -> 0.6 | E49: =SUM(E2:E22) -> 1.15 | F49: =SUM(F2:F22) -> 1.25 | G49: =SUM(G2:G22) -> 3.45 | H49: =SUM(H2:H22) -> 3.37 | I49: =SUM(I2:I22) -> 1 | ... CE49: =SUM(CE2:CE22) -> 1.5 | CO49: =CU40*CV41 -> 2.0364 | CX49: =CZ49/$CW$2 -> 0.364846 | CY49: 48 | CZ49: 182423 | DA49: =CZ49-CZ48 -> 3801 | DB49: =CZ49/$CZ$52 -> 0.94581437
A50: 1914 | B50: =SUM(B2:B23) -> 0.59 | C50: =SUM(C2:C23) -> 0.1 | D50: =SUM(D2:D23) -> 0.6 | E50: =SUM(E2:E23) -> 1.15 | F50: =SUM(F2:F23) -> 1.25 | G50: =SUM(G2:G23) -> 3.45 | H50: =SUM(H2:H23) -> 3.37 | I50: =SUM(I2:I23) -> 1 | ... CE50: =SUM(CE2:CE23) -> 1.5 | CO50: =CV40*CU41 -> 3.39395 | CT50: 13.576 | CX50: =CZ50/$CW$2 -> 0.372446 | CY50: 49 | CZ50: 186223 | DA50: =CZ50-CZ49 -> 3800 | DB50: =CZ50/$CZ$52 -> 0.96551635
A51: 1915 | B51: =SUM(B2:B24) -> 0.59 | C51: =SUM(C2:C24) -> 0.1 | D51: =SUM(D2:D24) -> 0.6 | E51: =SUM(E2:E24) -> 1.15 | F51: =SUM(F2:F24) -> 1.25 | G51: =SUM(G2:G24) -> 3.45 | H51: =SUM(H2:H24) -> 3.37 | I51: =SUM(I2:I24) -> 1 | ... CE51: =SUM(CE2:CE24) -> 1.5 | CT51: 9.697 | CU51: =CT51*CT52 -> 1.45455 | CX51: =CZ51/$CW$2 -> 0.380048 | CY51: 50 | CZ51: 190024 | DA51: =CZ51-CZ50 -> 3801 | DB51: =CZ51/$CZ$52 -> 0.98522351
A52: 1919 | B52: =SUM(B2:B25) -> 0.64 | C52: =SUM(C2:C25) -> 0.1 | D52: =SUM(D2:D25) -> 0.6 | E52: =SUM(E2:E25) -> 1.15 | F52: =SUM(F2:F25) -> 1.25 | G52: =SUM(G2:G25) -> 3.45 | H52: =SUM(H2:H25) -> 3.37 | I52: =SUM(I2:I25) -> 1 | ... CE52: =SUM(CE2:CE25) -> 1.5 | CO52: =CO49/CO50 -> 0.60000884 | CT52: 0.15 | CX52: =CZ52/$CW$2 -> 0.385748 | CY52: 51 | CZ52: 192874 | DA52: =CZ52-CZ51 -> 2850 | DB52: =CZ52/$CZ$52 -> 1
CP54: Soldier POPs | CQ54: Supply | CR54: Score | CX54: =CZ54/CZ52 -> 1.0833601 | CZ54: 208952
A55: Date | B55: RGO | C55: POPs | D55: Mobilization | E55: Mechanized Mining | F55: Distribution Channels | G55: Tractors | H55: RGO Output | I55: RGO Throughput | J55: RGO Size | K55: POP Growth | L55: Mobilisation Impact | CP55: 16258 | CQ55: 0.3 | CR55: 4.751 | CS55: =CR55/CQ55 -> 15.836667
A56: 1830 2 row | B56: Coal | C56: 100000 | D56: No | E56: No | F56: No | G56: No | H56: =VLOOKUP($A$56,$A$28:$CE$52,5,0)+INDEX($A$28:$CE$52, MATCH(A56, $A$28:$A$52, 0), MATCH(B56 & " Output", $A$28:$CE$28, 0))+IF(VLOOKUP(B56,B65:C92,2,0)="Mine",VLOOKUP(A56,$A$28:$CE$52,7,0),VLOOKUP(A56,$A$28:$CE$52,8,0))-3 -> 0.85 | I56: =VLOOKUP(A56,$A$28:$CE$52,6,0)-1 -> 0.25 | J56: =VLOOKUP($A$56,$A$28:$CE$52,5,0)+INDEX($A$28:$CE$52, MATCH(A56, $A$28:$A$52, 0), MATCH(B56 & " Size", $A$28:$CE$28, 0)) -> 2 | K56: =VLOOKUP(A56,$A$28:$CE$52,15,0) -> 0.0005 | L56: =VLOOKUP(A56,$A$28:$CE$52,16,0)-1 -> -0.1 | CQ56: =CP55/CQ55 -> 54193.333 | CR56: =CR55/CQ56 -> 8.766761e-05
CP59: Soldier POPs | CQ59: Supply | CR59: Score
CP60: 98168 | CQ60: 0.5 | CR60: =CP60*CQ60/1000 -> 49.084
B64: RGO | C64: Type
B65: Gold | C65: Mine
B66: Precious Goods | C66: Mine
B67: Gems | C67: Mine
B68: Pearls | C68: Mine
B69: Mercury | C69: Mine
B70: Precious Metal | C70: Mine
B71: Slave Trade | C71: Farm
B72: Ivory | C72: Farm
B73: Tropical Wood | C73: Mine
B74: Sulfur | C74: Mine
B75: Oil | C75: Mine
... B92: Opium | C92: Farm

Sheet Colonial RGOs
A1: Colony | B1: Total POPs | C1: % | D1: RGO | E1: Income | G1: Icon | H1: RGO | I1: Mean Good Value | J1: Value | K1: Base Price | L1: Min Price | M1: Max Price
A2: Niger | B2: =SUM(B3:B11) -> 515190 | C2: =SUM(C3:C11) -> 1 | E2: =SUM(E3:E11) -> 46.769615 | H2: Cattle | I2: =J2*K2 -> 3.4 | J2: 1.7 | K2: 2 | L2: =K2*0.5 -> 1 | M2: =K2*1.5 -> 3
A3: Ayuru | B3: 43950 | C3: =B3/$B$2 -> 0.085308333 | D3: Sugar | E3: =B3/40000*VLOOKUP(D3,$H$2:$I$29,2,0) -> 3.516 | H3: Coal | I3: =J3*K3 -> 5.52 | J3: 2.4 | K3: 2.3 | L3: =K3*0.5 -> 1.15 | M3: =K3*1.5 -> 3.45
A4: Gaweye | B4: 83630 | C4: =B4/$B$2 -> 0.16232846 | D4: Cotton | E4: =B4/40000*VLOOKUP(D4,$H$2:$I$29,2,0) -> 7.5267 | H4: Coffee | I4: =J4*K4 -> 3.15 | J4: 1.5 | K4: 2.1 | L4: =K4*0.5 -> 1.05 | M4: =K4*1.5 -> 3.15
A5: Say | B5: 48300 | C5: =B5/$B$2 -> 0.09375182 | D5: Cotton | E5: =B5/40000*VLOOKUP(D5,$H$2:$I$29,2,0) -> 4.347 | H5: Cotton | I5: =J5*K5 -> 3.6 | J5: 1.8 | K5: 2 | L5: =K5*0.5 -> 1 | M5: =K5*1.5 -> 3
A6: Nakoni | B6: 37120 | C6: =B6/$B$2 -> 0.072051088 | D6: Grain | E6: =B6/40000*VLOOKUP(D6,$H$2:$I$29,2,0) -> 3.47072 | H6: Sugar | I6: =J6*K6 -> 3.2 | J6: 1 | K6: 3.2 | L6: =K6*0.5 -> 1.6 | M6: =K6*1.5 -> 4.8
A7: Tshibiri | B7: 73880 | C7: =B7/$B$2 -> 0.1434034 | D7: Cotton | E7: =B7/40000*VLOOKUP(D7,$H$2:$I$29,2,0) -> 6.6492 | H7: Dye | I7: =J7*K7 -> 2.64 | J7: 0.22 | K7: 12 | L7: =K7*0.5 -> 6 | M7: =K7*1.5 -> 18
A8: Zinder | B8: 99070 | C8: =B8/$B$2 -> 0.19229799 | D8: Grain | E8: =B8/40000*VLOOKUP(D8,$H$2:$I$29,2,0) -> 9.263045 | H8: Fish | I8: =J8*K8 -> 3.15 | J8: 2.1 | K8: 1.5 | L8: =K8*0.5 -> 0.75 | M8: =K8*1.5 -> 2.25
A9: Kufe | B9: 71540 | C9: =B9/$B$2 -> 0.13886139 | D9: Cattle | E9: =B9/40000*VLOOKUP(D9,$H$2:$I$29,2,0) -> 6.0809 | H9: Grain | I9: =J9*K9 -> 3.74 | J9: 1.7 | K9: 2.2 | L9: =K9*0.5 -> 1.1 | M9: =K9*1.5 -> 3.3
A10: Agadez | B10: 45950 | C10: =B10/$B$2 -> 0.089190396 | D10: Wool | E10: =B10/40000*VLOOKUP(D10,$H$2:$I$29,2,0) -> 3.8598 | H10: Iron | I10: =J10*K10 -> 7 | J10: 2 | K10: 3.5 | L10: =K10*0.5 -> 1.75 | M10: =K10*1.5 -> 5.25
A11: Njiekime | B11: 11750 | C11: =B11/$B$2 -> 0.02280712 | D11: Iron | E11: =B11/40000*VLOOKUP(D11,$H$2:$I$29,2,0) -> 2.05625 | H11: Oil | I11: =J11*K11 -> 12 | J11: 1 | K11: 12 | L11: =K11*0.5 -> 6 | M11: =K11*1.5 -> 18
H12: Opium | I12: =J12*K12 -> 2.24 | J12: 0.7 | K12: 3.2 | L12: =K12*0.5 -> 1.6 | M12: =K12*1.5 -> 4.8
A13: Test | B13: =32200*(1-0.1+0.031) -> 29978.2 | D13: Cattle | E13: =B13/40000*VLOOKUP(D13,$H$2:$I$29,2,0) -> 2.548147 | H13: Fruit | I13: =J13*K13 -> 4.86 | J13: 2.7 | K13: 1.8 | L13: =K13*0.5 -> 0.9 | M13: =K13*1.5 -> 2.7
H14: Silver | I14: =J14*K14 -> 45 | J14: 2.25 | K14: 20 | L14: =K14*0.5 -> 10 | M14: =K14*1.5 -> 30
H15: Gold | I15: =J15*K15 -> 60 | J15: 3 | K15: 20 | L15: =K15*0.5 -> 10 | M15: =K15*1.5 -> 30
H16: Precious Goods | I16: =J16*K16 -> 54 | J16: 3 | K16: 18 | L16: =K16*0.5 -> 9 | M16: =K16*1.5 -> 27
H17: Gems | I17: =J17*K17 -> 54 | J17: 3 | K17: 18 | L17: =K17*0.5 -> 9 | M17: =K17*1.5 -> 27
H18: Pearls | I18: =J18*K18 -> 54 | J18: 3 | K18: 18 | L18: =K18*0.5 -> 9 | M18: =K18*1.5 -> 27
H19: Ivory | I19: =J19*K19 -> 30 | J19: 3 | K19: 10 | L19: =K19*0.5 -> 5 | M19: =K19*1.5 -> 15
H20: Slave Trade | I20: =J20*K20 -> 39 | J20: 3 | K20: 13 | L20: =K20*0.5 -> 6.5 | M20: =K20*1.5 -> 19.5
H21: Mercury | I21: =J21*K21 -> 54 | J21: 3 | K21: 18 | L21: =K21*0.5 -> 9 | M21: =K21*1.5 -> 27
H22: Rubber | I22: =J22*K22 -> 5.25 | J22: 0.75 | K22: 7 | L22: =K22*0.5 -> 3.5 | M22: =K22*1.5 -> 10.5
H23: Wool | I23: =J23*K23 -> 3.36 | J23: 4.8 | K23: 0.7 | L23: =K23*0.5 -> 0.35 | M23: =K23*1.5 -> 1.05
H24: Silk | I24: =J24*K24 -> 2.5 | J24: 0.25 | K24: 10 | L24: =K24*0.5 -> 5 | M24: =K24*1.5 -> 15
H25: Sulphur | I25: =J25*K25 -> 18 | J25: 3 | K25: 6 | L25: =K25*0.5 -> 3 | M25: =K25*1.5 -> 9
... H29: Tropical Wood | I29: =J29*K29 -> 21.6 | J29: 4 | K29: 5.4 | L29: =K29*0.5 -> 2.7 | M29: =K29*1.5 -> 8.1
